Workbook
Name Inv_Cap: #REF!
Name NOPLAT: #REF!
Name One: #REF!
Name Products: #REF!
Name Rev: #REF!

Sheet Cover
B7: PayPal
B9: Leveraged Buyout Model
B11: =TODAY() -> 46208
B13: By: Tyler Spencer
B15: RETURNS BY SCENARIO | F15: VALUATION
B18: Scenario | C18: MOIC | D18: IRR | F18: Methodology | J18: Low | K18: High
B19: Best Case (Bull) | C19: 4.38 | D19: 0.343 | F19: DCF | J19: ='Summary Outputs'!M47 -> 54.894513 | K19: ='Summary Outputs'!O47 -> 66.060539
B20: Base Case | C20: 2.48 | D20: 0.199 | F20: Precedent Transactions | J20: ='Summary Outputs'!M48 -> 100.73201 | K20: ='Summary Outputs'!O48 -> 115.61964
B21: Worst Case (Bear) | C21: 0.97 | D21: -0.005 | F21: Comparable Companies | J21: ='Summary Outputs'!M49 -> 77.949123 | K21: ='Summary Outputs'!O49 -> 90.012909
B22: ="Currently running: ("&CHOOSE(Scenarios!$C$6,Scenarios!$B$10,Scenarios!$B$11,Scenarios!$B$12)&"): MOIC "&TEXT('LBO Returns'!$D$16,"0.00x")&", IRR "&TEXT('LBO Returns'!$E$16,"0.0%") -> Currently running: (Base Case): MOIC 2.48x, IRR 19.9% | F22: LBO Range | J22: ='Summary Outputs'!M50 -> 41.902774 | K22: ='Summary Outputs'!O50 -> 53.317619
F23: ="Currently running: ("&CHOOSE(Scenarios!$C$6,Scenarios!$B$10,Scenarios!$B$11,Scenarios!$B$12)&"): MOIC "&TEXT('LBO Returns'!$D$16,"0.00x")&", IRR "&TEXT('LBO Returns'!$E$16,"0.0%") -> Currently running: (Base Case): MOIC 2.48x, IRR 19.9%
B24: Investment Thesis | F24: ="Max sponsor bid for 15% IRR: "&TEXT(K22,"$0.00") -> Max sponsor bid for 15% IRR: $53.32
B25: =IF('LBO Returns'!$E$16>0.149,"Clears sponsor return hurdle","Below sponsor return hurdle") -> Clears sponsor return hurdle | F25: ="Max LBO price premium compared to current market: "&TEXT((K22/Assumptions!N7)-1,"0.0%") -> Max LBO price premium compared to current market: 17.3%
B26: =IF(Cover!K22<MIN(Cover!J19,Cover!J20,Cover!J21),"Market premium below threshold","Market premium clears threshold") -> Market premium below threshold

Sheet Summary Outputs
O1: ="CURRENTLY RUNNING: "&UPPER(CHOOSE(Scenarios!$C$6,Scenarios!B10,Scenarios!B11,Scenarios!B12))&" SCENARIO" -> CURRENTLY RUNNING: BASE CASE SCENARIO
B2: =Cover!B7 -> PayPal
B3: Summary Outputs
C5: ="SUMMARY VALUES FOR "&UPPER(CHOOSE(Scenarios!$C$6,Scenarios!B10,Scenarios!B11,Scenarios!B12))&" SCENARIO" -> SUMMARY VALUES FOR BASE CASE SCENARIO
K6: Projected
D7: ($ Millions) | F7: Trend | H7: =IS!E6 -> 2023 | I7: =IS!F6 -> 2024 | J7: =IS!G6 -> 2025 | K7: =IS!H6 -> 2026 | L7: =IS!I6 -> 2027 | M7: =IS!J6 -> 2028 | N7: =IS!K6 -> 2029 | O7: =IS!L6 -> 2030
D9: Income Statement Items
D11: Net Revenue | H11: =IS!E8 -> 29771 | I11: =IS!F8 -> 31797 | J11: =IS!G8 -> 33172 | K11: =IS!H8 -> 34315.686 | L11: =IS!I8 -> 35688.889 | M11: =IS!J8 -> 37318.556 | N11: =IS!K8 -> 39243.381 | O11: =IS!L8 -> 41267.006
D12: Growth | I12: =(I11/H11)-1 -> 0.068052803 | J12: =(J11/I11)-1 -> 0.043243073 | K12: =(K11/J11)-1 -> 0.034477453 | L12: =(L11/K11)-1 -> 0.04001676 | M12: =(M11/L11)-1 -> 0.045663156 | N12: =(N11/M11)-1 -> 0.05157824 | O12: =(O11/N11)-1 -> 0.051566007
D15: EBITDA | H15: =IS!E28 -> 6100 | I15: =IS!F28 -> 6357 | J15: =IS!G28 -> 7028 | K15: =IS!H28 -> 7146.835 | L15: =IS!I28 -> 7104.3207 | M15: =IS!J28 -> 7245.4198 | N15: =IS!K28 -> 7545.2307 | O15: =IS!L28 -> 7904.1752
D16: Margin | H16: =H15/H11 -> 0.20489738 | I16: =I15/I11 -> 0.19992452 | J16: =J15/J11 -> 0.21186543 | K16: =K15/K11 -> 0.20826729 | L16: =L15/L11 -> 0.19906254 | M16: =M15/M11 -> 0.19415059 | N16: =N15/N11 -> 0.1922676 | O16: =O15/O11 -> 0.1915374
D17: Growth | I17: =(I15/H15)-1 -> 0.042131148 | J17: =(J15/I15)-1 -> 0.10555293 | K17: =(K15/J15)-1 -> 0.016908788 | L17: =(L15/K15)-1 -> -0.0059486872 | M17: =(M15/L15)-1 -> 0.019861029 | N17: =(N15/M15)-1 -> 0.041379365 | O17: =(O15/N15)-1 -> 0.04757237
D20: Net Income | H20: =IS!E25 -> 4246 | I20: =IS!F25 -> 4147 | J20: =IS!G25 -> 5233 | K20: =IS!H25 -> 5255.3709 | L20: =IS!I25 -> 5168.7406 | M20: =IS!J25 -> 5227.7721 | N20: =IS!K25 -> 5453.3605 | O20: =IS!L25 -> 5705.2741
D21: Margin | H21: =H20/H11 -> 0.14262201 | I21: =I20/I11 -> 0.13042111 | J21: =J20/J11 -> 0.15775353 | K21: =K20/K11 -> 0.15314777 | L21: =L20/L11 -> 0.14482773 | M21: =M20/M11 -> 0.14008506 | N21: =N20/N11 -> 0.13896255 | O21: =O20/O11 -> 0.13825268
D22: Growth | I22: =(I20/H20)-1 -> -0.023316062 | J22: =(J20/I20)-1 -> 0.26187605 | K22: =(K20/J20)-1 -> 0.0042749697 | L22: =(L20/K20)-1 -> -0.016484142 | M22: =(M20/L20)-1 -> 0.011420852 | N22: =(N20/M20)-1 -> 0.043151933 | O22: =(O20/N20)-1 -> 0.046194191
D24: LBO Credit Statistics
D25: Total Debt | K25: ='LBO Debt Schedule'!H89 -> 26385.01 | L25: ='LBO Debt Schedule'!I89 -> 22348.578 | M25: ='LBO Debt Schedule'!J89 -> 18127.413 | N25: ='LBO Debt Schedule'!K89 -> 13587.376 | O25: ='LBO Debt Schedule'!L89 -> 8614.2824
D26: Net Debt | K26: ='LBO Debt Schedule'!H90 -> 25385.01 | L26: ='LBO Debt Schedule'!I90 -> 21348.578 | M26: ='LBO Debt Schedule'!J90 -> 17127.413 | N26: ='LBO Debt Schedule'!K90 -> 12587.376 | O26: ='LBO Debt Schedule'!L90 -> 7614.2824
D27: Gross Leverage | K27: ='LBO Debt Schedule'!H91 -> 3.6918454 | L27: ='LBO Debt Schedule'!I91 -> 3.1457727 | M27: ='LBO Debt Schedule'!J91 -> 2.5019134 | N27: ='LBO Debt Schedule'!K91 -> 1.80079 | O27: ='LBO Debt Schedule'!L91 -> 1.0898395
D28: Net Leverage | K28: ='LBO Debt Schedule'!H92 -> 3.5519234 | L28: ='LBO Debt Schedule'!I92 -> 3.0050133 | M28: ='LBO Debt Schedule'!J92 -> 2.3638952 | N28: ='LBO Debt Schedule'!K92 -> 1.668256 | O28: ='LBO Debt Schedule'!L92 -> 0.96332409
D29: Interest Coverage | K29: ='LBO Debt Schedule'!H93 -> 3.9472369 | L29: ='LBO Debt Schedule'!I93 -> 4.6524269 | M29: ='LBO Debt Schedule'!J93 -> 5.8134091 | N29: ='LBO Debt Schedule'!K93 -> 7.7362735 | O29: ='LBO Debt Schedule'!L93 -> 11.339523
C32: LBO EQUITY VALUE CREATION | K32: DCF VALUATION
C33: Component | H33: $mm
C35: Entry Equity | H35: =LBO!D48 -> 19244.94 | N35: Perpetuity | O35: EBITDA
C36: Change in EBITDA | H36: =('LBO Exit Valuation'!G8 - LBO!E10) * LBO!E22 -> 8065.2262 | K36: EV | N36: =DCF!C91 -> 55213.605 | O36: =DCF!D91 -> 53479.884
C37: Change in Multiple | H37: =('LBO Exit Valuation'!G7 - LBO!E22) * 'LBO Exit Valuation'!G8 -> 0 | K37: Net debt | N37: =DCF!C92 -> -3369 | O37: =DCF!D92 -> -3369
C38: Debt Paydown | H38: =(SUM(LBO!D43:D47) - ('LBO Debt Schedule'!L66)) -> 21769.718 | K38: Equity value | N38: =N36-N37 -> 58582.605 | O38: =O36-O37 -> 56848.884
C39: Less: Fees | H39: =-LBO!D37 -> -1364.94 | K39: Shares outstanding | N39: =DCF!C94 -> 952.421 | O39: =DCF!D94 -> 952.421
C40: Exit Equity | H40: ='LBO Exit Valuation'!G19 -> 47714.944 | K40: Equity value/ share | N40: =N38/N39 -> 61.509149 | O40: =O38/O39 -> 59.688818
C41: Check | H41: =SUM(H35:H39)-H40 -> 0
C43: VALUATION SUMMARY
L46: Methodology | M46: Low | N46: Difference | O46: High
C47: ="DCF Value at "&TEXT(DCF!D122,"0.0x")&"-"&TEXT(DCF!H122,"0.0x")&" Exit EBITDA Range at "&TEXT(DCF!C125,"0.0%")&" WACC" -> DCF Value at 6.0x-8.0x Exit EBITDA Range at 9.2% WACC | L47: DCF | M47: =DCF!D166 -> 54.894513 | N47: =O47-M47 -> 11.166026 | O47: =DCF!F166 -> 66.060539
C48: ="Implied precedent transaction value at "&TEXT(Precedents!F81,"0.0x")&"-"&TEXT(Precedents!E81,"0.0x")&" based on LTM EBITDA" -> Implied precedent transaction value at 13.7x-15.8x based on LTM EBITDA | L48: Precedents | M48: =Precedents!F87 -> 100.73201 | N48: =O48-M48 -> 14.88763 | O48: =Precedents!E87 -> 115.61964
C49: ="Implied comparable company value at "&TEXT(Comps!M48,"0.0x")&"-"&TEXT(Comps!M47,"0.0x")&" based on LTM EBITDA" -> Implied comparable company value at 10.5x-12.2x based on LTM EBITDA | L49: Comparables | M49: =Comps!M58 -> 77.949123 | N49: =O49-M49 -> 12.063786 | O49: =Comps!M64 -> 90.012909
C50: ="Offer value/share at "&TEXT('LBO Returns'!F25,"0.0%")&" - "&TEXT('LBO Returns'!I25,"0.0%")&" IRR" -> Offer value/share at 15.0% - 30.0% IRR | L50: LBO | M50: ='LBO Returns'!I28 -> 41.902774 | N50: =O50-M50 -> 11.414845 | O50: ='LBO Returns'!F28 -> 53.317619
C51: 52 Week Market High/Low | L51: 52 Wk Range | M51: 38.46 | N51: =O51-M51 -> 41.04 | O51: 79.5

Sheet Assumptions
N1: ="CURRENTLY RUNNING: "&UPPER(CHOOSE(Scenarios!$C$6,Scenarios!B10,Scenarios!B11,Scenarios!B12))&" SCENARIO" -> CURRENTLY RUNNING: BASE CASE SCENARIO
B2: =Cover!B7 -> PayPal
B3: Inputs and Assumptions
C5: GENERAL | J5: EQUITY
C7: - | D7: First year of forecast in financial model: | G7: 2026 | J7: Most Recent Stock Price | N7: 45.47
J8: Stock Price Date | N8: 46208
C9: - | D9: Three scenarios have been used for Total Payment Volume (TPV), | J9: Shares Outstanding 1/28/26 (in MM) | N9: 920.664
D10: Take Rate Compression, Other Value Added Services, Transaction | J10: LTM Average Share Price | N10: 58.49
D11: Expense, Transaction and Credit Losses, and Technology and | J11: Outstanding RSU's | N11: 31.757
D12: Development | J12: Dividend Per Share | N12: 0.56
C16: SCENARIO CASES | J16: REVENUE DRIVERS
C18: - | D18: The Total Payment Volume cases are as follows:
C19: Pricing Case | J19: Total Payment Volume Growth | N19: =Scenarios!H11 -> 0.06
C20: Base Case | E20: Research Forecast | J20: Take Rate Compression Year 1 | N20: =Scenarios!H14 -> -0.0004
C21: Best Case | F21: 0.02 | J21: Other Value-Added Services Growth | N21: =Scenarios!H20 -> 0.04
C22: Worst Case | F22: -0.02
C25: COSTS | J25: INTEREST RATES
C27: Driver
C28: Transaction Expenses | F28: % of TPV | H28: =Scenarios!H26 -> 0.0089 | J28: Interest earned on Cash balances: | N28: 0.03
C29: Transaction & Credit Losses | F29: % of TPV | H29: =Scenarios!H32 -> 0.00096 | J29: Interest rate on Bank Revolver:
C30: Customer Support & Operations | F30: % of rev | H30: 0.051 | J30: Interest rate on Senior Secured Term Debt: | N30: 0.039
C31: Sales & Marketing | F31: % of rev | H31: 0.069 | J31: Yield on customer balances: | N31: 0.032
C32: Technology & Development Growth | F32: % | H32: =Scenarios!H38 -> 0.03 | J32: Customer funds balance growth: | N32: 0.03
C33: General & Administrative | F33: % | H33: 0.02
C34: Stock-based compensation | F34: % of rev | H34: 0.034
C37: Capex & D&A | J37: TAXES
C39: Capital Expenditures | F39: % of rev | H39: 0.024 | J39: Tax rate assumed in the model: | N39: 0.21
C40: D&A | F40: % of capex
C42: Debt Repayment | J42: Circuit Breaker & Other
C44: Year | J44: Circuit Breaker | N44: OFF
D45: 2026 | F45: 10-K FY 2025 p. 105 | H45: 1397
D46: 2027 | F46: 10-K FY 2025 p. 105 | H46: 1075 | J46: Minimum cash of $1,000M assumes upstream distributions
D47: 2028 | F47: 10-K FY 2025 p. 105 | H47: 1137 | J47: from regulated subsidiaries are feasible; actual sweepable cash may
D48: 2029 | F48: 10-K FY 2025 p. 105 | H48: 1500 | J48: be lower due to money-transmitter licensing requirements at
D49: 2030 | F49: 10-K FY 2025 p. 105 | H49: 1000 | J49: PayPal, Inc. (FY2025 10-K pp. 10, 44).
C54: OTHER ASSUMPTIONS | H54: 2024 | I54: =H54+1 -> 2025 | J54: =I54+1 -> 2026 | K54: =J54+1 -> 2027 | L54: =K54+1 -> 2028 | M54: =L54+1 -> 2029 | N54: =M54+1 -> 2030
C57: Take Rate Compression | G57: % | J57: -0.0004 | K57: -0.0003 | L57: -0.0002 | M57: -0.0001 | N57: -0.0001
C59: Capital Expenditures | G59: MM | J59: =$H$39*'Revenue Build'!H11 -> 823.57647 | K59: =$H$39*'Revenue Build'!I11 -> 856.53333 | L59: =$H$39*'Revenue Build'!J11 -> 895.64534 | M59: =$H$39*'Revenue Build'!K11 -> 941.84115 | N59: =$H$39*'Revenue Build'!L11 -> 990.40814
C61: Income Tax
D62: Reduction in EBT for timing differences | G62: MM | H62: =231/$N$39 -> 1100 | I62: =217/$N$39 -> 1033.3333 | J62: =J65/$N$39 -> 1144.4047 | K62: =K65/$N$39 -> 759.74868 | L62: =L65/$N$39 -> 504.38283 | M62: =M65/$N$39 -> 334.85025 | N62: =N65/$N$39 -> 222.30077
D63: Capitalized R&D DTA, year-end | G63: MM | H63: 1077 | I63: 715 | J63: =I63*(1-$I$64) -> 474.67502 | K63: =J63*(1-$I$64) -> 315.1278 | L63: =K63*(1-$I$64) -> 209.20741 | M63: =L63*(1-$I$64) -> 138.88885 | N63: =M63*(1-$I$64) -> 92.205693
D64: Annual reversal rate (% of prior-year DTA) | I64: =(H63-I63)/H63 -> 0.33611885
D65: Annual DTA reversal | G65: MM | J65: =I63-J63 -> 240.32498 | K65: =J63-K63 -> 159.54722 | L65: =K63-L63 -> 105.92039 | M65: =L63-M63 -> 70.318553 | N65: =M63-N63 -> 46.683162
C67: Working Capital Days
D68: Accounts Receivable | G68: days | H68: 11.3 | I68: 9.2 | J68: =I68 -> 9.2 | K68: =J68 -> 9.2 | L68: =K68 -> 9.2 | M68: =L68 -> 9.2 | N68: =M68 -> 9.2
D69: Prepaid Expenses | G69: days | H69: 32.2 | I69: 34.4 | J69: =I69 -> 34.4 | K69: =J69 -> 34.4 | L69: =K69 -> 34.4 | M69: =L69 -> 34.4 | N69: =M69 -> 34.4
D70: Accounts Payable | G70: days | H70: 4.4 | I70: 4.5 | J70: =I70 -> 4.5 | K70: =J70 -> 4.5 | L70: =K70 -> 4.5 | M70: =L70 -> 4.5 | N70: =M70 -> 4.5
D71: Other Liabilities | G71: days | H71: 85.2 | I71: 86.7 | J71: =I71 -> 86.7 | K71: =J71 -> 86.7 | L71: =K71 -> 86.7 | M71: =L71 -> 86.7 | N71: =M71 -> 86.7
C73: LTM Revenue | G73: MM | J73: 33734
C74: LTM EBITDA | G74: MM | J74: 6752

Sheet Scenarios
L1: ="CURRENTLY RUNNING: "&UPPER(CHOOSE(Scenarios!$C$6,Scenarios!B10,Scenarios!B11,Scenarios!B12))&" SCENARIO" -> CURRENTLY RUNNING: BASE CASE SCENARIO
B2: =Cover!B7 -> PayPal
B3: Scenario Analysis
H5: Projected
B6: Scenario Switch | C6: 2 | H6: ='Equity Schedule'!H6 -> 2026 | I6: ='Equity Schedule'!I6 -> 2027 | J6: ='Equity Schedule'!J6 -> 2028 | K6: ='Equity Schedule'!K6 -> 2029 | L6: ='Equity Schedule'!L6 -> 2030
B8: Total Payment Volume (TPV) | H8: =CHOOSE($C$6,H10,H11,H12) -> 0.06 | I8: =CHOOSE($C$6,I10,I11,I12) -> 0.06 | J8: =CHOOSE($C$6,J10,J11,J12) -> 0.06 | K8: =CHOOSE($C$6,K10,K11,K12) -> 0.06 | L8: =CHOOSE($C$6,L10,L11,L12) -> 0.06
B10: Best Case | C10: 0.02 | H10: =H11+$C$10 -> 0.08 | I10: =I11+$C$10 -> 0.08 | J10: =J11+$C$10 -> 0.08 | K10: =K11+$C$10 -> 0.08 | L10: =L11+$C$10 -> 0.08
B11: Base Case | H11: 0.06 | I11: 0.06 | J11: 0.06 | K11: 0.06 | L11: 0.06
B12: Worst Case | C12: -0.02 | H12: =H11+$C$12 -> 0.04 | I12: =I11+$C$12 -> 0.04 | J12: =J11+$C$12 -> 0.04 | K12: =K11+$C$12 -> 0.04 | L12: =L11+$C$12 -> 0.04
B14: Take Rate Compression | H14: =CHOOSE($C$6,H16,H17,H18) -> -0.0004 | I14: =CHOOSE($C$6,I16,I17,I18) -> -0.0003 | J14: =CHOOSE($C$6,J16,J17,J18) -> -0.0002 | K14: =CHOOSE($C$6,K16,K17,K18) -> -0.0001 | L14: =CHOOSE($C$6,L16,L17,L18) -> -0.0001
B16: Best Case | C16: 5e-05 | H16: =H17+$C$16 -> -0.00035 | I16: =I17+$C$16 -> -0.00025 | J16: =J17+$C$16 -> -0.00015 | K16: =K17+$C$16 -> -5e-05 | L16: =L17+$C$16 -> -5e-05
B17: Base Case | H17: =Assumptions!J57 -> -0.0004 | I17: =Assumptions!K57 -> -0.0003 | J17: =Assumptions!L57 -> -0.0002 | K17: =Assumptions!M57 -> -0.0001 | L17: =Assumptions!N57 -> -0.0001
B18: Worst Case | C18: -5e-05 | H18: =H17+$C$18 -> -0.00045 | I18: =I17+$C$18 -> -0.00035 | J18: =J17+$C$18 -> -0.00025 | K18: =K17+$C$18 -> -0.00015 | L18: =L17+$C$18 -> -0.00015
B20: Other Value-Added Services, ex-interest | H20: =CHOOSE($C$6,H22,H23,H24) -> 0.04 | I20: =CHOOSE($C$6,I22,I23,I24) -> 0.04 | J20: =CHOOSE($C$6,J22,J23,J24) -> 0.04 | K20: =CHOOSE($C$6,K22,K23,K24) -> 0.04 | L20: =CHOOSE($C$6,L22,L23,L24) -> 0.04
B22: Best Case | C22: 0.03 | H22: =H23+$C$22 -> 0.07 | I22: =I23+$C$22 -> 0.07 | J22: =J23+$C$22 -> 0.07 | K22: =K23+$C$22 -> 0.07 | L22: =L23+$C$22 -> 0.07
B23: Base Case | H23: 0.04 | I23: 0.04 | J23: 0.04 | K23: 0.04 | L23: 0.04
B24: Worst Case | C24: -0.03 | H24: =H23+$C$24 -> 0.01 | I24: =I23+$C$24 -> 0.01 | J24: =J23+$C$24 -> 0.01 | K24: =K23+$C$24 -> 0.01 | L24: =L23+$C$24 -> 0.01
B26: Transaction Expense | H26: =CHOOSE($C$6,H28,H29,H30) -> 0.0089 | I26: =CHOOSE($C$6,I28,I29,I30) -> 0.0089 | J26: =CHOOSE($C$6,J28,J29,J30) -> 0.0089 | K26: =CHOOSE($C$6,K28,K29,K30) -> 0.0089 | L26: =CHOOSE($C$6,L28,L29,L30) -> 0.0089
B28: Best Case | C28: -0.00025 | H28: =H29+$C$28 -> 0.00865 | I28: =I29+$C$28 -> 0.00865 | J28: =J29+$C$28 -> 0.00865 | K28: =K29+$C$28 -> 0.00865 | L28: =L29+$C$28 -> 0.00865
B29: Base Case | H29: 0.0089 | I29: 0.0089 | J29: 0.0089 | K29: 0.0089 | L29: 0.0089
B30: Worst Case | C30: 0.00025 | H30: =H29+$C$30 -> 0.00915 | I30: =I29+$C$30 -> 0.00915 | J30: =J29+$C$30 -> 0.00915 | K30: =K29+$C$30 -> 0.00915 | L30: =L29+$C$30 -> 0.00915
B32: Transaction and Credit Losses | H32: =CHOOSE($C$6,H34,H35,H36) -> 0.00096 | I32: =CHOOSE($C$6,I34,I35,I36) -> 0.00096 | J32: =CHOOSE($C$6,J34,J35,J36) -> 0.00096 | K32: =CHOOSE($C$6,K34,K35,K36) -> 0.00096 | L32: =CHOOSE($C$6,L34,L35,L36) -> 0.00096
B34: Best Case | C34: -0.0001 | H34: =H35+$C$34 -> 0.00086 | I34: =I35+$C$34 -> 0.00086 | J34: =J35+$C$34 -> 0.00086 | K34: =K35+$C$34 -> 0.00086 | L34: =L35+$C$34 -> 0.00086
B35: Base Case | H35: 0.00096 | I35: 0.00096 | J35: 0.00096 | K35: 0.00096 | L35: 0.00096
B36: Worst Case | C36: 0.0001 | H36: =H35+$C$36 -> 0.00106 | I36: =I35+$C$36 -> 0.00106 | J36: =J35+$C$36 -> 0.00106 | K36: =K35+$C$36 -> 0.00106 | L36: =L35+$C$36 -> 0.00106
B38: Technology and Development | H38: =CHOOSE($C$6,H40,H41,H42) -> 0.03 | I38: =CHOOSE($C$6,I40,I41,I42) -> 0.03 | J38: =CHOOSE($C$6,J40,J41,J42) -> 0.03 | K38: =CHOOSE($C$6,K40,K41,K42) -> 0.03 | L38: =CHOOSE($C$6,L40,L41,L42) -> 0.03
B40: Best Case | C40: -0.01 | H40: =H41+$C$40 -> 0.02 | I40: =I41+$C$40 -> 0.02 | J40: =J41+$C$40 -> 0.02 | K40: =K41+$C$40 -> 0.02 | L40: =L41+$C$40 -> 0.02
B41: Base Case | H41: 0.03 | I41: 0.03 | J41: 0.03 | K41: 0.03 | L41: 0.03
B42: Worst Case | C42: 0.01 | H42: =H41+$C$42 -> 0.04 | I42: =I41+$C$42 -> 0.04 | J42: =J41+$C$42 -> 0.04 | K42: =K41+$C$42 -> 0.04 | L42: =L41+$C$42 -> 0.04
B44: LBO Exit Multiple | H44: =CHOOSE($C$6,H46,H47,H48) -> 7 | I44: =CHOOSE($C$6,I46,I47,I48) -> 7 | J44: =CHOOSE($C$6,J46,J47,J48) -> 7 | K44: =CHOOSE($C$6,K46,K47,K48) -> 7 | L44: =CHOOSE($C$6,L46,L47,L48) -> 7
B46: Best Case | C46: 1 | H46: =H47+$C$46 -> 8 | I46: =I47+$C$46 -> 8 | J46: =J47+$C$46 -> 8 | K46: =K47+$C$46 -> 8 | L46: =L47+$C$46 -> 8
B47: Base Case | H47: 7 | I47: 7 | J47: 7 | K47: 7 | L47: 7
B48: Worst Case | C48: -1 | H48: =H47+$C$48 -> 6 | I48: =I47+$C$48 -> 6 | J48: =J47+$C$48 -> 6 | K48: =K47+$C$48 -> 6 | L48: =L47+$C$48 -> 6

Sheet Revenue Build
L1: ="CURRENTLY RUNNING: "&UPPER(CHOOSE(Scenarios!$C$6,Scenarios!B10,Scenarios!B11,Scenarios!B12))&" SCENARIO" -> CURRENTLY RUNNING: BASE CASE SCENARIO
B2: =Cover!$B$7 -> PayPal
B3: Revenue Build
B4: ($ Millions)
H5: Projected
E6: =F6-1 -> 2023 | F6: =G6-1 -> 2024 | G6: 2025 | H6: =G6+1 -> 2026 | I6: =H6+1 -> 2027 | J6: =I6+1 -> 2028 | K6: =J6+1 -> 2029 | L6: =K6+1 -> 2030
B8: Revenue by Service
C9: Transaction Revenue | E9: =E16 -> 26857 | F9: =F16 -> 28842 | G9: =G16 -> 29798 | H9: =H16 -> 30826.92 | I9: =I16 -> 32073.162 | J9: =J16 -> 33571.168 | K9: =K16 -> 35359.455 | L9: =L16 -> 37241.48
C10: Other Value-Added Services | E10: =E19 -> 2914 | F10: =F19 -> 2955 | G10: =G19 -> 3374 | H10: =H19 -> 3488.7661 | I10: =I19 -> 3615.7267 | J10: =J19 -> 3747.388 | K10: =K19 -> 3883.9267 | L10: =L19 -> 4025.5263
C11: Total | E11: =SUM(E9:E10) -> 29771 | F11: =SUM(F9:F10) -> 31797 | G11: =SUM(G9:G10) -> 33172 | H11: =SUM(H9:H10) -> 34315.686 | I11: =SUM(I9:I10) -> 35688.889 | J11: =SUM(J9:J10) -> 37318.556 | K11: =SUM(K9:K10) -> 39243.381 | L11: =SUM(L9:L10) -> 41267.006
B13: Transaction Revenue
C14: Total Payment Volume (TPV) | E14: 1527000 | F14: 1680000 | G14: 1790000 | H14: =G14*(1+Assumptions!N19) -> 1897400 | I14: =H14*(1+Scenarios!I8) -> 2011244 | J14: =I14*(1+Scenarios!J8) -> 2131918.6 | K14: =J14*(1+Scenarios!K8) -> 2259833.8 | L14: =K14*(1+Scenarios!L8) -> 2395423.8
C15: Take rate | E15: =E16/E14 -> 0.017588081 | F15: =F16/F14 -> 0.017167857 | G15: =G16/G14 -> 0.016646927 | H15: =G15+Scenarios!H14 -> 0.016246927 | I15: =H15+Scenarios!I14 -> 0.015946927 | J15: =I15+Scenarios!J14 -> 0.015746927 | K15: =J15+Scenarios!K14 -> 0.015646927 | L15: =K15+Scenarios!L14 -> 0.015546927
C16: Revenue | E16: 26857 | F16: 28842 | G16: 29798 | H16: =H14*H15 -> 30826.92 | I16: =I14*I15 -> 32073.162 | J16: =J14*J15 -> 33571.168 | K16: =K14*K15 -> 35359.455 | L16: =L14*L15 -> 37241.48
B18: Other Value-Added Services
C19: Total OVAS Revenue | E19: 2914 | F19: 2955 | G19: 3374 | H19: =H23+H24 -> 3488.7661 | I19: =I23+I24 -> 3615.7267 | J19: =J23+J24 -> 3747.388 | K19: =K23+K24 -> 3883.9267 | L19: =L23+L24 -> 4025.5263
C21: Customer funds balance | E21: 38935 | F21: 37671 | G21: 38198 | H21: =G21*(1+Assumptions!$N$32) -> 39343.94 | I21: =H21*(1+Assumptions!$N$32) -> 40524.258 | J21: =I21*(1+Assumptions!$N$32) -> 41739.986 | K21: =J21*(1+Assumptions!$N$32) -> 42992.186 | L21: =K21*(1+Assumptions!$N$32) -> 44281.951
C22: Effective yield | E22: =E23/E21 -> 0.023218184 | F22: =F23/F21 -> 0.034084574 | G22: =G23/G21 -> 0.032200639 | H22: =Assumptions!$N$31 -> 0.032 | I22: =Assumptions!$N$31 -> 0.032 | J22: =Assumptions!$N$31 -> 0.032 | K22: =Assumptions!$N$31 -> 0.032 | L22: =Assumptions!$N$31 -> 0.032
C23: Interest on customer balances | E23: 904 | F23: 1284 | G23: 1230 | H23: =H21*H22 -> 1259.0061 | I23: =I21*I22 -> 1296.7763 | J23: =J21*J22 -> 1335.6796 | K23: =K21*K22 -> 1375.7499 | L23: =L21*L22 -> 1417.0224
C24: Remaining OVAS, ex-interest | E24: =E19-E23 -> 2010 | F24: =F19-F23 -> 1671 | G24: =G19-G23 -> 2144 | H24: =G24*(1+Assumptions!$N$21) -> 2229.76 | I24: =H24*(1+Assumptions!$N$21) -> 2318.9504 | J24: =I24*(1+Assumptions!$N$21) -> 2411.7084 | K24: =J24*(1+Assumptions!$N$21) -> 2508.1768 | L24: =K24*(1+Assumptions!$N$21) -> 2608.5038

Sheet IS
L1: ="CURRENTLY RUNNING: "&UPPER(CHOOSE(Scenarios!$C$6,Scenarios!B10,Scenarios!B11,Scenarios!B12))&" SCENARIO" -> CURRENTLY RUNNING: BASE CASE SCENARIO
B2: =Cover!$B$7 -> PayPal
B3: Income Statement
B4: ($ Millions)
H5: Projected
E6: =F6-1 -> 2023 | F6: =G6-1 -> 2024 | G6: 2025 | H6: =G6+1 -> 2026 | I6: =H6+1 -> 2027 | J6: =I6+1 -> 2028 | K6: =J6+1 -> 2029 | L6: =K6+1 -> 2030
C8: Net Revenue | E8: 29771 | F8: 31797 | G8: 33172 | H8: ='Revenue Build'!H11 -> 34315.686 | I8: ='Revenue Build'!I11 -> 35688.889 | J8: ='Revenue Build'!J11 -> 37318.556 | K8: ='Revenue Build'!K11 -> 39243.381 | L8: ='Revenue Build'!L11 -> 41267.006
C9: Transaction Expense | E9: -14385 | F9: -15697 | G9: -15987 | H9: =-('Revenue Build'!H14*Assumptions!$H$28) -> -16886.86 | I9: =-('Revenue Build'!I14*Assumptions!$H$28) -> -17900.072 | J9: =-('Revenue Build'!J14*Assumptions!$H$28) -> -18974.076 | K9: =-('Revenue Build'!K14*Assumptions!$H$28) -> -20112.52 | L9: =-('Revenue Build'!L14*Assumptions!$H$28) -> -21319.272
C10: Transaction and Credit Losses | E10: -1682 | F10: -1442 | G10: -1720 | H10: =-('Revenue Build'!H14*Assumptions!$H$29) -> -1821.504 | I10: =-('Revenue Build'!I14*Assumptions!$H$29) -> -1930.7942 | J10: =-('Revenue Build'!J14*Assumptions!$H$29) -> -2046.6419 | K10: =-('Revenue Build'!K14*Assumptions!$H$29) -> -2169.4404 | L10: =-('Revenue Build'!L14*Assumptions!$H$29) -> -2299.6068
C11: Customer Support and Operations | E11: -1919 | F11: -1768 | G11: -1704 | H11: =-H8*Assumptions!$H$30 -> -1750.1 | I11: =-I8*Assumptions!$H$30 -> -1820.1333 | J11: =-J8*Assumptions!$H$30 -> -1903.2464 | K11: =-K8*Assumptions!$H$30 -> -2001.4125 | L11: =-L8*Assumptions!$H$30 -> -2104.6173
C12: Gross Profit | E12: =SUM(E8:E11) -> 11785 | F12: =SUM(F8:F11) -> 12890 | G12: =SUM(G8:G11) -> 13761 | H12: =SUM(H8:H11) -> 13857.222 | I12: =SUM(I8:I11) -> 14037.89 | J12: =SUM(J8:J11) -> 14394.592 | K12: =SUM(K8:K11) -> 14960.008 | L12: =SUM(L8:L11) -> 15543.51
C14: Sales and Marketing | E14: -1809 | F14: -2001 | G14: -2283 | H14: =-H8*Assumptions!$H$31 -> -2367.7823 | I14: =-I8*Assumptions!$H$31 -> -2462.5333 | J14: =-J8*Assumptions!$H$31 -> -2574.9804 | K14: =-K8*Assumptions!$H$31 -> -2707.7933 | L14: =-L8*Assumptions!$H$31 -> -2847.4234
C15: Technology and Development | E15: -2973 | F15: -2979 | G15: -3103 | H15: =G15*(1+Assumptions!$H$32) -> -3196.09 | I15: =H15*(1+Assumptions!$H$32) -> -3291.9727 | J15: =I15*(1+Assumptions!$H$32) -> -3390.7319 | K15: =J15*(1+Assumptions!$H$32) -> -3492.4538 | L15: =K15*(1+Assumptions!$H$32) -> -3597.2275
C16: General and Administrative | E16: -2059 | F16: -2147 | G16: -1979 | H16: =G16*(1+Assumptions!$H$33) -> -2018.58 | I16: =H16*(1+Assumptions!$H$33) -> -2058.9516 | J16: =I16*(1+Assumptions!$H$33) -> -2100.1306 | K16: =J16*(1+Assumptions!$H$33) -> -2142.1332 | L16: =K16*(1+Assumptions!$H$33) -> -2184.9759
C17: Restructuring and Other | E17: 84 | F17: -438 | G17: -331 | H17: 0 | I17: 0 | J17: 0 | K17: 0 | L17: 0
C18: EBIT | E18: =SUM(E12:E17) -> 5028 | F18: =SUM(F12:F17) -> 5325 | G18: =SUM(G12:G17) -> 6065 | H18: =SUM(H12:H17) -> 6274.7698 | I18: =SUM(I12:I17) -> 6224.4319 | J18: =SUM(J12:J17) -> 6328.7489 | K18: =SUM(K12:K17) -> 6617.6277 | L18: =SUM(L12:L17) -> 6913.8833
C20: Interest Income (Expense) | H20: ='Debt Schedule'!H39 -> -131.277 | I20: ='Debt Schedule'!I39 -> -88.34739 | J20: ='Debt Schedule'!J39 -> -50.059065 | K20: ='Debt Schedule'!K39 -> -8.3171577 | L20: ='Debt Schedule'!L39 -> 44.223401
C21: Other Income (expense), net | E21: 383 | F21: 4 | G21: 227 | H21: =AVERAGE($E$21:$G$21) -> 204.66667 | I21: =AVERAGE($E$21:$G$21) -> 204.66667 | J21: =AVERAGE($E$21:$G$21) -> 204.66667 | K21: =AVERAGE($E$21:$G$21) -> 204.66667 | L21: =AVERAGE($E$21:$G$21) -> 204.66667
C22: EBT | E22: =E21+E18 -> 5411 | F22: =F21+F18 -> 5329 | G22: =G21+G18 -> 6292 | H22: =H18+H21+H20 -> 6348.1594 | I22: =I18+I21+I20 -> 6340.7512 | J22: =J18+J21+J20 -> 6483.3565 | K22: =K18+K21+K20 -> 6813.9772 | L22: =L18+L21+L20 -> 7162.7734
C24: Income Tax Expense | E24: -1165 | F24: -1182 | G24: -1059 | H24: =-'Income Tax Schedule'!H17 -> -1092.7885 | I24: =-'Income Tax Schedule'!I17 -> -1172.0105 | J24: =-'Income Tax Schedule'!J17 -> -1255.5845 | K24: =-'Income Tax Schedule'!K17 -> -1360.6167 | L24: =-'Income Tax Schedule'!L17 -> -1457.4992
C25: Net Income | E25: =E22+E24 -> 4246 | F25: =F22+F24 -> 4147 | G25: =G22+G24 -> 5233 | H25: =H22+H24 -> 5255.3709 | I25: =I22+I24 -> 5168.7406 | J25: =J22+J24 -> 5227.7721 | K25: =K22+K24 -> 5453.3605 | L25: =L22+L24 -> 5705.2741
C27: Depreciation & Amortization | E27: -1072 | F27: -1032 | G27: -963 | H27: ='D&A Schedule'!G29 -> -872.06521 | I27: ='D&A Schedule'!H29 -> -879.8888 | J27: ='D&A Schedule'!I29 -> -916.67086 | K27: ='D&A Schedule'!J29 -> -927.60299 | L27: ='D&A Schedule'!K29 -> -990.2919
C28: EBITDA | E28: =E18-E27 -> 6100 | F28: =F18-F27 -> 6357 | G28: =G18-G27 -> 7028 | H28: =H18-H27 -> 7146.835 | I28: =I18-I27 -> 7104.3207 | J28: =J18-J27 -> 7245.4198 | K28: =K18-K27 -> 7545.2307 | L28: =L18-L27 -> 7904.1752
C30: Stock Based Compensation | E30: 1145 | F30: 1326 | G30: 1135 | H30: =H8*Assumptions!$H$34 -> 1166.7333 | I30: =I8*Assumptions!$H$34 -> 1213.4222 | J30: =J8*Assumptions!$H$34 -> 1268.8309 | K30: =K8*Assumptions!$H$34 -> 1334.275 | L30: =L8*Assumptions!$H$34 -> 1403.0782
C31: Adjusted EBITDA | H31: =H28+H30 -> 8313.5683 | I31: =I28+I30 -> 8317.7429 | J31: =J28+J30 -> 8514.2507 | K31: =K28+K30 -> 8879.5056 | L31: =L28+L30 -> 9307.2534
B33: Growth Rates & Margins
C34: Revenue Growth Rate | F34: =(F8/E8)-1 -> 0.068052803 | G34: =(G8/F8)-1 -> 0.043243073 | H34: =(H8/G8)-1 -> 0.034477453 | I34: =(I8/H8)-1 -> 0.04001676 | J34: =(J8/I8)-1 -> 0.045663156 | K34: =(K8/J8)-1 -> 0.05157824 | L34: =(L8/K8)-1 -> 0.051566007
C35: Transaction Expenses | E35: =-(E9/E8) -> 0.48318834 | F35: =-(F9/F8) -> 0.49366292 | G35: =-(G9/G8) -> 0.4819426 | H35: =-(H9/H8) -> 0.49210323 | I35: =-(I9/I8) -> 0.50155867 | J35: =-(J9/J8) -> 0.50843543 | K35: =-(K9/K8) -> 0.51250733 | L35: =-(L9/L8) -> 0.51661785
C36: Transaction & Credit Losses | E36: =-(E10/E8) -> 0.056497934 | F36: =-(F10/F8) -> 0.04535019 | G36: =-(G10/G8) -> 0.051850959 | H36: =-(H10/H8) -> 0.053080798 | I36: =-(I10/I8) -> 0.054100711 | J36: =-(J10/J8) -> 0.054842473 | K36: =-(K10/K8) -> 0.055281689 | L36: =-(L10/L8) -> 0.055725071
C37: Customer Support & Operations | F37: =(F11/E11)-1 -> -0.078686816 | G37: =(G11/F11)-1 -> -0.036199095 | H37: =(H11/G11)-1 -> 0.027053985 | I37: =(I11/H11)-1 -> 0.04001676 | J37: =(J11/I11)-1 -> 0.045663156 | K37: =(K11/J11)-1 -> 0.05157824 | L37: =(L11/K11)-1 -> 0.051566007
C38: Sales & Marketing | F38: =(F14/E14)-1 -> 0.10613599 | G38: =(G14/F14)-1 -> 0.14092954 | H38: =(H14/G14)-1 -> 0.037136373 | I38: =(I14/H14)-1 -> 0.04001676 | J38: =(J14/I14)-1 -> 0.045663156 | K38: =(K14/J14)-1 -> 0.05157824 | L38: =(L14/K14)-1 -> 0.051566007
C39: Technology & Development Growth | F39: =(F15/E15)-1 -> 0.0020181635 | G39: =(G15/F15)-1 -> 0.041624706 | H39: =(H15/G15)-1 -> 0.03 | I39: =(I15/H15)-1 -> 0.03 | J39: =(J15/I15)-1 -> 0.03 | K39: =(K15/J15)-1 -> 0.03 | L39: =(L15/K15)-1 -> 0.03
C40: General & Administrative | F40: =(F16/E16)-1 -> 0.042739194 | G40: =(G16/F16)-1 -> -0.078248719 | H40: =(H16/G16)-1 -> 0.02 | I40: =(I16/H16)-1 -> 0.02 | J40: =(J16/I16)-1 -> 0.02 | K40: =(K16/J16)-1 -> 0.02 | L40: =(L16/K16)-1 -> 0.02
C41: Stock-based compensation
C42: Gross Profit Margin | E42: =E12/E8 -> 0.39585503 | F42: =F12/F8 -> 0.40538416 | G42: =G12/G8 -> 0.41483782 | H42: =H12/H8 -> 0.40381597 | I42: =I12/I8 -> 0.39334062 | J42: =J12/J8 -> 0.3857221 | K42: =K12/K8 -> 0.38121099 | L42: =L12/L8 -> 0.37665708
C43: EBITDA Margin | E43: =E28/E8 -> 0.20489738 | F43: =F28/F8 -> 0.19992452 | G43: =G28/G8 -> 0.21186543 | H43: =H28/H8 -> 0.20826729 | I43: =I28/I8 -> 0.19906254 | J43: =J28/J8 -> 0.19415059 | K43: =K28/K8 -> 0.1922676 | L43: =L28/L8 -> 0.1915374
C44: EBIT Margin | E44: =E18/E8 -> 0.16888919 | F44: =F18/F8 -> 0.16746863 | G44: =G18/G8 -> 0.18283492 | H44: =H18/H8 -> 0.18285427 | I44: =I18/I8 -> 0.17440812 | J44: =J18/J8 -> 0.16958719 | K44: =K18/K8 -> 0.16863041 | L44: =L18/L8 -> 0.16754022
C45: Return on Equity | H45: =IS!H25/BS!H44 -> 0.24776892 | I45: =IS!I25/BS!I44 -> 0.23310461 | J45: =IS!J25/BS!J44 -> 0.22438236 | K45: =IS!K25/BS!K44 -> 0.22022729 | L45: =IS!L25/BS!L44 -> 0.21452488

Sheet BS
L1: ="CURRENTLY RUNNING: "&UPPER(CHOOSE(Scenarios!$C$6,Scenarios!B10,Scenarios!B11,Scenarios!B12))&" SCENARIO" -> CURRENTLY RUNNING: BASE CASE SCENARIO
B2: =Cover!$B$7 -> PayPal
B3: Balance Sheet
B4: ($ Millions)
H5: Projected
F6: =IS!F6 -> 2024 | G6: =IS!G6 -> 2025 | H6: =IS!H6 -> 2026 | I6: =IS!I6 -> 2027 | J6: =IS!J6 -> 2028 | K6: =IS!K6 -> 2029 | L6: =IS!L6 -> 2030
B8: Assets
C9: Cash & Equivalents | F9: =6662+4262 -> 10924 | G9: =8049+2373 -> 10422 | H9: ='Debt Schedule'!H11 -> 10036.887 | I9: ='Debt Schedule'!I11 -> 9915.6645 | J9: ='Debt Schedule'!J11 -> 9828.9614 | K9: ='Debt Schedule'!K11 -> 9630.3134 | L9: ='Debt Schedule'!L11 -> 10303.079
C10: Accounts Receivable, Net | F10: 984 | G10: 840 | H10: ='Working Capital Schedule'!H21 -> 864.94332 | I10: ='Working Capital Schedule'!I21 -> 899.55555 | J10: ='Working Capital Schedule'!J21 -> 938.06206 | K10: ='Working Capital Schedule'!K21 -> 989.14824 | L10: ='Working Capital Schedule'!L21 -> 1040.1547
C11: Inventory and Interest Receivable, Held for Sale | F11: 541 | G11: 1726 | H11: =(G11/IS!G8)*IS!H8 -> 1785.5081 | I11: =(H11/IS!H8)*IS!I8 -> 1856.9583 | J11: =(I11/IS!I8)*IS!J8 -> 1941.7529 | K11: =(J11/IS!J8)*IS!K8 -> 2041.9051 | L11: =(K11/IS!K8)*IS!L8 -> 2147.198
C12: Loans and Interest Receivable, Net of Allowances | F12: 6422 | G12: 6746 | H12: =G12*(IS!H8/IS!G8) -> 6978.5849 | I12: =H12*(IS!I8/IS!H8) -> 7257.8453 | J12: =I12*(IS!J8/IS!I8) -> 7589.2614 | K12: =J12*(IS!K8/IS!J8) -> 7980.7021 | L12: =K12*(IS!L8/IS!K8) -> 8392.2351
C13: Funds Receivable and Customer Accounts | F13: 37671 | G13: 38198 | H13: ='Working Capital Schedule'!H31 -> 39514.97 | I13: ='Working Capital Schedule'!I31 -> 41096.231 | J13: ='Working Capital Schedule'!J31 -> 42972.814 | K13: ='Working Capital Schedule'!K31 -> 45189.277 | L13: ='Working Capital Schedule'!L31 -> 47519.507
C14: Prepaid Expenses and Other Current Assets | F14: 1664 | G14: 1827 | H14: ='Working Capital Schedule'!H22 -> 1928.1402 | I14: ='Working Capital Schedule'!I22 -> 2040.5325 | J14: ='Working Capital Schedule'!J22 -> 2154.6021 | K14: ='Working Capital Schedule'!K22 -> 2288.6248 | L14: ='Working Capital Schedule'!L22 -> 2424.3514
C15: Total Current Assets | F15: =SUM(F9:F14) -> 58206 | G15: =SUM(G9:G14) -> 59759 | H15: =SUM(H9:H14) -> 61109.033 | I15: =SUM(I9:I14) -> 63066.787 | J15: =SUM(J9:J14) -> 65425.454 | K15: =SUM(K9:K14) -> 68119.97 | L15: =SUM(L9:L14) -> 71826.525
C17: Long-Term Investments | F17: 4583 | G17: 4330 | H17: =G17 -> 4330 | I17: =H17 -> 4330 | J17: =I17 -> 4330 | K17: =J17 -> 4330 | L17: =K17 -> 4330
C18: Property and Equipment, Net | F18: 1508 | G18: 1700 | H18: ='D&A Schedule'!G25 -> 1749.5113 | I18: ='D&A Schedule'!H25 -> 1788.1558 | J18: ='D&A Schedule'!I25 -> 1815.1303 | K18: ='D&A Schedule'!J25 -> 1829.3684 | L18: ='D&A Schedule'!K25 -> 1829.4847
C19: Goodwill | F19: 10837 | G19: 10864 | H19: =G19 -> 10864 | I19: =H19 -> 10864 | J19: =I19 -> 10864 | K19: =J19 -> 10864 | L19: =K19 -> 10864
C20: Intangible Assets, Net | F20: 326 | G20: 208 | H20: ='D&A Schedule'!G11 -> 110 | I20: ='D&A Schedule'!H11 -> 48 | J20: ='D&A Schedule'!I11 -> 0 | K20: ='D&A Schedule'!J11 -> 0 | L20: ='D&A Schedule'!K11 -> 0
C21: Other Assets | F21: 3265 | G21: 3312 | H21: =(G21/IS!G8)*IS!H8 -> 3426.1893 | I21: =(H21/IS!H8)*IS!I8 -> 3563.2943 | J21: =(I21/IS!I8)*IS!J8 -> 3726.0056 | K21: =(J21/IS!J8)*IS!K8 -> 3918.1864 | L21: =(K21/IS!K8)*IS!L8 -> 4120.2316
C22: Total Long Term Assets | F22: =SUM(F17:F21) -> 20519 | G22: =SUM(G17:G21) -> 20414 | H22: =SUM(H17:H21) -> 20479.701 | I22: =SUM(I17:I21) -> 20593.45 | J22: =SUM(J17:J21) -> 20735.136 | K22: =SUM(K17:K21) -> 20941.555 | L22: =SUM(L17:L21) -> 21143.716
C24: Total Assets | F24: =+F15+F22 -> 78725 | G24: =+G15+G22 -> 80173 | H24: =+H15+H22 -> 81588.734 | I24: =+I15+I22 -> 83660.237 | J24: =+J15+J22 -> 86160.59 | K24: =+K15+K22 -> 89061.525 | L24: =+L15+L22 -> 92970.242
B27: Liabilities and Equity
C28: Accounts Payable | F28: 227 | G28: 240 | H28: ='Working Capital Schedule'!H23 -> 252.22764 | I28: ='Working Capital Schedule'!I23 -> 266.93013 | J28: ='Working Capital Schedule'!J23 -> 281.85202 | K28: ='Working Capital Schedule'!K23 -> 299.38405 | L28: ='Working Capital Schedule'!L23 -> 317.13899
C29: Funds Payable to Customers | F29: 39671 | G29: 40198 | H29: =-'Working Capital Schedule'!H32 -> 41583.925 | I29: =-'Working Capital Schedule'!I32 -> 43247.979 | J29: =-'Working Capital Schedule'!J32 -> 45222.818 | K29: =-'Working Capital Schedule'!K32 -> 47555.331 | L29: =-'Working Capital Schedule'!L32 -> 50007.57
C30: Accrued Expenses and Other Current Liabilities | F30: =5592-1191 -> 4401 | G30: =6005-1396 -> 4609 | H30: ='Working Capital Schedule'!H24 -> 4859.5858 | I30: ='Working Capital Schedule'!I24 -> 5142.8538 | J30: ='Working Capital Schedule'!J24 -> 5430.3489 | K30: ='Working Capital Schedule'!K24 -> 5768.1328 | L30: ='Working Capital Schedule'!L24 -> 6110.2112
C31: Current Portion of Term Debt | F31: 1191 | G31: 1396
C32: Total Current Liabilities | F32: =SUM(F28:F31) -> 45490 | G32: =SUM(G28:G31) -> 46443 | H32: =SUM(H28:H31) -> 46695.738 | I32: =SUM(I28:I31) -> 48657.763 | J32: =SUM(J28:J31) -> 50935.019 | K32: =SUM(K28:K31) -> 53622.848 | L32: =SUM(L28:L31) -> 56434.92
C34: Other Long-Term Liabilities | F34: 2939 | G34: 3487 | H34: =G34*(1+Assumptions!$N$19) -> 3696.22 | I34: =H34*(1+Assumptions!$N$19) -> 3917.9932 | J34: =I34*(1+Assumptions!$N$19) -> 4153.0728 | K34: =J34*(1+Assumptions!$N$19) -> 4402.2572 | L34: =K34*(1+Assumptions!$N$19) -> 4666.3926
C35: Long-Term Debt | F35: 9879 | G35: 9987 | H35: ='Debt Schedule'!H34 -> 9986 | I35: ='Debt Schedule'!I34 -> 8911 | J35: ='Debt Schedule'!J34 -> 7774 | K35: ='Debt Schedule'!K34 -> 6274 | L35: ='Debt Schedule'!L34 -> 5274
C36: Total Long Term Liabilities | F36: =SUM(F34:F35) -> 12818 | G36: =SUM(G34:G35) -> 13474 | H36: =SUM(H34:H35) -> 13682.22 | I36: =SUM(I34:I35) -> 12828.993 | J36: =SUM(J34:J35) -> 11927.073 | K36: =SUM(K34:K35) -> 10676.257 | L36: =SUM(L34:L35) -> 9940.3926
C38: Total Liabilities | F38: =F36+F32 -> 58308 | G38: =G36+G32 -> 59917 | H38: =H36+H32 -> 60377.958 | I38: =I36+I32 -> 61486.756 | J38: =J36+J32 -> 62862.092 | K38: =K36+K32 -> 64299.105 | L38: =L36+L32 -> 66375.312
C40: Treasury Stock | F40: -27085 | G40: -33138 | H40: =G40-(Assumptions!$N$10*'Equity Schedule'!H9) -> -38138 | I40: =H40-(Assumptions!$N$10*'Equity Schedule'!I9) -> -43138 | J40: =I40-(Assumptions!$N$10*'Equity Schedule'!J9) -> -48138 | K40: =J40-(Assumptions!$N$10*'Equity Schedule'!K9) -> -53138 | L40: =K40-(Assumptions!$N$10*'Equity Schedule'!L9) -> -58138
C41: Additional Paid-In-Capital | F41: 20705 | G41: 21582 | H41: =G41+IS!H30 -> 22748.733 | I41: =H41+IS!I30 -> 23962.156 | J41: =I41+IS!J30 -> 25230.986 | K41: =J41+IS!K30 -> 26565.261 | L41: =K41+IS!L30 -> 27968.34
C42: Retained Earnings | F42: 27347 | G42: 32470 | H42: ='Equity Schedule'!H19 -> 37258.042 | I42: ='Equity Schedule'!I19 -> 42007.326 | J42: ='Equity Schedule'!J19 -> 46863.512 | K42: ='Equity Schedule'!K19 -> 51993.158 | L42: ='Equity Schedule'!L19 -> 57422.59
C43: Accumulated Other Comprhensive Income (Loss) | F43: -550 | G43: -658 | H43: =G43 -> -658 | I43: =H43 -> -658 | J43: =I43 -> -658 | K43: =J43 -> -658 | L43: =K43 -> -658
C44: Shareholder's Equity | F44: =SUM(F40:F43) -> 20417 | G44: =SUM(G40:G43) -> 20256 | H44: =SUM(H40:H43) -> 21210.776 | I44: =SUM(I40:I43) -> 22173.481 | J44: =SUM(J40:J43) -> 23298.499 | K44: =SUM(K40:K43) -> 24762.42 | L44: =SUM(L40:L43) -> 26594.929
B46: Total Liabilities and Equity | F46: =F44+F38 -> 78725 | G46: =G44+G38 -> 80173 | H46: =H44+H38 -> 81588.734 | I46: =I44+I38 -> 83660.237 | J46: =J44+J38 -> 86160.59 | K46: =K44+K38 -> 89061.525 | L46: =L44+L38 -> 92970.242
D48: Check | F48: =ROUND(F24-F46,3) -> 0 | G48: =ROUND(G24-G46,3) -> 0 | H48: =ROUND(H24-H46,3) -> 0 | I48: =ROUND(I24-I46,3) -> 0 | J48: =ROUND(J24-J46,3) -> 0 | K48: =ROUND(K24-K46,3) -> 0 | L48: =ROUND(L24-L46,3) -> 0

Sheet CFS
L1: ="CURRENTLY RUNNING: "&UPPER(CHOOSE(Scenarios!$C$6,Scenarios!B10,Scenarios!B11,Scenarios!B12))&" SCENARIO" -> CURRENTLY RUNNING: BASE CASE SCENARIO
B2: =Cover!$B$7 -> PayPal
B3: Cash Flow Statement
B4: ($ Millions)
H5: Projected
H6: =IS!H6 -> 2026 | I6: =IS!I6 -> 2027 | J6: =IS!J6 -> 2028 | K6: =IS!K6 -> 2029 | L6: =IS!L6 -> 2030
B7: Operating Activities
C8: Net Income | H8: =IS!H25 -> 5255.3709 | I8: =IS!I25 -> 5168.7406 | J8: =IS!J25 -> 5227.7721 | K8: =IS!K25 -> 5453.3605 | L8: =IS!L25 -> 5705.2741
C9: Depreciation & Amortization | H9: =-'D&A Schedule'!G29 -> 872.06521 | I9: =-'D&A Schedule'!H29 -> 879.8888 | J9: =-'D&A Schedule'!I29 -> 916.67086 | K9: =-'D&A Schedule'!J29 -> 927.60299 | L9: =-'D&A Schedule'!K29 -> 990.2919
C10: Stock Based Compensation | H10: =IS!H30 -> 1166.7333 | I10: =IS!I30 -> 1213.4222 | J10: =IS!J30 -> 1268.8309 | K10: =IS!K30 -> 1334.275 | L10: =IS!L30 -> 1403.0782
C11: Adjustments to Loans and Interest Receivable, Held for Sale | H11: =BS!G11-BS!H11 -> -59.508084 | I11: =BS!H11-BS!I11 -> -71.450249 | J11: =BS!I11-BS!J11 -> -84.794578 | K11: =BS!J11-BS!K11 -> -100.1522 | L11: =BS!K11-BS!L11 -> -105.29289
C12: Accounts Receivable | H12: =BS!G10-BS!H10 -> -24.94332 | I12: =BS!H10-BS!I10 -> -34.612229 | J12: =BS!I10-BS!J10 -> -38.506512 | K12: =BS!J10-BS!K10 -> -51.086181 | L12: =BS!K10-BS!L10 -> -51.006425
C13: Other Current Assest and Non-Current Assets | H13: =(BS!G14-BS!H14)+(BS!G21-BS!H21) -> -215.32949 | I13: =(BS!H14-BS!I14)+(BS!H21-BS!I21) -> -249.49735 | J13: =(BS!I14-BS!J14)+(BS!I21-BS!J21) -> -276.78084 | K13: =(BS!J14-BS!K14)+(BS!J21-BS!K21) -> -326.20349 | L13: =(BS!K14-BS!L14)+(BS!K21-BS!L21) -> -337.77184
C14: Accounts Payable | H14: =BS!H28-BS!G28 -> 12.227638 | I14: =BS!I28-BS!H28 -> 14.702488 | J14: =BS!J28-BS!I28 -> 14.921892 | K14: =BS!K28-BS!J28 -> 17.532036 | L14: =BS!L28-BS!K28 -> 17.754935
C15: Other Current Liabilities and Non-Current Liabilities | H15: =(BS!H30-BS!G30)+(BS!H34-BS!G34) -> 459.80583 | I15: =(BS!I30-BS!H30)+(BS!I34-BS!H34) -> 505.04114 | J15: =(BS!J30-BS!I30)+(BS!J34-BS!I34) -> 522.5747 | K15: =(BS!K30-BS!J30)+(BS!K34-BS!J34) -> 586.96827 | L15: =(BS!L30-BS!K30)+(BS!L34-BS!K34) -> 606.21384
C16: Operating Cash Flow | H16: =SUM(H8:H15) -> 7466.422 | I16: =SUM(I8:I15) -> 7426.2354 | J16: =SUM(J8:J15) -> 7550.6885 | K16: =SUM(K8:K15) -> 7842.2969 | L16: =SUM(L8:L15) -> 8228.5418
B18: Investing Activities
C19: Purchases of Property and Equipment | H19: =-('D&A Schedule'!G22) -> -823.57647 | I19: =-('D&A Schedule'!H22) -> -856.53333 | J19: =-('D&A Schedule'!I22) -> -895.64534 | K19: =-('D&A Schedule'!J22) -> -941.84115 | L19: =-('D&A Schedule'!K22) -> -990.40814
C20: Net Loan & Investment Forecast | H20: =(BS!G12-BS!H12)+(BS!G13-BS!H13) -> -1549.5547 | I20: =(BS!H12-BS!I12)+(BS!H13-BS!I13) -> -1860.5214 | J20: =(BS!I12-BS!J12)+(BS!I13-BS!J13) -> -2207.9997 | K20: =(BS!J12-BS!K12)+(BS!J13-BS!K13) -> -2607.9029 | L20: =(BS!K12-BS!L12)+(BS!K13-BS!L13) -> -2741.7635
C21: Investing Cash Flow | H21: =SUM(H19:H20) -> -2373.1311 | I21: =SUM(I19:I20) -> -2717.0548 | J21: =SUM(J19:J20) -> -3103.6451 | K21: =SUM(K19:K20) -> -3549.744 | L21: =SUM(L19:L20) -> -3732.1716
B23: Financing Activities
C24: Purchases of treasury stock | H24: =-('Equity Schedule'!H9*Assumptions!$N$10) -> -5000 | I24: =-('Equity Schedule'!I9*Assumptions!$N$10) -> -5000 | J24: =-('Equity Schedule'!J9*Assumptions!$N$10) -> -5000 | K24: =-('Equity Schedule'!K9*Assumptions!$N$10) -> -5000 | L24: =-('Equity Schedule'!L9*Assumptions!$N$10) -> -5000
C25: Repayments under financing arrangements | H25: ='Debt Schedule'!H19 -> -1397 | I25: ='Debt Schedule'!I19 -> -1075 | J25: ='Debt Schedule'!J19 -> -1137 | K25: ='Debt Schedule'!K19 -> -1500 | L25: ='Debt Schedule'!L19 -> -1000
C26: Common Dividends | H26: =-('Equity Schedule'!H13) -> -467.32857 | I26: =-('Equity Schedule'!I13) -> -419.45714 | J26: =-('Equity Schedule'!J13) -> -371.58571 | K26: =-('Equity Schedule'!K13) -> -323.71428 | L26: =-('Equity Schedule'!L13) -> -275.84284
C27: Net Float & Financing , Forecast | H27: =BS!H29-BS!G29 -> 1385.9247 | I27: =BS!I29-BS!H29 -> 1664.0539 | J27: =BS!J29-BS!I29 -> 1974.8392 | K27: =BS!K29-BS!J29 -> 2332.5133 | L27: =BS!L29-BS!K29 -> 2452.2385
C28: Financing Cash Flow | H28: =SUM(H24:H27) -> -5478.4039 | I28: =SUM(I24:I27) -> -4830.4032 | J28: =SUM(J24:J27) -> -4533.7465 | K28: =SUM(K24:K27) -> -4491.2009 | L28: =SUM(L24:L27) -> -3823.6043
B31: Change in the Cash Position | H31: =H28+H21+H16 -> -385.113 | I31: =I28+I21+I16 -> -121.2225 | J31: =J28+J21+J16 -> -86.703086 | K31: =K28+K21+K16 -> -198.64803 | L31: =L28+L21+L16 -> 672.76588
B32: Beginning Cash | H32: =BS!G9 -> 10422 | I32: =+H33 -> 10036.887 | J32: =+I33 -> 9915.6645 | K32: =+J33 -> 9828.9614 | L32: =+K33 -> 9630.3134
B33: Ending Cash | H33: =H32+H31 -> 10036.887 | I33: =I32+I31 -> 9915.6645 | J33: =J32+J31 -> 9828.9614 | K33: =K32+K31 -> 9630.3134 | L33: =L32+L31 -> 10303.079

Sheet Working Capital Schedule
L1: ="CURRENTLY RUNNING: "&UPPER(CHOOSE(Scenarios!$C$6,Scenarios!B10,Scenarios!B11,Scenarios!B12))&" SCENARIO" -> CURRENTLY RUNNING: BASE CASE SCENARIO
B2: PayPal
B3: Working Capital Schedule
B4: ($ Millions)
H5: Projected
E6: =IS!E6 -> 2023 | F6: =IS!F6 -> 2024 | G6: =IS!G6 -> 2025 | H6: =IS!H6 -> 2026 | I6: =IS!I6 -> 2027 | J6: =IS!J6 -> 2028 | K6: =IS!K6 -> 2029 | L6: =IS!L6 -> 2030
B8: Days per Year | F8: =DATE(F6,12,31)-DATE(E6,12,31) -> 366 | G8: =DATE(G6,12,31)-DATE(F6,12,31) -> 365 | H8: =DATE(H6,12,31)-DATE(G6,12,31) -> 365 | I8: =DATE(I6,12,31)-DATE(H6,12,31) -> 365 | J8: =DATE(J6,12,31)-DATE(I6,12,31) -> 366 | K8: =DATE(K6,12,31)-DATE(J6,12,31) -> 365 | L8: =DATE(L6,12,31)-DATE(K6,12,31) -> 365
B10: Income Statement Items
C11: Net Revenue | F11: =IS!F8 -> 31797 | G11: =IS!G8 -> 33172 | H11: =IS!H8 -> 34315.686 | I11: =IS!I8 -> 35688.889 | J11: =IS!J8 -> 37318.556 | K11: =IS!K8 -> 39243.381 | L11: =IS!L8 -> 41267.006
C12: Cost of Sales | F12: =-(IS!F9+IS!F10+IS!F11) -> 18907 | G12: =-(IS!G9+IS!G10+IS!G11) -> 19411 | H12: =-(IS!H9+IS!H10+IS!H11) -> 20458.464 | I12: =-(IS!I9+IS!I10+IS!I11) -> 21650.999 | J12: =-(IS!J9+IS!J10+IS!J11) -> 22923.964 | K12: =-(IS!K9+IS!K10+IS!K11) -> 24283.373 | L12: =-(IS!L9+IS!L10+IS!L11) -> 25723.496
B14: Days In
C15: Accounts Receivable (days) | F15: =F21/F11*F8 -> 11.326352 | G15: =G21/G11*G8 -> 9.2427348 | H15: =Assumptions!J68 -> 9.2 | I15: =Assumptions!K68 -> 9.2 | J15: =Assumptions!L68 -> 9.2 | K15: =Assumptions!M68 -> 9.2 | L15: =Assumptions!N68 -> 9.2
C16: Prepaid Expenses (days) | F16: =F22/F12*F8 -> 32.211562 | G16: =G22/G12*G8 -> 34.35449 | H16: =Assumptions!J69 -> 34.4 | I16: =Assumptions!K69 -> 34.4 | J16: =Assumptions!L69 -> 34.4 | K16: =Assumptions!M69 -> 34.4 | L16: =Assumptions!N69 -> 34.4
C17: Accounts Payable (days) | F17: =F23/F12*F8 -> 4.3942455 | G17: =G23/G12*G8 -> 4.5129051 | H17: =Assumptions!J70 -> 4.5 | I17: =Assumptions!K70 -> 4.5 | J17: =Assumptions!L70 -> 4.5 | K17: =Assumptions!M70 -> 4.5 | L17: =Assumptions!N70 -> 4.5
C18: Other Liabilities (days) | F18: =F24/F12*F8 -> 85.194161 | G18: =G24/G12*G8 -> 86.666581 | H18: =Assumptions!J71 -> 86.7 | I18: =Assumptions!K71 -> 86.7 | J18: =Assumptions!L71 -> 86.7 | K18: =Assumptions!M71 -> 86.7 | L18: =Assumptions!N71 -> 86.7
B20: Account Balances
C21: Accounts Receivable | F21: 984 | G21: 840 | H21: =H11/H8*H15 -> 864.94332 | I21: =I11/I8*I15 -> 899.55555 | J21: =J11/J8*J15 -> 938.06206 | K21: =K11/K8*K15 -> 989.14824 | L21: =L11/L8*L15 -> 1040.1547
C22: Prepaid Expenses | F22: 1664 | G22: 1827 | H22: =H12/H8*H16 -> 1928.1402 | I22: =I12/I8*I16 -> 2040.5325 | J22: =J12/J8*J16 -> 2154.6021 | K22: =K12/K8*K16 -> 2288.6248 | L22: =L12/L8*L16 -> 2424.3514
C23: Accounts Payable | F23: 227 | G23: 240 | H23: =H12/H8*H17 -> 252.22764 | I23: =I12/I8*I17 -> 266.93013 | J23: =J12/J8*J17 -> 281.85202 | K23: =K12/K8*K17 -> 299.38405 | L23: =L12/L8*L17 -> 317.13899
C24: Accrued Expenses and Other Current Liabilities | F24: 4401 | G24: 4609 | H24: =H12/H8*H18 -> 4859.5858 | I24: =I12/I8*I18 -> 5142.8538 | J24: =J12/J8*J18 -> 5430.3489 | K24: =K12/K8*K18 -> 5768.1328 | L24: =L12/L8*L18 -> 6110.2112
C25: Net Working Capital | F25: =SUM(F21:F22)-SUM(F23:F24) -> -1980 | G25: =SUM(G21:G22)-SUM(G23:G24) -> -2182 | H25: =SUM(H21:H22)-SUM(H23:H24) -> -2318.73 | I25: =SUM(I21:I22)-SUM(I23:I24) -> -2469.6958 | J25: =SUM(J21:J22)-SUM(J23:J24) -> -2619.5367 | K25: =SUM(K21:K22)-SUM(K23:K24) -> -2789.7438 | L25: =SUM(L21:L22)-SUM(L23:L24) -> -2962.8441
B27: Change in Working Capital | G27: =F25-G25 -> 202 | H27: =G25-H25 -> 136.72998 | I27: =H25-I25 -> 150.96585 | J27: =I25-J25 -> 149.84092 | K27: =J25-K25 -> 170.20708 | L27: =K25-L25 -> 173.10031
B29: Custodial Float
C31: Funds Receivable and Customer Accounts | F31: 37671 | G31: 38198 | H31: =G31*(IS!H8/IS!G8) -> 39514.97 | I31: =H31*(IS!I8/IS!H8) -> 41096.231 | J31: =I31*(IS!J8/IS!I8) -> 42972.814 | K31: =J31*(IS!K8/IS!J8) -> 45189.277 | L31: =K31*(IS!L8/IS!K8) -> 47519.507
C32: Funds Payable to Customers | F32: -39671 | G32: -40198 | H32: =G32*(IS!H8/IS!G8) -> -41583.925 | I32: =H32*(IS!I8/IS!H8) -> -43247.979 | J32: =I32*(IS!J8/IS!I8) -> -45222.818 | K32: =J32*(IS!K8/IS!J8) -> -47555.331 | L32: =K32*(IS!L8/IS!K8) -> -50007.57
C33: Net Float | F33: =F31+F32 -> -2000 | G33: =G31+G32 -> -2000 | H33: =H31+H32 -> -2068.9549 | I33: =I31+I32 -> -2151.7478 | J33: =J31+J32 -> -2250.0034 | K33: =K31+K32 -> -2366.0546 | L33: =L31+L32 -> -2488.0626

Sheet D&A Schedule
K1: ="CURRENTLY RUNNING: "&UPPER(CHOOSE(Scenarios!$C$6,Scenarios!B10,Scenarios!B11,Scenarios!B12))&" SCENARIO" -> CURRENTLY RUNNING: BASE CASE SCENARIO
B2: =Cover!$B$7 -> PayPal
B3: Intangible Assets
B4: ($ Millions)
G5: Projected
E6: =IS!F6 -> 2024 | F6: =IS!G6 -> 2025 | G6: =IS!H6 -> 2026 | H6: =IS!I6 -> 2027 | I6: =IS!J6 -> 2028 | J6: =IS!K6 -> 2029 | K6: =IS!L6 -> 2030
B8: Beginning of Period | E8: 533 | F8: =E11 -> 326 | G8: =F11 -> 208 | H8: =G11 -> 110 | I8: =H11 -> 48 | J8: =I11 -> 0 | K8: =J11 -> 0
C9: Less: Amortization | E9: -207 | F9: -175 | G9: -98 | H9: -62 | I9: -48
C10: Other/Non-Cash | E10: 0 | F10: 57 | G10: 0 | H10: 0 | I10: 0 | J10: 0 | K10: 0
C11: End of Period | E11: 326 | F11: =SUM(F8:F10) -> 208 | G11: =SUM(G8:G10) -> 110 | H11: =SUM(H8:H10) -> 48 | I11: =SUM(I8:I10) -> 0 | J11: =SUM(J8:J10) -> 0 | K11: =SUM(K8:K10) -> 0
B15: =Cover!$B$7 -> PayPal
B16: Property, Plant, & Equipment
B17: ($ Millions)
G18: Projected
E19: =E6 -> 2024 | F19: =F6 -> 2025 | G19: =CFS!H6 -> 2026 | H19: =CFS!I6 -> 2027 | I19: =CFS!J6 -> 2028 | J19: =CFS!K6 -> 2029 | K19: =CFS!L6 -> 2030
B21: Beginning of Period | F21: =E25 -> 1508 | G21: =F25 -> 1700 | H21: =G25 -> 1749.5113 | I21: =H25 -> 1788.1558 | J21: =I25 -> 1815.1303 | K21: =J25 -> 1829.3684
C22: Plus: Capital Expenditure | E22: 683 | F22: 852 | G22: =Assumptions!J59 -> 823.57647 | H22: =Assumptions!K59 -> 856.53333 | I22: =Assumptions!L59 -> 895.64534 | J22: =Assumptions!M59 -> 941.84115 | K22: =Assumptions!N59 -> 990.40814
C23: Less: Depreciation | E23: -825 | F23: -788 | G23: =-G22*G27 -> -774.06521 | H23: =-H22*H27 -> -817.8888 | I23: =-I22*I27 -> -868.67086 | J23: =-J22*J27 -> -927.60299 | K23: =-K22*K27 -> -990.2919
C24: Non-Cash Additions/ Other | F24: 128
C25: End of Period | E25: =BS!F18 -> 1508 | F25: =BS!G18 -> 1700 | G25: =SUM(G21:G24) -> 1749.5113 | H25: =SUM(H21:H24) -> 1788.1558 | I25: =SUM(I21:I24) -> 1815.1303 | J25: =SUM(J21:J24) -> 1829.3684 | K25: =SUM(K21:K24) -> 1829.4847
C27: PP&E related D&A as % of capex | D27: 0.015 | E27: =-(E23/E22) -> 1.2079063 | F27: =-(F23/F22) -> 0.92488263 | G27: =F27+$D$27 -> 0.93988263 | H27: =G27+$D$27 -> 0.95488263 | I27: =H27+$D$27 -> 0.96988263 | J27: =I27+$D$27 -> 0.98488263 | K27: =J27+$D$27 -> 0.99988263
B29: Total D&A | E29: =E23+E9 -> -1032 | F29: =F23+F9 -> -963 | G29: =G23+G9 -> -872.06521 | H29: =H23+H9 -> -879.8888 | I29: =I23+I9 -> -916.67086 | J29: =J23+J9 -> -927.60299 | K29: =K23+K9 -> -990.2919

Sheet Debt Schedule
L1: ="CURRENTLY RUNNING: "&UPPER(CHOOSE(Scenarios!$C$6,Scenarios!B10,Scenarios!B11,Scenarios!B12))&" SCENARIO" -> CURRENTLY RUNNING: BASE CASE SCENARIO
B2: =Cover!$B$7 -> PayPal
B3: Debt and Interest Schedule
B4: ($ Millions)
H5: Projected
G6: ='D&A Schedule'!F19 -> 2025 | H6: ='Income Tax Schedule'!H6 -> 2026 | I6: ='Income Tax Schedule'!I6 -> 2027 | J6: ='Income Tax Schedule'!J6 -> 2028 | K6: ='Income Tax Schedule'!K6 -> 2029 | L6: ='Income Tax Schedule'!L6 -> 2030
B7: Financing Component
C8: Cash
C9: Amount Outstanding - Beginning | H9: =G11 -> 10422 | I9: =H11 -> 10036.887 | J9: =I11 -> 9915.6645 | K9: =J11 -> 9828.9614 | L9: =K11 -> 9630.3134
C10: Change in Cash | H10: =CFS!H31 -> -385.113 | I10: =CFS!I31 -> -121.2225 | J10: =CFS!J31 -> -86.703086 | K10: =CFS!K31 -> -198.64803 | L10: =CFS!L31 -> 672.76588
C11: Amount Outstanding - Ending | G11: =BS!G9 -> 10422 | H11: =SUM(H9:H10) -> 10036.887 | I11: =SUM(I9:I10) -> 9915.6645 | J11: =SUM(J9:J10) -> 9828.9614 | K11: =SUM(K9:K10) -> 9630.3134 | L11: =SUM(L9:L10) -> 10303.079
C13: Interest Rate | H13: =Assumptions!N28 -> 0.03 | I13: =H13 -> 0.03 | J13: =I13 -> 0.03 | K13: =J13 -> 0.03 | L13: =K13 -> 0.03
C14: Annual Interest Income | H14: =H13*H9 -> 312.66 | I14: =I13*I9 -> 301.10661 | J14: =J13*J9 -> 297.46993 | K14: =K13*K9 -> 294.86884 | L14: =L13*L9 -> 288.9094
C16: Revolver
C17: Operating Cash Flow | H17: =CFS!H16 -> 7466.422 | I17: =CFS!I16 -> 7426.2354 | J17: =CFS!J16 -> 7550.6885 | K17: =CFS!K16 -> 7842.2969 | L17: =CFS!L16 -> 8228.5418
C18: Investing Cash Flow | H18: =CFS!H21 -> -2373.1311 | I18: =CFS!I21 -> -2717.0548 | J18: =CFS!J21 -> -3103.6451 | K18: =CFS!K21 -> -3549.744 | L18: =CFS!L21 -> -3732.1716
C19: Mandatory Debt Repayments | H19: =H33 -> -1397 | I19: =I33 -> -1075 | J19: =J33 -> -1137 | K19: =K33 -> -1500 | L19: =L33 -> -1000
C20: Common Stock Issuance / (Buy-back) | H20: =IS!G269 -> 0 | I20: =IS!H269 -> 0 | J20: =IS!I269 -> 0 | K20: =IS!J269 -> 0 | L20: =IS!K269 -> 0
C21: Dividends | I21: =BS!H31 -> 0 | J21: =BS!I31 -> 0 | K21: =BS!J31 -> 0 | L21: =BS!K31 -> 0
C22: FCF After Mandatory Debt Repayment and Dividend | H22: =SUM(H17:H21) -> 3696.2909 | I22: =SUM(I17:I21) -> 3634.1807 | J22: =SUM(J17:J21) -> 3310.0434 | K22: =SUM(K17:K21) -> 2792.5529 | L22: =SUM(L17:L21) -> 3496.3702
C24: Revolver Outstanding - Beginning | H24: =G26 -> 0 | I24: =H26 -> 0 | J24: =I26 -> 0 | K24: =J26 -> 0 | L24: =K26 -> 0
C25: Additions / (Repayments) | H25: =-MIN((H22+H9),H24) -> 0 | I25: =-MIN((I22+I9),I24) -> 0 | J25: =-MIN((J22+J9),J24) -> 0 | K25: =-MIN((K22+K9),K24) -> 0 | L25: =-MIN((L22+L9),L24) -> 0
C26: Revolver Outstanding - Ending | G26: 0 | H26: =SUM(H24:H25) -> 0 | I26: =SUM(I24:I25) -> 0 | J26: =SUM(J24:J25) -> 0 | K26: =SUM(K24:K25) -> 0 | L26: =SUM(L24:L25) -> 0
C28: Interest Rate | H28: 0.045 | I28: =H28 -> 0.045 | J28: =I28 -> 0.045 | K28: =J28 -> 0.045 | L28: =K28 -> 0.045
C29: Annual Interest Expense | H29: =H28*H24 -> 0 | I29: =I28*I24 -> 0 | J29: =J28*J24 -> 0 | K29: =K28*K24 -> 0 | L29: =L28*L24 -> 0
C31: Term Debt
C32: Amount Outstanding - Beginning | H32: =G34 -> 11383 | I32: =H34 -> 9986 | J32: =I34 -> 8911 | K32: =J34 -> 7774 | L32: =K34 -> 6274
C33: Additions / (Repayments) | H33: =-Assumptions!H45 -> -1397 | I33: =-Assumptions!H46 -> -1075 | J33: =-Assumptions!H47 -> -1137 | K33: =-Assumptions!H48 -> -1500 | L33: =-Assumptions!H49 -> -1000
C34: Amount Outstanding - Ending | G34: =BS!G35+BS!G31 -> 11383 | H34: =SUM(H32:H33) -> 9986 | I34: =SUM(I32:I33) -> 8911 | J34: =SUM(J32:J33) -> 7774 | K34: =SUM(K32:K33) -> 6274 | L34: =SUM(L32:L33) -> 5274
C36: Interest Rate | H36: =Assumptions!N30 -> 0.039 | I36: =H36 -> 0.039 | J36: =I36 -> 0.039 | K36: =J36 -> 0.039 | L36: =K36 -> 0.039
C37: Annual Interest Expense | H37: =H36*H32 -> 443.937 | I37: =I36*I32 -> 389.454 | J37: =J36*J32 -> 347.529 | K37: =K36*K32 -> 303.186 | L37: =L36*L32 -> 244.686
C39: Net Interest Expense | H39: =H14-H37 -> -131.277 | I39: =I14-I37 -> -88.34739 | J39: =J14-J37 -> -50.059065 | K39: =K14-K37 -> -8.3171577 | L39: =L14-L37 -> 44.223401

Sheet Income Tax Schedule
L1: ="CURRENTLY RUNNING: "&UPPER(CHOOSE(Scenarios!$C$6,Scenarios!B10,Scenarios!B11,Scenarios!B12))&" SCENARIO" -> CURRENTLY RUNNING: BASE CASE SCENARIO
B2: =Cover!$B$7 -> PayPal
B3: Income Tax Schedule
B4: ($ Millions)
H5: Projected
C6: Tax Rate | E6: 0.21 | H6: ='D&A Schedule'!G19 -> 2026 | I6: ='D&A Schedule'!H19 -> 2027 | J6: ='D&A Schedule'!I19 -> 2028 | K6: ='D&A Schedule'!J19 -> 2029 | L6: ='D&A Schedule'!K19 -> 2030
C9: Accounting EBT (as is on I/S) | G9: A | H9: =IS!H22 -> 6348.1594 | I9: =IS!I22 -> 6340.7512 | J9: =IS!J22 -> 6483.3565 | K9: =IS!K22 -> 6813.9772 | L9: =IS!L22 -> 7162.7734
C11: Less: Reduction in EBT for timing differences | H11: =Assumptions!J62 -> 1144.4047 | I11: =Assumptions!K62 -> 759.74868 | J11: =Assumptions!L62 -> 504.38283 | K11: =Assumptions!M62 -> 334.85025 | L11: =Assumptions!N62 -> 222.30077
C12: Government EBT | G12: B | H12: =H9-H11 -> 5203.7548 | I12: =I9-I11 -> 5581.0025 | J12: =J9-J11 -> 5978.9737 | K12: =K9-K11 -> 6479.1269 | L12: =L9-L11 -> 6940.4726
C14: =CONCATENATE("Accounting Taxes (",$E$6*100,"% of A)") -> Accounting Taxes (21% of A) | H14: =$E$6*H9 -> 1333.1135 | I14: =$E$6*I9 -> 1331.5577 | J14: =$E$6*J9 -> 1361.5049 | K14: =$E$6*K9 -> 1430.9352 | L14: =$E$6*L9 -> 1504.1824
C16: Taxes as Appearing on Income Statement
C17: =CONCATENATE("Current Tax (",$E$6*100,"% of B)") -> Current Tax (21% of B) | H17: =$E$6*H12 -> 1092.7885 | I17: =$E$6*I12 -> 1172.0105 | J17: =$E$6*J12 -> 1255.5845 | K17: =$E$6*K12 -> 1360.6167 | L17: =$E$6*L12 -> 1457.4992
C18: Increase (Decrease) in Deferred Income Taxes | H18: =H14-H17 -> 240.32498 | I18: =I14-I17 -> 159.54722 | J18: =J14-J17 -> 105.92039 | K18: =K14-K17 -> 70.318553 | L18: =L14-L17 -> 46.683162
C19: Total Income Taxes (Same as Accounting Taxes Above) | H19: =SUM(H17:H18) -> 1333.1135 | I19: =SUM(I17:I18) -> 1331.5577 | J19: =SUM(J17:J18) -> 1361.5049 | K19: =SUM(K17:K18) -> 1430.9352 | L19: =SUM(L17:L18) -> 1504.1824

Sheet Equity Schedule
L1: ="CURRENTLY RUNNING: "&UPPER(CHOOSE(Scenarios!$C$6,Scenarios!B10,Scenarios!B11,Scenarios!B12))&" SCENARIO" -> CURRENTLY RUNNING: BASE CASE SCENARIO
B2: =Cover!$B$7 -> PayPal
B3: Equity Schedule
B4: ($ Millions)
H5: Projected
G6: ='D&A Schedule'!F19 -> 2025 | H6: ='Income Tax Schedule'!H6 -> 2026 | I6: ='Income Tax Schedule'!I6 -> 2027 | J6: ='Income Tax Schedule'!J6 -> 2028 | K6: ='Income Tax Schedule'!K6 -> 2029 | L6: ='Income Tax Schedule'!L6 -> 2030
B7: Common Shares
C8: Amount Outstanding - Beginning | H8: =G10 -> 920 | I8: =H10 -> 834.5153 | J8: =I10 -> 749.0306 | K8: =J10 -> 663.54591 | L8: =K10 -> 578.06121
C9: New Issuance / (Buy-Back) | H9: =5000000000/Assumptions!$N$10/1000000 -> 85.484698 | I9: =5000000000/Assumptions!$N$10/1000000 -> 85.484698 | J9: =5000000000/Assumptions!$N$10/1000000 -> 85.484698 | K9: =5000000000/Assumptions!$N$10/1000000 -> 85.484698 | L9: =5000000000/Assumptions!$N$10/1000000 -> 85.484698
C10: Amount Outstanding - Ending | G10: 920 | H10: =H8-H9 -> 834.5153 | I10: =I8-I9 -> 749.0306 | J10: =J8-J9 -> 663.54591 | K10: =K8-K9 -> 578.06121 | L10: =L8-L9 -> 492.57651
C12: Dividend/ Share | H12: 0.56 | I12: =H12 -> 0.56 | J12: =I12 -> 0.56 | K12: =J12 -> 0.56 | L12: =K12 -> 0.56
C13: Common Dividend | H13: =H12*H10 -> 467.32857 | I13: =I12*I10 -> 419.45714 | J13: =J12*J10 -> 371.58571 | K13: =K12*K10 -> 323.71428 | L13: =L12*L10 -> 275.84284
B15: Retained Earnings
C16: Amount Outstanding - Beginning | H16: =G19 -> 32470 | I16: =H19 -> 37258.042 | J16: =I19 -> 42007.326 | K16: =J19 -> 46863.512 | L16: =K19 -> 51993.158
C17: Net Income | H17: =IS!H25 -> 5255.3709 | I17: =IS!I25 -> 5168.7406 | J17: =IS!J25 -> 5227.7721 | K17: =IS!K25 -> 5453.3605 | L17: =IS!L25 -> 5705.2741
C18: Common Dividend | H18: =-H13 -> -467.32857 | I18: =-I13 -> -419.45714 | J18: =-J13 -> -371.58571 | K18: =-K13 -> -323.71428 | L18: =-L13 -> -275.84284
C19: Amount Outstanding - Ending | G19: =BS!G42 -> 32470 | H19: =SUM(H16:H18) -> 37258.042 | I19: =SUM(I16:I18) -> 42007.326 | J19: =SUM(J16:J18) -> 46863.512 | K19: =SUM(K16:K18) -> 51993.158 | L19: =SUM(L16:L18) -> 57422.59
H21: Projected
G22: =G6 -> 2025 | H22: =H6 -> 2026 | I22: =I6 -> 2027 | J22: =J6 -> 2028 | K22: =K6 -> 2029 | L22: =L6 -> 2030
B24: Earnings Per Share
C25: Net Income | G25: =IS!G25 -> 5233 | H25: =IS!H25 -> 5255.3709 | I25: =IS!I25 -> 5168.7406 | J25: =IS!J25 -> 5227.7721 | K25: =IS!K25 -> 5453.3605 | L25: =IS!L25 -> 5705.2741
C26: Basic Shares | G26: =Assumptions!N9 -> 920.664 | H26: =(H10+H8)/2 -> 877.25765 | I26: =(I10+I8)/2 -> 791.77295 | J26: =(J10+J8)/2 -> 706.28825 | K26: =(K10+K8)/2 -> 620.80356 | L26: =(L10+L8)/2 -> 535.31886
C27: Basic EPS | G27: =G25/G26 -> 5.6839412 | H27: =H25/H26 -> 5.9906812 | I27: =I25/I26 -> 6.5280591 | J27: =J25/J26 -> 7.4017542 | K27: =K25/K26 -> 8.7843578 | L27: =L25/L26 -> 10.657712
C29: Diluted Shares | G29: =G26+Assumptions!N11 -> 952.421 | H29: =(G29-G26)+H26 -> 909.01465 | I29: =(H29-H26)+I26 -> 823.52995 | J29: =(I29-I26)+J26 -> 738.04525 | K29: =(J29-J26)+K26 -> 652.56056 | L29: =(K29-K26)+L26 -> 567.07586
C30: Diluted EPS | G30: =G25/G29 -> 5.494419 | H30: =H25/H29 -> 5.781393 | I30: =I25/I29 -> 6.2763238 | J30: =J25/J29 -> 7.0832676 | K30: =K25/K29 -> 8.3568651 | L30: =L25/L29 -> 10.060866
C32: $ amount of shares repurchased | H32: =H9*Assumptions!$N$10 -> 5000 | I32: =I9*Assumptions!$N$10 -> 5000 | J32: =J9*Assumptions!$N$10 -> 5000 | K32: =K9*Assumptions!$N$10 -> 5000 | L32: =L9*Assumptions!$N$10 -> 5000
C33: $ amount of new shares issued | H33: =IS!H30 -> 1166.7333 | I33: =IS!I30 -> 1213.4222 | J33: =IS!J30 -> 1268.8309 | K33: =IS!K30 -> 1334.275 | L33: =IS!L30 -> 1403.0782
C34: Target P/E | H34: 8 | I34: 8 | J34: 8 | K34: 8 | L34: 8
C35: Avg price (share count only) | H35: =(H25/G26)*H34 -> 45.665919 | I35: =(I25/H26)*I34 -> 47.13544 | J35: =(J25/I26)*J34 -> 52.820921 | K35: =(K25/J26)*K34 -> 61.769234 | L35: =(L25/K26)*L34 -> 73.521152

Sheet DCF
I1: ="CURRENTLY RUNNING: "&UPPER(CHOOSE(Scenarios!$C$6,Scenarios!B10,Scenarios!B11,Scenarios!B12))&" SCENARIO" -> CURRENTLY RUNNING: BASE CASE SCENARIO
B2: =Cover!B7 -> PayPal
B3: Discounted Cash Flow Analysis
B4: ($ Millions)
B6: Most recent fiscal year end | C6: 46022 | G6: Discount rate (WACC) | I6: =E53 -> 0.095880549
B7: End of first fiscal year | C7: 46387 | G7: Share price | I7: =Assumptions!N7 -> 45.47
B8: Most recent quarter end date | G8: Share price date | I8: =Assumptions!N8 -> 46208
B9: Valuation date | C9: 46204 | G9: Midyear adjustment? | I9: 0
B10: Portion of First Year Cash Flows | C10: =1-YEARFRAC(C9,C7) -> 0.5
B12: Unlevered Free Cash Flows | E12: Projected
B13: Fiscal year | D13: ='Equity Schedule'!G6 -> 2025 | E13: ='Equity Schedule'!H6 -> 2026 | F13: ='Equity Schedule'!I6 -> 2027 | G13: ='Equity Schedule'!J6 -> 2028 | H13: ='Equity Schedule'!K6 -> 2029 | I13: ='Equity Schedule'!L6 -> 2030
B14: Year Ended | D14: =C6 -> 46022 | E14: =EOMONTH(D14,12) -> 46387 | F14: =EOMONTH(E14,12) -> 46752 | G14: =EOMONTH(F14,12) -> 47118 | H14: =EOMONTH(G14,12) -> 47483 | I14: =EOMONTH(H14,12) -> 47848
B16: Revenue | D16: =IS!G8 -> 33172 | E16: =IS!H8 -> 34315.686 | F16: =IS!I8 -> 35688.889 | G16: =IS!J8 -> 37318.556 | H16: =IS!K8 -> 39243.381 | I16: =IS!L8 -> 41267.006
B17: % growth | E17: =E16/D16-1 -> 0.034477453 | F17: =F16/E16-1 -> 0.04001676 | G17: =G16/F16-1 -> 0.045663156 | H17: =H16/G16-1 -> 0.05157824 | I17: =I16/H16-1 -> 0.051566007
B18: EBITDA | D18: =IS!G28 -> 7028 | E18: =IS!H28 -> 7146.835 | F18: =IS!I28 -> 7104.3207 | G18: =IS!J28 -> 7245.4198 | H18: =IS!K28 -> 7545.2307 | I18: =IS!L28 -> 7904.1752
B19: % margin | D19: =D18/D16 -> 0.21186543 | E19: =E18/E16 -> 0.20826729 | F19: =F18/F16 -> 0.19906254 | G19: =G18/G16 -> 0.19415059 | H19: =H18/H16 -> 0.1922676 | I19: =I18/I16 -> 0.1915374
B20: EBIT | D20: =IS!G18 -> 6065 | E20: =IS!H18 -> 6274.7698 | F20: =IS!I18 -> 6224.4319 | G20: =IS!J18 -> 6328.7489 | H20: =IS!K18 -> 6617.6277 | I20: =IS!L18 -> 6913.8833
B21: % margin | D21: =D20/D16 -> 0.18283492 | E21: =E20/E16 -> 0.18285427 | F21: =F20/F16 -> 0.17440812 | G21: =G20/G16 -> 0.16958719 | H21: =H20/H16 -> 0.16863041 | I21: =I20/I16 -> 0.16754022
B23: Tax on EBIT | D23: =D20*Assumptions!$N$39 -> 1273.65 | E23: =E20*Assumptions!$N$39 -> 1317.7016 | F23: =F20*Assumptions!$N$39 -> 1307.1307 | G23: =G20*Assumptions!$N$39 -> 1329.0373 | H23: =H20*Assumptions!$N$39 -> 1389.7018 | I23: =I20*Assumptions!$N$39 -> 1451.9155
B24: Tax rate | D24: =Assumptions!$N$39 -> 0.21 | E24: =Assumptions!$N$39 -> 0.21 | F24: =Assumptions!$N$39 -> 0.21 | G24: =Assumptions!$N$39 -> 0.21 | H24: =Assumptions!$N$39 -> 0.21 | I24: =Assumptions!$N$39 -> 0.21
B25: NOPAT (aka EBIAT) | D25: =D20*(1-D24) -> 4791.35 | E25: =E20*(1-E24) -> 4957.0681 | F25: =F20*(1-F24) -> 4917.3012 | G25: =G20*(1-G24) -> 4999.7117 | H25: =H20*(1-H24) -> 5227.9259 | I25: =I20*(1-I24) -> 5461.9678
B27: Depreciation & amortization | E27: =-('D&A Schedule'!G29) -> 872.06521 | F27: =-('D&A Schedule'!H29) -> 879.8888 | G27: =-('D&A Schedule'!I29) -> 916.67086 | H27: =-('D&A Schedule'!J29) -> 927.60299 | I27: =-('D&A Schedule'!K29) -> 990.2919
B28: Changes in net working capital | E28: =(SUM(BS!G10:G14)-SUM(BS!H10:H14))+(SUM(BS!H28:H31)-SUM(BS!G28:G31)) -> -1482.4081 | F28: =(SUM(BS!H10:H14)-SUM(BS!I10:I14))+(SUM(BS!I28:I31)-SUM(BS!H28:H31)) -> -116.95189 | G28: =(SUM(BS!I10:I14)-SUM(BS!J10:J14))+(SUM(BS!J28:J31)-SUM(BS!I28:I31)) -> -168.11419 | H28: =(SUM(BS!J10:J14)-SUM(BS!K10:K14))+(SUM(BS!K28:K31)-SUM(BS!J28:J31)) -> -205.33465 | I28: =(SUM(BS!K10:K14)-SUM(BS!L10:L14))+(SUM(BS!L28:L31)-SUM(BS!K28:K31)) -> -221.71754
B29: Capital expenditures | E29: ='D&A Schedule'!G22 -> 823.57647 | F29: ='D&A Schedule'!H22 -> 856.53333 | G29: ='D&A Schedule'!I22 -> 895.64534 | H29: ='D&A Schedule'!J22 -> 941.84115 | I29: ='D&A Schedule'!K22 -> 990.40814
B30: as % of revenue | E30: =E29/E16 -> 0.024 | F30: =F29/F16 -> 0.024 | G30: =G29/G16 -> 0.024 | H30: =H29/H16 -> 0.024 | I30: =I29/I16 -> 0.024
B32: Unlevered free cash flows (UFCF) | E32: =E25+E27+E28-E29 -> 3523.1488 | F32: =F25+F27+F28-F29 -> 4823.7048 | G32: =G25+G27+G28-G29 -> 4852.623 | H32: =H25+H27+H28-H29 -> 5008.3531 | I32: =I25+I27+I28-I29 -> 5240.134
B34: Net working capital (WC Assets - WC liabilities) | E34: =SUM(BS!H10:H14)-SUM(BS!H28:H31) -> 4376.4081 | F34: =SUM(BS!I10:I14)-SUM(BS!I28:I31) -> 4493.36 | G34: =SUM(BS!J10:J14)-SUM(BS!J28:J31) -> 4661.4742 | H34: =SUM(BS!K10:K14)-SUM(BS!K28:K31) -> 4866.8088 | I34: =SUM(BS!L10:L14)-SUM(BS!L28:L31) -> 5088.5264
B35: as % of revenue | E35: =E34/E16 -> 0.12753375 | F35: =F34/F16 -> 0.12590361 | G35: =G34/G16 -> 0.12491036 | H35: =H34/H16 -> 0.12401604 | I35: =I34/I16 -> 0.12330738
B37: Weighted Average Cost of Capital
B39: Risk free rate (Rf) | E39: 0.0437
B40: Equity Beta | E40: 1.34
B41: Equity risk premium (Rm - Rf) | E41: 0.05
B42: Cost of Equity (Ke) | E42: =E39+E40*E41 -> 0.1107
B44: Cost of debt | E44: 0.05
B45: Tax rate | E45: =Assumptions!N39 -> 0.21
B46: After-tax Cost of Debt (Kdt) | E46: =E44*(1-E45) -> 0.0395
B48: Percentage of Capital
B49: Debt | D49: ='Debt Schedule'!H32 -> 11383 | E49: =D49/D51 -> 0.20813836
B50: Equity | D50: ='Equity Schedule'!G29*(Assumptions!$N$7) -> 43306.583 | E50: =D50/D51 -> 0.79186164
B51: Total capital | D51: =SUM(D49:D50) -> 54689.583 | E51: =SUM(E49:E50) -> 1
B53: Weighted Average Cost of Capital | E53: =E42*E50+E46*E49 -> 0.095880549
B55: ="Present value of UFCF on "&TEXT(C9,"mmm dd, yyyy")&" valuation date" -> Present value of UFCF on Jul 01, 2026 valuation date
D56: Val date | E56: Yr 1 - Stub | F56: Year 2 | G56: Year 3 | H56: Year 4 | I56: Year 5
B57: Date for discounting cash flows | D57: =C9 -> 46204 | E57: =IF($I$9=1,AVERAGE(E14,$D$57),E14) -> 46387 | F57: =IF($I$9=1,AVERAGE(F14,$D$57),F14) -> 46752 | G57: =IF($I$9=1,AVERAGE(G14,$D$57),G14) -> 47118 | H57: =IF($I$9=1,AVERAGE(H14,$D$57),H14) -> 47483 | I57: =IF($I$9=1,AVERAGE(I14,$D$57),I14) -> 47848
B58: Unlevered free cash flows (UFCF) stub adjusted | C58: =C10 -> 0.5 | E58: =E32*C58 -> 1761.5744 | F58: =F32 -> 4823.7048 | G58: =G32 -> 4852.623 | H58: =H32 -> 5008.3531 | I58: =I32 -> 5240.134
B59: Present value of of unlevered free cash flows | E59: =E58/(1+$I$6)^((E57-$C$9)/365) -> 1682.5381 | F59: =F58/(1+$I$6)^((F57-$C$9)/365) -> 4204.1812 | G59: =G58/(1+$I$6)^((G57-$C$9)/365) -> 3858.3809 | H59: =H58/(1+$I$6)^((H57-$C$9)/365) -> 3633.7936 | I59: =I58/(1+$I$6)^((I57-$C$9)/365) -> 3469.3211
B61: Terminal value - growth in perpetuity approach | E61: Terminal value - EBITDA multiple approach
B62: Long term growth rate | C62: 0.005 | E62: Terminal year EBITDA | I62: =I18 -> 7904.1752
B63: =YEAR(I14)&" FCF x (1+g)" -> 2030 FCF x (1+g) | C63: =I58*(1+C62) -> 5266.3347 | E63: EBITDA multiple | I63: 7
B64: ="Terminal value in "&YEAR(I14) -> Terminal value in 2030 | C64: =C63/(I6-C62) -> 57947.875 | E64: ="Terminal value in "&YEAR(I14) -> Terminal value in 2030 | I64: =I62*I63 -> 55329.226
B65: Present value of terminal value | C65: =C64/(1+I6)^((I14-$D$57)/365) -> 38365.39 | E65: Present value of terminal value | I65: =I64/(1+I6)^((I14-D57)/365) -> 36631.669
B66: Present value of stage 1 cash flows | C66: =SUM(E59:I59) -> 16848.215 | E66: Present value of stage 1 cash flows | I66: =C66 -> 16848.215
B67: Total enterprise value (TEV) | C67: =C66+C65 -> 55213.605 | E67: Enterprise value (stage 1 + 2) | I67: =SUM(I65:I66) -> 53479.884
B69: Terminal value as % of TEV | C69: =C65/$C$67 -> 0.69485393 | E69: Terminal value as % of TEV | I69: =+I65/I67 -> 0.68496164
B70: Stage 1 cash flows as % of TEV | C70: =1-C69 -> 0.30514607 | E70: Cash flows as % of TEV | I70: =1-I69 -> 0.31503836
B71: Implied TV exit EBITDA multiple | C71: =(C64/I18) -> 7.3312994 | E71: Implied long term growth rate | I71: =(I6-I58/I64)/(1+I58/I64) -> 0.0010708809
B73: Net debt
B74: Source doc | C74: PayPal 10-K 2026
B75: Source date | C75: =C9 -> 46204
B76: Gross debt and equivalents
B77: Debt | C77: =D49 -> 11383
B78: Convertible debt | C78: 0
B79: Preferred stock | C79: 0
B80: Noncontrolling (minority) interests | C80: 0
B81: Nonoperating assets
B82: Cash | C82: =BS!G9 -> 10422
B83: Long-Term Investments | C83: =BS!G17 -> 4330
B85: Net debt | C85: =SUM(C77:C80)-SUM(C82:C83) -> -3369
B87: Net diluted shares outstanding | C87: ='Equity Schedule'!G29 -> 952.421
B89: Valuation
C90: Perpetuity | D90: EBITDA
B91: Enterprise value | C91: =C67 -> 55213.605 | D91: =I67 -> 53479.884
B92: Net debt | C92: =$C$85 -> -3369 | D92: =$C$85 -> -3369
B93: Equity value | C93: =C91-C92 -> 58582.605 | D93: =D91-D92 -> 56848.884
B94: Shares outstanding | C94: =$C$87 -> 952.421 | D94: =$C$87 -> 952.421
B95: Equity value per share | C95: =C93/C94 -> 61.509149 | D95: =D93/D94 -> 59.688818
C97: Last Twelve Months (LTM)
C98: Perpetuity | D98: EBITDA
B99: EV / Revenue | C99: =C91/$D$16 -> 1.6644642 | D99: =D91/$D$16 -> 1.6121996
B100: EV / EBITDA | C100: =C91/$D$18 -> 7.8562329 | D100: =D91/$D$18 -> 7.6095452
B101: EV / EBIT | C101: =C91/$D$20 -> 9.1036447 | D101: =D91/$D$20 -> 8.8177879
C103: Year 1
C104: Perpetuity | D104: EBITDA
B105: EV / Revenue | C105: =C91/$E$16 -> 1.6089903 | D105: =D91/$E$16 -> 1.5584676
B106: EV / EBITDA | C106: =C91/$E$18 -> 7.7256024 | D106: =D91/$E$18 -> 7.4830164
B107: EV / EBIT | C107: =C91/$E$20 -> 8.7993038 | D107: =D91/$E$20 -> 8.5230033
B109: Sensitivity Analysis
D111: Equity Value Per Share
D112: Long Term Growth Rate
C113: =C95 -> 61.509149 | D113: =E113-0.005 -> -0.005 | E113: =F113-0.005 -> 0 | F113: 0.005 | G113: =F113+0.005 -> 0.01 | H113: =G113+0.005 -> 0.015
C114: =C115+0.005 -> 0.102 | D114: 53.999538 | E114: 55.792993 | F114: 57.771341 | G114: 59.964726 | H114: 62.410225
C115: =C116+0.005 -> 0.097 | D115: 56.549342 | E115: 58.559467 | F115: 60.788084 | G115: 63.272864 | H115: 66.060666
B116: WACC | C116: 0.092 | D116: 59.363395 | E116: 61.627974 | F116: 64.15285 | G116: 66.985638 | H116: 70.18632
C117: =C116-0.005 -> 0.087 | D117: 62.484809 | E117: 65.050616 | F117: 67.929327 | G117: 71.181897 | H117: 74.886212
C118: 0.116 | D118: 47.986863 | E118: 49.321058 | F118: 50.775452 | G118: 52.367052 | H118: 54.116237
D120: Equity Value Per Share
D121: Exit EBITDA Multiple
C122: =D95 -> 59.688818 | D122: =E122-0.5 -> 6 | E122: =F122-0.5 -> 6.5 | F122: 7 | G122: =F122+0.5 -> 7.5 | H122: =G122+0.5 -> 8
C123: =C124+0.005 -> 0.102 | D123: 53.116002 | E123: 55.795214 | F123: 58.474426 | G123: 61.153638 | H123: 63.83285
C124: =C125+0.005 -> 0.097 | D124: 53.994695 | E124: 56.72935 | F124: 59.464005 | G124: 62.19866 | H124: 64.933315
...

Sheet Comps
M1: ="CURRENTLY RUNNING: "&UPPER(CHOOSE(Scenarios!$C$6,Scenarios!B10,Scenarios!B11,Scenarios!B12))&" SCENARIO" -> CURRENTLY RUNNING: BASE CASE SCENARIO
B2: =Cover!B7 -> PayPal
B3: Comps Analysis
B4: ($ Millions)
B6: Enterprise Value | H6: Enterprise Value Multiples
B8: ="Amounts in millions as of "&TEXT(Assumptions!N8,"mmmm d, yyyy") -> Amounts in millions as of July 5, 2026 | I8: =J8-1 -> 2024 | J8: ='Equity Schedule'!G6 -> 2025 | K8: LTM | L8: ='Equity Schedule'!H6 -> 2026 | M8: ='Equity Schedule'!I6 -> 2027
B10: Share price | F10: =Assumptions!N7 -> 45.47 | H10: Revenue | I10: =IS!F8 -> 31797 | J10: =IS!G8 -> 33172 | K10: =Assumptions!J73 -> 33734 | L10: =IS!H8 -> 34315.686 | M10: =IS!I8 -> 35688.889
B11: Diluted Shares | F11: =Assumptions!N11+Assumptions!N9 -> 952.421 | H11: EBITDA | I11: =IS!F28 -> 6357 | J11: =IS!G28 -> 7028 | K11: =Assumptions!J74 -> 6752 | L11: =IS!H28 -> 7146.835 | M11: =IS!I28 -> 7104.3207
B12: Equity Value | F12: =F10 * F11 -> 43306.583 | H12: EV / Revenue | I12: =$F$15/I10 -> 1.3921937 | J12: =$F$15/J10 -> 1.3344864 | K12: =$F$15/K10 -> 1.3122542 | L12: =$F$15/L10 -> 1.2900101 | M12: =$F$15/M10 -> 1.2403744
B13: Total Debt | F13: =BS!G35+BS!G31 -> 11383 | H13: EV / EBITDA | I13: =$F$15/I11 -> 6.9635965 | J13: =$F$15/J11 -> 6.2987454 | K13: =$F$15/K11 -> 6.5562178 | L13: =$F$15/L11 -> 6.1940122 | M13: =$F$15/M11 -> 6.2310789
B14: Cash | F14: =BS!G9 -> 10422 | H14: ="LTM = FY"&J8 -> LTM = FY2025
B15: Enterprise Value | F15: =F12+F13-F14 -> 44267.583
F18: Market | G18: Enterprise | H18: Enterprise Value / Revenue | K18: Enterprise Value / EBITDA
B19: Company | F19: Value | G19: Value | H19: =I19-1 -> 2024 | I19: =J8 -> 2025 | J19: LTM | K19: =L19-1 -> 2024 | L19: =I19 -> 2025 | M19: LTM
B21: Block | F21: 32668.7 | G21: 34408.6 | H21: =$G$21/H22 -> 1.4264938 | I21: =$G$21/I22 -> 1.4222132 | J21: =$G$21/J22 -> 1.4056547 | K21: =$G$21/K23 -> 25.571195 | L21: =$G$21/L23 -> 16.618498 | M21: =$G$21/M23 -> 21.835639
B22: Revenue | H22: 24121.1 | I22: 24193.7 | J22: 24478.7
B23: EBITDA | K23: 1345.6 | L23: 2070.5 | M23: 1575.8
B25: Adyen | F25: 28461.3 | G25: 16159.7 | H25: =$G$25/H26 -> 8.0201003 | I25: =$G$25/I26 -> 6.8000757 | J25: =$G$25/J26 -> 6.8000757 | K25: =$G$25/K27 -> 16.926469 | L25: =$G$25/L27 -> 13.500167 | M25: =$G$25/M27 -> 13.500167
B26: Revenue | H26: 2014.9 | I26: 2376.4 | J26: 2376.4
B27: EBITDA | K27: 954.7 | L27: 1197 | M27: 1197
B29: Fiserv | F29: 33664.1 | G29: 61880.1 | H29: =$G$29/H30 -> 3.0250342 | I29: =$G$29/I30 -> 2.9198367 | J29: =$G$29/J30 -> 2.9340967 | K29: =$G$29/K31 -> 6.895487 | L29: =$G$29/L31 -> 6.9849983 | M29: =$G$29/M31 -> 7.3930824
B30: Revenue | H30: 20456 | I30: 21193 | J30: 21090
B31: EBITDA | K31: 8974 | L31: 8859 | M31: 8370
B33: Global Payments | F33: 25898.1 | G33: 37111.2 | H33: =$G$33/H34 -> 4.7972079 | I33: =$G$33/I34 -> 4.8159462 | J33: =$G$33/J34 -> 4.1908935 | K33: =$G$33/K35 -> 10.971206 | L33: =$G$33/L35 -> 10.790963 | M33: =$G$33/M35 -> 9.4666599
B34: Revenue | H34: 7736 | I34: 7705.9 | J34: 8855.2
B35: EBITDA | K35: 3382.6 | L35: 3439.1 | M35: 3920.2
B37: Fidelity National Information Services | F37: 24748 | G37: 37483 | H37: =$G$37/H38 -> 3.7012936 | I37: =$G$37/I38 -> 3.5106303 | J37: =$G$37/J38 -> 3.276486 | K37: =$G$37/K39 -> 11.971575 | L37: =$G$37/L39 -> 11.941064 | M37: =$G$37/M39 -> 11.331016
B38: Revenue | H38: 10127 | I38: 10677 | J38: 11440
B39: EBITDA | K39: 3131 | L39: 3139 | M39: 3308
B41: Shift4 | F41: 3082.1 | G41: 8222.1 | H41: =$G$41/H42 -> 2.4683579 | I41: =$G$41/I42 -> 1.9670096 | J41: =$G$41/J42 -> 1.8464181 | K41: =$G$41/K43 -> 15.141989 | L41: =$G$41/L43 -> 10.487372 | M41: =$G$41/M43 -> 9.6616921
B42: Revenue | H42: 3331 | I42: 4180 | J42: 4453
B43: EBITDA | K43: 543 | L43: 784 | M43: 851
B46: Source: Koyfin | G46: High | H46: =MAX(H21,H25,H29,H33,H37,H41) -> 8.0201003 | I46: =MAX(I21,I25,I29,I33,I37,I41) -> 6.8000757 | J46: =MAX(J21,J25,J29,J33,J37,J41) -> 6.8000757 | K46: =MAX(K21,K25,K29,K33,K37,K41) -> 25.571195 | L46: =MAX(L21,L25,L29,L33,L37,L41) -> 16.618498 | M46: =MAX(M21,M25,M29,M33,M37,M41) -> 21.835639
G47: Mean | H47: =AVERAGE(H21,H25,H29,H33,H37,H41) -> 3.9064146 | I47: =AVERAGE(I21,I25,I29,I33,I37,I41) -> 3.5726186 | J47: =AVERAGE(J21,J25,J29,J33,J37,J41) -> 3.4089375 | K47: =AVERAGE(K21,K25,K29,K33,K37,K41) -> 14.579653 | L47: =AVERAGE(L21,L25,L29,L33,L37,L41) -> 11.72051 | M47: =AVERAGE(M21,M25,M29,M33,M37,M41) -> 12.198043
G48: Median | H48: =MEDIAN(H21,H25,H29,H37,H33,H41) -> 3.3631639 | I48: =MEDIAN(I21,I25,I29,I37,I33,I41) -> 3.2152335 | J48: =MEDIAN(J21,J25,J29,J37,J33,J41) -> 3.1052914 | K48: =MEDIAN(K21,K25,K29,K37,K33,K41) -> 13.556782 | L48: =MEDIAN(L21,L25,L29,L37,L33,L41) -> 11.366013 | M48: =MEDIAN(M21,M25,M29,M37,M33,M41) -> 10.496354
G49: Low | H49: =MIN(H21,H25,H29,H33,H37,H41) -> 1.4264938 | I49: =MIN(I21,I25,I29,I33,I37,I41) -> 1.4222132 | J49: =MIN(J21,J25,J29,J33,J37,J41) -> 1.4056547 | K49: =MIN(K21,K25,K29,K33,K37,K41) -> 6.895487 | L49: =MIN(L21,L25,L29,L33,L37,L41) -> 6.9849983 | M49: =MIN(M21,M25,M29,M33,M37,M41) -> 7.3930824
G51: Enterprise | H51: Enterprise Value / Revenue | K51: Enterprise Value / EBITDA
B52: =B2&" Implied Valuation" -> PayPal Implied Valuation | G52: Value | H52: 2024 | I52: 2025 | J52: LTM | K52: 2024 | L52: 2025 | M52: LTM
B54: Median Enterprise Value | G54: =F15 -> 44267.583 | H54: =H48*I10 -> 106938.52 | I54: =I48*J10 -> 106655.73 | J54: =J48*K10 -> 104753.9 | K54: =K48*I11 -> 86180.462 | L54: =L48*J11 -> 79880.342 | M54: =M48*K11 -> 70871.382
B55: Net Debt (From DCF) | H55: =DCF!$C$85 -> -3369 | I55: =DCF!$C$85 -> -3369 | J55: =DCF!$C$85 -> -3369 | K55: =DCF!$C$85 -> -3369 | L55: =DCF!$C$85 -> -3369 | M55: =DCF!$C$85 -> -3369
B56: Equity Value | H56: =H54-H55 -> 110307.52 | I56: =I54-I55 -> 110024.73 | J56: =J54-J55 -> 108122.9 | K56: =K54-K55 -> 89549.462 | L56: =L54-L55 -> 83249.342 | M56: =M54-M55 -> 74240.382
B57: Diluted Shares Outstanding | H57: =$F$11 -> 952.421 | I57: =$F$11 -> 952.421 | J57: =$F$11 -> 952.421 | K57: =$F$11 -> 952.421 | L57: =$F$11 -> 952.421 | M57: =$F$11 -> 952.421
B58: Implied Equity Value/ Share | H58: =H56/H57 -> 115.81803 | I58: =I56/I57 -> 115.52111 | J58: =J56/J57 -> 113.52427 | K58: =K56/K57 -> 94.022981 | L58: =L56/L57 -> 87.408134 | M58: =M56/M57 -> 77.949123
B60: Mean Enterprise Value | G60: =G54 -> 44267.583 | H60: =H47*I10 -> 124212.26 | I60: =I47*J10 -> 118510.91 | J60: =J47*K10 -> 114997.1 | K60: =K47*I11 -> 92682.856 | L60: =L47*J11 -> 82371.747 | M60: =M47*K11 -> 82361.184
B61: Net Debt (From DCF) | H61: =DCF!$C$85 -> -3369 | I61: =DCF!$C$85 -> -3369 | J61: =DCF!$C$85 -> -3369 | K61: =DCF!$C$85 -> -3369 | L61: =DCF!$C$85 -> -3369 | M61: =DCF!$C$85 -> -3369
B62: Equity Value | H62: =H60-H61 -> 127581.26 | I62: =I60-I61 -> 121879.91 | J62: =J60-J61 -> 118366.1 | K62: =K60-K61 -> 96051.856 | L62: =L60-L61 -> 85740.747 | M62: =M60-M61 -> 85730.184
B63: Diluted Shares Outstanding | H63: =$F$11 -> 952.421 | I63: =$F$11 -> 952.421 | J63: =$F$11 -> 952.421 | K63: =$F$11 -> 952.421 | L63: =$F$11 -> 952.421 | M63: =$F$11 -> 952.421
B64: Implied Equity Value/ Share | H64: =H62/H63 -> 133.9547 | I64: =I62/I63 -> 127.96852 | J64: =J62/J63 -> 124.27918 | K64: =K62/K63 -> 100.85021 | L64: =L62/L63 -> 90.023999 | M64: =M62/M63 -> 90.012909

Sheet Precedents
J1: ="CURRENTLY RUNNING: "&UPPER(CHOOSE(Scenarios!$C$6,Scenarios!B10,Scenarios!B11,Scenarios!B12))&" SCENARIO" -> CURRENTLY RUNNING: BASE CASE SCENARIO
B2: =Cover!B7 -> PayPal
B3: Precedent Transactions
B4: ($ Millions)
B6: General Transaction Information
E7: 1 | F7: =E7+1 -> 2 | G7: =F7+1 -> 3 | H7: =G7+1 -> 4 | I7: =H7+1 -> 5 | J7: =I7+1 -> 6
B8: Target | C8: --- | E8: Worldpay | F8: Global Blue | G8: Nuvei | H8: EVO Payments | I8: First Data | J8: Honey
B9: Acquirer | E9: Global Payments | F9: Shift4 | G9: Advent International | H9: Global Payments | I9: Fiserv | J9: PayPal
B10: Announcement date | E10: 45764 | F10: 45704 | G10: 45383 | H10: 44774 | I10: 43481 | J10: 43789
B11: Deal status | E11: Completed | F11: Completed | G11: Completed | H11: Completed | I11: Completed | J11: Completed
B12: Target currency | E12: USD | F12: EUR | G12: USD | H12: USD | I12: USD | J12: USD
B13: =D2&" to target exchange rate at announcement date" -> to target exchange rate at announcement date | E13: 1 | F13: 1.04 | G13: 1 | H13: 1 | I13: 1 | J13: 1
B14: Buyer type | E14: Strategic | F14: Strategic | G14: Financial Sponsor | H14: Strategic | I14: Strategic | J14: Strategic
B16: Transaction Terms
B18: Form of consideration | E18: Cash | F18: Cash | G18: Cash | H18: Cash | I18: Stock | J18: Cash
B19: Offer price per share | E19: N/A | F19: 7.5 | G19: 34 | H19: 34 | I19: 22.74 | J19: N/A
B20: % of target acquired | E20: 1 | F20: 1 | G20: 1 | H20: 1 | I20: 1 | J20: 1
B21: Annouced synergies (mm's) | E21: 600 | F21: ND | G21: N/A | H21: ND | I21: 900 | J21: N/A
B22: Comments | E22: Priced on EV basis (no public shares/net debt); buyer synergies embedded in multiple. | F22: EUR financials; USD-listed shares & $7.50 offer; EV $2,500M | G22: Financial-sponsor take-private (Advent) deal, EV 6.3B | H22: Strategic merchant-acquiring consolidation; all-cash $34.00/share, EV 4B | I22: All-stock (0.303 Fiserv sh per FDC sh), tax-free to FDC holders; disclosed equity value ~$22B. | J22: Strategic tuck-in; private target, no per-share offer or synergy target disclosed; ~$4B mostly cash.
B24: Premiums Paid
B26: Unaffected target share price - 1 day prior | F26: 6.54 | G26: 31.62 | H26: 27.34 | I26: 17.55
B27: Unaffected target share price - 1 week prior | F27: 6.63 | G27: 28.9 | H27: 26.22 | I27: 17.75
B28: Unaffected target share price - 1 month prior | F28: 7.65 | G28: 26.07 | H28: 23.8 | I28: 16.42
B29: Premium paid - 1 day prior | E29: =IFERROR(E19/E26-1, "NM") -> NM | F29: =IFERROR(F19/F26-1, "NM") -> 0.14678899 | G29: =IFERROR(G19/G26-1, "NM") -> 0.075268817 | H29: =IFERROR(H19/H26-1, "NM") -> 0.24359912 | I29: =IFERROR(I19/I26-1, "NM") -> 0.2957265 | J29: =IFERROR(J19/J26-1, "NM") -> NM
B30: Premium paid - 1 week prior | E30: =IFERROR(E19/E27-1, "NM") -> NM | F30: =IFERROR(F19/F27-1, "NM") -> 0.13122172 | G30: =IFERROR(G19/G27-1, "NM") -> 0.17647059 | H30: =IFERROR(H19/H27-1, "NM") -> 0.29672006 | I30: =IFERROR(I19/I27-1, "NM") -> 0.28112676 | J30: =IFERROR(J19/J27-1, "NM") -> NM
B31: Premium paid - 1 month prior | E31: =IFERROR(E19/E28-1, "NM") -> NM | F31: =IFERROR(F19/F28-1, "NM") -> -0.019607843 | G31: =IFERROR(G19/G28-1, "NM") -> 0.30418105 | H31: =IFERROR(H19/H28-1, "NM") -> 0.42857143 | I31: =IFERROR(I19/I28-1, "NM") -> 0.38489647 | J31: =IFERROR(J19/J28-1, "NM") -> NM
B33: Calculation of Offer & Transaction Value
B35: Diluted Shares Outstanding | E35: ND | F35: 199.636 | G35: 139.248 | H35: 91.508 | I35: 957 | J35: ND
B36: Offer value (purchase price) | E36: =IFERROR(E19*E35,"NM") -> NM | F36: =IFERROR(F19*F35,"NM") -> 1497.27 | G36: =IFERROR(G19*G35,"NM") -> 4734.432 | H36: =IFERROR(H19*H35,"NM") -> 3111.272 | I36: =IFERROR(I19*I35,"NM") -> 21762.18 | J36: =IFERROR(J19*J35,"NM") -> NM
B37: Override | E37: 24250 | F37: 1993 | G37: 5210 | H37: 3500 | I37: 22000 | J37: 4000
B38: Total offer value (purchase price) | E38: =IF(E37,E37,E36) -> 24250 | F38: =IF(F37,F37,F36) -> 1993 | G38: =IF(G37,G37,G36) -> 5210 | H38: =IF(H37,H37,H36) -> 3500 | I38: =IF(I37,I37,I36) -> 22000 | J38: =IF(J37,J37,J36) -> 4000
B40: Net Debt
B41: Period ending | F41: 45747 | G41: 45291 | H41: 44742 | I41: 43646
B43: ST debt (incl. current portion of LT debt) | F43: 0.759 | G43: 12 | H43: 14 | I43: 1150
B44: LT debt | F44: 531.981 | G44: 1248 | H44: 623 | I44: 15811
B45: Noncontrolling interests | F45: 14.8 | G45: 17 | I45: 2768
B46: Preferred stock | H46: 174
B47: Gross debt | E47: =SUM(E43:E46) -> 0 | F47: =SUM(F43:F46) -> 547.54 | G47: =SUM(G43:G46) -> 1277 | H47: =SUM(H43:H46) -> 811 | I47: =SUM(I43:I46) -> 19729 | J47: =SUM(J43:J46) -> 0
B48: Less: Cash & Cash equivalents | E48: 1550 | F48: 123.783 | G48: 170 | H48: 356 | I48: 544
B49: Net debt | E49: =E47-E48 -> -1550 | F49: =F47-F48 -> 423.757 | G49: =G47-G48 -> 1107 | H49: =H47-H48 -> 455 | I49: =I47-I48 -> 19185 | J49: =J47-J48 -> 0
B51: Transaction Value | E51: =IFERROR(E38+E49, "NM") -> 22700 | F51: =IFERROR(F38+F49, "NM") -> 2416.757 | G51: =IFERROR(G38+G49, "NM") -> 6317 | H51: =IFERROR(H38+H49, "NM") -> 3955 | I51: =IFERROR(I38+I49, "NM") -> 41185 | J51: =IFERROR(J38+J49, "NM") -> 4000
B53: LTM Financial Metrics
B55: Revenue | E55: ND | F55: =507.879*F$13 -> 528.19416 | G55: 1189 | H55: 543 | I55: =4801+(9498-4730) -> 9569 | J55: 100
B56: Gross Profit | E56: ND | F56: ND | G56: =1189.893-222.906 -> 966.987 | H56: =543.082-89.37 -> 453.712 | I56: =(4413-1514)+((8679-3005)-(4328-1530)) -> 5775 | J56: ND
B57: EBITDA | E57: 2670.588 | F57: =189.08*F$13 -> 196.6432 | G57: 252 | H57: 203 | I57: =1491+(2904-1391) -> 3004 | J57: ND
B58: EBIT | E58: ND | F58: =134.665*F$13 -> 140.0516 | G58: 14.947 | H58: 66 | I58: =567+(1895-886) -> 1576 | J58: ND
B59: Net Income | E59: ND | F59: =93.568*F$13 -> 97.31072 | G59: -0.696 | H59: 20 | I59: =444+(1005-442) -> 1007 | J59: ND
B61: Transaction Multiples
B63: EV/ Revenue | E63: =IFERROR(E51/E55,"ND") -> ND | F63: =IFERROR(F51/F55,"ND") -> 4.5755087 | G63: =IFERROR(G51/G55,"ND") -> 5.312868 | H63: =IFERROR(H51/H55,"ND") -> 7.2836096 | I63: =IFERROR(I51/I55,"ND") -> 4.3040025 | J63: =IFERROR(J51/J55,"ND") -> 40
B64: EV/ Gross Profit | E64: =IFERROR(E51/E56,"ND") -> ND | F64: =IFERROR(F51/F56,"ND") -> ND | G64: =IFERROR(G51/G56,"ND") -> 6.5326628 | H64: =IFERROR(H51/H56,"ND") -> 8.7169835 | I64: =IFERROR(I51/I56,"ND") -> 7.1316017 | J64: =IFERROR(J51/J56,"ND") -> ND
B65: EV / EBITDA | E65: =IFERROR(E51/E57,"ND") -> 8.5000007 | F65: =IFERROR(F51/F57,"ND") -> 12.290061 | G65: =IFERROR(G51/G57,"ND") -> 25.06746 | H65: =IFERROR(H51/H57,"ND") -> 19.482759 | I65: =IFERROR(I51/I57,"ND") -> 13.710053 | J65: =IFERROR(J51/J57,"ND") -> ND
B66: EV / EBIT | E66: =IFERROR(IF(E51/E58<30,E51/E58,"NM"),"ND") -> ND | F66: =IFERROR(F51/F58,"ND") -> 17.25619 | G66: =IFERROR(G51/G58,"ND") -> 422.62661 | H66: =IFERROR(H51/H58,"ND") -> 59.924242 | I66: =IFERROR(I51/I58,"ND") -> 26.132614 | J66: =IFERROR(J51/J58,"ND") -> ND
B68: Additional Metrics
B69: EBITDA margin | E69: =IFERROR(E57/E55,"ND") -> ND | F69: =F57/F55 -> 0.3722934 | G69: =IFERROR(G57/G55,"NM") -> 0.21194281 | H69: =IFERROR(H57/H55,"NM") -> 0.37384899 | I69: =I57/I55 -> 0.3139304 | J69: =IFERROR(J57/J55,"NM") -> NM
B70: Revenue growth (YoY) | E70: ND | F70: 0.202 | G70: 0.4109 | H70: 0.093 | I70: 0.067 | J70: 1
B72: Summary Statistics
E73: EV/ Revenue | F73: EV / Gross Profit | G73: EV / EBITDA | H73: EV / EBIT | I73: EBITDA Margin | J73: Revenue Growth
B74: High | E74: =MAX(E63:H63,I63) -> 7.2836096 | F74: =MAX(E64:H64,I64:J64) -> 8.7169835 | G74: =MAX(E65:H65,I65:J65) -> 25.06746 | H74: =MAX(E66:F66,I66:J66) -> 26.132614 | I74: =MAX(E69:J69) -> 0.37384899 | J74: =MAX(E70:J70) -> 1
B75: Mean | E75: =AVERAGE(E63:H63,I63) -> 5.3689972 | F75: =AVERAGE(E64:H64,I64:J64) -> 7.460416 | G75: =AVERAGE(E65:H65,I65:J65) -> 15.810067 | H75: =AVERAGE(E66:F66,I66:J66) -> 21.694402 | I75: =AVERAGE(E69:J69) -> 0.3180039 | J75: =AVERAGE(E70:J70) -> 0.35458
B76: Median | E76: =MEDIAN(E63:H63,I63) -> 4.9441884 | F76: =MEDIAN(E64:H64,I64:J64) -> 7.1316017 | G76: =MEDIAN(E65:H65,I65:J65) -> 13.710053 | H76: =MEDIAN(E66:F66,I66:J66) -> 21.694402 | I76: =MEDIAN(E69:J69) -> 0.3431119 | J76: =MEDIAN(E70:J70) -> 0.202
B77: Low | E77: =MIN(E63:H63,I63) -> 4.3040025 | F77: =MIN(E64:H64,I64:J64) -> 6.5326628 | G77: =MIN(E65:J65) -> 8.5000007 | H77: =MIN(E66:F66,I66:J66) -> 17.25619 | I77: =MIN(E69:J69) -> 0.21194281 | J77: =MIN(E70:J70) -> 0.067
B79: Implied Valuation
E80: Mean | F80: Median
B81: LTM EV/EBITDA | E81: =G75 -> 15.810067 | F81: =G76 -> 13.710053
B82: LTM EBITDA | E82: =Assumptions!J74 -> 6752 | F82: =Assumptions!J74 -> 6752
B83: Implied EV | E83: =E81*E82 -> 106749.57 | F83: =F81*F82 -> 92570.28
B84: Net Debt (From DCF) | E84: =DCF!$C$85 -> -3369 | F84: =DCF!$C$85 -> -3369
B85: Equity Value | E85: =E83-E84 -> 110118.57 | F85: =F83-F84 -> 95939.28
B86: Diluted Shares | E86: =Assumptions!$N$9+Assumptions!$N$11 -> 952.421 | F86: =Assumptions!$N$9+Assumptions!$N$11 -> 952.421
B87: Equity value/ share | E87: =E85/E86 -> 115.61964 | F87: =F85/F86 -> 100.73201

Sheet LBO
J1: ="CURRENTLY RUNNING: "&UPPER(CHOOSE(Scenarios!$C$6,Scenarios!B10,Scenarios!B11,Scenarios!B12))&" SCENARIO" -> CURRENTLY RUNNING: BASE CASE SCENARIO
B2: =Cover!B7 -> PayPal
B3: Leveraged Buyout Model
B4: ($ Millions)
B6: Transaction Assumptions
B8: Latest Share Price Date | E8: =Assumptions!N8 -> 46208
B9: Latest Share Price | E9: =Assumptions!N7 -> 45.47
B10: EBITDA (LTM) | E10: =Assumptions!J74 -> 6752
B11: Gross Debt (input as a -) | E11: -11383
B12: Cash | E12: 10422
B13: Minimum cash desired | E13: 1000
B14: EV / LTM EBITDA multiple at exit | E14: =Scenarios!H44 -> 7
B16: Initial Valuation
B18: Valuation Approach | E18: 1 | G18: Approach 1 | I18: Approach 2
E19: =CHOOSE(E18,G19,I19) -> EBITDA Multiple | G19: EBITDA Multiple | I19: Offer/Share Price
B21: LTM EBITDA | E21: =E10 -> 6752 | G21: =E10 -> 6752 | I21: =E10 -> 6752
B22: EV / LTM EBITDA | E22: =CHOOSE(E18,G22,I22) -> 7 | G22: 7 | I22: =I23/I21 -> 7.0541512
B23: Enterprise value | E23: =E21*E22 -> 47264 | G23: =G21*G22 -> 47264 | I23: =I28-I26-I25 -> 47629.629
B25: Less: Gross Debt (latest filing) | E25: =E11 -> -11383 | G25: =E11 -> -11383 | I25: =E11 -> -11383
B26: Plus: Cash (latest filing) | E26: =E12 -> 10422 | G26: =E12 -> 10422 | I26: =E12 -> 10422
B28: Offer value | E28: =E23+E25+E26 -> 46303 | G28: =G23+G25+G26 -> 46303 | I28: =I29*I31 -> 46668.629
B29: Diluted shares outstanding | E29: =Assumptions!N9+Assumptions!N11 -> 952.421 | G29: =Assumptions!N9+Assumptions!N11 -> 952.421 | I29: =Assumptions!N9+Assumptions!N11 -> 952.421
B31: Offer value / per share | E31: =E28/E29 -> 48.616106 | G31: =G28/G29 -> 48.616106 | I31: 49
B32: % Premium / discount | E32: =(E31/E9)-1 -> 0.0691908 | G32: =(G31/E9)-1 -> 0.0691908 | I32: =(I31/E9)-1 -> 0.077633605
B34: Uses of Funds
B35: Buyout of equity | D35: =E28 -> 46303
B36: Refinancing of oldco debt | D36: =-(E11) -> 11383
B37: Fees (transaction & financing) | D37: =H48+H51 -> 1364.94
B38: Total Uses | D38: =SUM(D35:D37) -> 59050.94
B40: Sources of Funds | F40: FEES
C41: EBITDA turns | D41: $ investment | G41: % fees | H41: Fee | I41: Term | J41: Fee amort / year
B42: Excess cash | C42: =D42/E10 -> 1.3954384 | D42: =MAX(E12-E13,0) -> 9422 | F42: Financing fees
B43: Revolver | C43: 0 | D43: =C43*$E$21 -> 0 | F43: =B43 -> Revolver | G43: 0.01 | H43: =D43*G43 -> 0 | I43: 5 | J43: =IFERROR(G43*D43/I43, "NM") -> 0
B44: Term Loan A | C44: 2 | D44: =C44*$E$21 -> 13504 | F44: =B44 -> Term Loan A | G44: 0.015 | H44: =D44*G44 -> 202.56 | I44: 7 | J44: =IFERROR(G44*D44/I44, "NM") -> 28.937143
B45: Term Loan B | C45: 1.5 | D45: =C45*$E$21 -> 10128 | F45: =B45 -> Term Loan B | G45: 0.015 | H45: =D45*G45 -> 151.92 | I45: 7 | J45: =IFERROR(G45*D45/I45, "NM") -> 21.702857
B46: Senior Secured | C46: 0.5 | D46: =C46*$E$21 -> 3376 | F46: =B46 -> Senior Secured | G46: 0.015 | H46: =D46*G46 -> 50.64 | I46: 7 | J46: =IFERROR(G46*D46/I46, "NM") -> 7.2342857
B47: Senior Unsecured | C47: 0.5 | D47: =C47*$E$21 -> 3376 | F47: =B47 -> Senior Unsecured | G47: 0.01 | H47: =D47*G47 -> 33.76 | I47: 7 | J47: =IFERROR(G47*D47/I47, "NM") -> 4.8228571
B48: Sponsor equity | C48: =D48/E10 -> 2.8502577 | D48: =D38-SUM(D42:D47) -> 19244.94 | F48: Financing fees | H48: =SUM(H43:H47) -> 438.88 | J48: =SUM(J43:J47) -> 62.697143
B49: Total Sources | C49: =SUM(C42:C48) -> 8.7456961 | D49: =SUM(D42:D48) -> 59050.94
G50: % of offer value | H50: Fee
F51: Trans. fees | G51: 0.02 | H51: =G51*G28 -> 926.06

Sheet IS Pro Forma
L1: ="CURRENTLY RUNNING: "&UPPER(CHOOSE(Scenarios!$C$6,Scenarios!B10,Scenarios!B11,Scenarios!B12))&" SCENARIO" -> CURRENTLY RUNNING: BASE CASE SCENARIO
B2: =Cover!$B$7 -> PayPal
B3: Pro Forma Income Statement
B4: ($ Millions)
H5: Projected
E6: =F6-1 -> 2023 | F6: =G6-1 -> 2024 | G6: 2025 | H6: =G6+1 -> 2026 | I6: =H6+1 -> 2027 | J6: =I6+1 -> 2028 | K6: =J6+1 -> 2029 | L6: =K6+1 -> 2030
C8: Net Revenue | E8: 29771 | F8: 31797 | G8: 33172 | H8: ='Revenue Build'!H11 -> 34315.686 | I8: ='Revenue Build'!I11 -> 35688.889 | J8: ='Revenue Build'!J11 -> 37318.556 | K8: ='Revenue Build'!K11 -> 39243.381 | L8: ='Revenue Build'!L11 -> 41267.006
C9: Transaction Expense | E9: -14385 | F9: -15697 | G9: -15987 | H9: =-('Revenue Build'!H14*Assumptions!$H$28) -> -16886.86 | I9: =-('Revenue Build'!I14*Assumptions!$H$28) -> -17900.072 | J9: =-('Revenue Build'!J14*Assumptions!$H$28) -> -18974.076 | K9: =-('Revenue Build'!K14*Assumptions!$H$28) -> -20112.52 | L9: =-('Revenue Build'!L14*Assumptions!$H$28) -> -21319.272
C10: Transaction and Credit Losses | E10: -1682 | F10: -1442 | G10: -1720 | H10: =-('Revenue Build'!H14*Assumptions!$H$29) -> -1821.504 | I10: =-('Revenue Build'!I14*Assumptions!$H$29) -> -1930.7942 | J10: =-('Revenue Build'!J14*Assumptions!$H$29) -> -2046.6419 | K10: =-('Revenue Build'!K14*Assumptions!$H$29) -> -2169.4404 | L10: =-('Revenue Build'!L14*Assumptions!$H$29) -> -2299.6068
C11: Customer Support and Operations | E11: -1919 | F11: -1768 | G11: -1704 | H11: =-H8*Assumptions!$H$30 -> -1750.1 | I11: =-I8*Assumptions!$H$30 -> -1820.1333 | J11: =-J8*Assumptions!$H$30 -> -1903.2464 | K11: =-K8*Assumptions!$H$30 -> -2001.4125 | L11: =-L8*Assumptions!$H$30 -> -2104.6173
C12: Gross Profit | E12: =SUM(E8:E11) -> 11785 | F12: =SUM(F8:F11) -> 12890 | G12: =SUM(G8:G11) -> 13761 | H12: =SUM(H8:H11) -> 13857.222 | I12: =SUM(I8:I11) -> 14037.89 | J12: =SUM(J8:J11) -> 14394.592 | K12: =SUM(K8:K11) -> 14960.008 | L12: =SUM(L8:L11) -> 15543.51
C14: Sales and Marketing | E14: -1809 | F14: -2001 | G14: -2283 | H14: =-H8*Assumptions!$H$31 -> -2367.7823 | I14: =-I8*Assumptions!$H$31 -> -2462.5333 | J14: =-J8*Assumptions!$H$31 -> -2574.9804 | K14: =-K8*Assumptions!$H$31 -> -2707.7933 | L14: =-L8*Assumptions!$H$31 -> -2847.4234
C15: Technology and Development | E15: -2973 | F15: -2979 | G15: -3103 | H15: =G15*(1+Assumptions!$H$32) -> -3196.09 | I15: =H15*(1+Assumptions!$H$32) -> -3291.9727 | J15: =I15*(1+Assumptions!$H$32) -> -3390.7319 | K15: =J15*(1+Assumptions!$H$32) -> -3492.4538 | L15: =K15*(1+Assumptions!$H$32) -> -3597.2275
C16: General and Administrative | E16: -2059 | F16: -2147 | G16: -1979 | H16: =G16*(1+Assumptions!$H$33) -> -2018.58 | I16: =H16*(1+Assumptions!$H$33) -> -2058.9516 | J16: =I16*(1+Assumptions!$H$33) -> -2100.1306 | K16: =J16*(1+Assumptions!$H$33) -> -2142.1332 | L16: =K16*(1+Assumptions!$H$33) -> -2184.9759
C17: Restructuring and Other | E17: 84 | F17: -438 | G17: -331 | H17: 0 | I17: =H17 -> 0 | J17: =I17 -> 0 | K17: =J17 -> 0 | L17: =K17 -> 0
C18: EBIT | E18: =SUM(E12:E17) -> 5028 | F18: =SUM(F12:F17) -> 5325 | G18: =SUM(G12:G17) -> 6065 | H18: =SUM(H12:H17) -> 6274.7698 | I18: =SUM(I12:I17) -> 6224.4319 | J18: =SUM(J12:J17) -> 6328.7489 | K18: =SUM(K12:K17) -> 6617.6277 | L18: =SUM(L12:L17) -> 6913.8833
C20: Interest Expense | H20: =-'LBO Debt Schedule'!H83+'LBO Debt Schedule'!H61 -> -1873.289 | I20: =-'LBO Debt Schedule'!I83+'LBO Debt Schedule'!I61 -> -1589.7111 | J20: =-'LBO Debt Schedule'!J83+'LBO Debt Schedule'!J61 -> -1309.026 | K20: =-'LBO Debt Schedule'!K83+'LBO Debt Schedule'!K61 -> -1038.0027 | L20: =-'LBO Debt Schedule'!L83+'LBO Debt Schedule'!L61 -> -759.74365
C21: Other Income (expense), net | E21: 383 | F21: 4 | G21: 227 | H21: =AVERAGE($E$21:$G$21) -> 204.66667 | I21: =AVERAGE($E$21:$G$21) -> 204.66667 | J21: =AVERAGE($E$21:$G$21) -> 204.66667 | K21: =AVERAGE($E$21:$G$21) -> 204.66667 | L21: =AVERAGE($E$21:$G$21) -> 204.66667
C22: EBT | E22: =E21+E18 -> 5411 | F22: =F21+F18 -> 5329 | G22: =G21+G18 -> 6292 | H22: =H18+H21+H20 -> 4606.1474 | I22: =I18+I21+I20 -> 4839.3875 | J22: =J18+J21+J20 -> 5224.3896 | K22: =K18+K21+K20 -> 5784.2916 | L22: =L18+L21+L20 -> 6358.8063
C24: Income Tax Expense | E24: -1165 | F24: -1182 | G24: -1059 | H24: =-'LBO Tax Schedule'!H17 -> -726.96598 | I24: =-'LBO Tax Schedule'!I17 -> -856.72415 | J24: =-'LBO Tax Schedule'!J17 -> -991.20141 | K24: =-'LBO Tax Schedule'!K17 -> -1144.3827 | L24: =-'LBO Tax Schedule'!L17 -> -1288.6662
C25: Net Income | E25: =E22+E24 -> 4246 | F25: =F22+F24 -> 4147 | G25: =G22+G24 -> 5233 | H25: =H22+H24 -> 3879.1814 | I25: =I22+I24 -> 3982.6633 | J25: =J22+J24 -> 4233.1881 | K25: =K22+K24 -> 4639.9089 | L25: =L22+L24 -> 5070.1401
C27: Depreciation & Amortization | E27: -1072 | F27: -1032 | G27: -963 | H27: ='D&A Schedule'!G29 -> -872.06521 | I27: ='D&A Schedule'!H29 -> -879.8888 | J27: ='D&A Schedule'!I29 -> -916.67086 | K27: ='D&A Schedule'!J29 -> -927.60299 | L27: ='D&A Schedule'!K29 -> -990.2919
C28: EBITDA | E28: =E18-E27 -> 6100 | F28: =F18-F27 -> 6357 | G28: =G18-G27 -> 7028 | H28: =H18-H27 -> 7146.835 | I28: =I18-I27 -> 7104.3207 | J28: =J18-J27 -> 7245.4198 | K28: =K18-K27 -> 7545.2307 | L28: =L18-L27 -> 7904.1752
B30: Growth Rates & Margins
C31: Revenue Growth Rate | F31: =(F8/E8)-1 -> 0.068052803 | G31: =(G8/F8)-1 -> 0.043243073 | H31: =(H8/G8)-1 -> 0.034477453 | I31: =(I8/H8)-1 -> 0.04001676 | J31: =(J8/I8)-1 -> 0.045663156 | K31: =(K8/J8)-1 -> 0.05157824 | L31: =(L8/K8)-1 -> 0.051566007
C32: Transaction Expenses | E32: =-(E9/E8) -> 0.48318834 | F32: =-(F9/F8) -> 0.49366292 | G32: =-(G9/G8) -> 0.4819426 | H32: =-(H9/H8) -> 0.49210323 | I32: =-(I9/I8) -> 0.50155867 | J32: =-(J9/J8) -> 0.50843543 | K32: =-(K9/K8) -> 0.51250733 | L32: =-(L9/L8) -> 0.51661785
C33: Transaction & Credit Losses | E33: =-(E10/E8) -> 0.056497934 | F33: =-(F10/F8) -> 0.04535019 | G33: =-(G10/G8) -> 0.051850959 | H33: =-(H10/H8) -> 0.053080798 | I33: =-(I10/I8) -> 0.054100711 | J33: =-(J10/J8) -> 0.054842473 | K33: =-(K10/K8) -> 0.055281689 | L33: =-(L10/L8) -> 0.055725071
C34: Customer Support & Operations | F34: =(F11/E11)-1 -> -0.078686816 | G34: =(G11/F11)-1 -> -0.036199095 | H34: =(H11/G11)-1 -> 0.027053985 | I34: =(I11/H11)-1 -> 0.04001676 | J34: =(J11/I11)-1 -> 0.045663156 | K34: =(K11/J11)-1 -> 0.05157824 | L34: =(L11/K11)-1 -> 0.051566007
C35: Sales & Marketing | F35: =(F14/E14)-1 -> 0.10613599 | G35: =(G14/F14)-1 -> 0.14092954 | H35: =(H14/G14)-1 -> 0.037136373 | I35: =(I14/H14)-1 -> 0.04001676 | J35: =(J14/I14)-1 -> 0.045663156 | K35: =(K14/J14)-1 -> 0.05157824 | L35: =(L14/K14)-1 -> 0.051566007
C36: Technology & Developlment Growth | F36: =(F15/E15)-1 -> 0.0020181635 | G36: =(G15/F15)-1 -> 0.041624706 | H36: =(H15/G15)-1 -> 0.03 | I36: =(I15/H15)-1 -> 0.03 | J36: =(J15/I15)-1 -> 0.03 | K36: =(K15/J15)-1 -> 0.03 | L36: =(L15/K15)-1 -> 0.03
C37: General & Administrative | F37: =(F16/E16)-1 -> 0.042739194 | G37: =(G16/F16)-1 -> -0.078248719 | H37: =(H16/G16)-1 -> 0.02 | I37: =(I16/H16)-1 -> 0.02 | J37: =(J16/I16)-1 -> 0.02 | K37: =(K16/J16)-1 -> 0.02 | L37: =(L16/K16)-1 -> 0.02
C38: Stock-based compensation
C39: Gross Profit Margin | E39: =E12/E8 -> 0.39585503 | F39: =F12/F8 -> 0.40538416 | G39: =G12/G8 -> 0.41483782 | H39: =H12/H8 -> 0.40381597 | I39: =I12/I8 -> 0.39334062 | J39: =J12/J8 -> 0.3857221 | K39: =K12/K8 -> 0.38121099 | L39: =L12/L8 -> 0.37665708
C40: EBITDA Margin | E40: =E28/E8 -> 0.20489738 | F40: =F28/F8 -> 0.19992452 | G40: =G28/G8 -> 0.21186543 | H40: =H28/H8 -> 0.20826729 | I40: =I28/I8 -> 0.19906254 | J40: =J28/J8 -> 0.19415059 | K40: =K28/K8 -> 0.1922676 | L40: =L28/L8 -> 0.1915374
C41: EBIT Margin | E41: =E18/E8 -> 0.16888919 | F41: =F18/F8 -> 0.16746863 | G41: =G18/G8 -> 0.18283492 | H41: =H18/H8 -> 0.18285427 | I41: =I18/I8 -> 0.17440812 | J41: =J18/J8 -> 0.16958719 | K41: =K18/K8 -> 0.16863041 | L41: =L18/L8 -> 0.16754022
C42: Return on Equity | H42: ='IS Pro Forma'!H25/BS!H44 -> 0.1828873 | I42: ='IS Pro Forma'!I25/BS!I44 -> 0.1796138 | J42: ='IS Pro Forma'!J25/BS!J44 -> 0.1816936 | K42: ='IS Pro Forma'!K25/BS!K44 -> 0.18737704 | L42: ='IS Pro Forma'!L25/BS!L44 -> 0.19064311

Sheet BS Pro Forma
L1: ="CURRENTLY RUNNING: "&UPPER(CHOOSE(Scenarios!$C$6,Scenarios!B10,Scenarios!B11,Scenarios!B12))&" SCENARIO" -> CURRENTLY RUNNING: BASE CASE SCENARIO
B2: =Cover!$B$7 -> PayPal
B3: Pro Forma Balance Sheet
B4: ($ Millions)
H5: Projected
F6: =G6-1 -> 2024 | G6: 2025 | H6: =G6+1 -> 2026 | I6: =H6+1 -> 2027 | J6: =I6+1 -> 2028 | K6: =J6+1 -> 2029 | L6: =K6+1 -> 2030
B7: Assets
C8: Cash & Equivalents | F8: 10924 | G8: 10422 | H8: ='CFS Pro Forma'!H34 -> 1000 | I8: ='CFS Pro Forma'!I34 -> 1000 | J8: ='CFS Pro Forma'!J34 -> 1000 | K8: ='CFS Pro Forma'!K34 -> 1000 | L8: ='CFS Pro Forma'!L34 -> 1000
C9: Accounts Receivable, Net | F9: 984 | G9: 840 | H9: ='Working Capital Schedule'!H21 -> 864.94332 | I9: ='Working Capital Schedule'!I21 -> 899.55555 | J9: ='Working Capital Schedule'!J21 -> 938.06206 | K9: ='Working Capital Schedule'!K21 -> 989.14824 | L9: ='Working Capital Schedule'!L21 -> 1040.1547
C10: Inventory and Interest Receivable, Held for Sale | F10: 541 | G10: 1726 | H10: =(G10/'IS Pro Forma'!G8)*'IS Pro Forma'!H8 -> 1785.5081 | I10: =(H10/'IS Pro Forma'!H8)*'IS Pro Forma'!I8 -> 1856.9583 | J10: =(I10/'IS Pro Forma'!I8)*'IS Pro Forma'!J8 -> 1941.7529 | K10: =(J10/'IS Pro Forma'!J8)*'IS Pro Forma'!K8 -> 2041.9051 | L10: =(K10/'IS Pro Forma'!K8)*'IS Pro Forma'!L8 -> 2147.198
C11: Loans and Interest Receivable, Net of Allowances | F11: 6422 | G11: 6746 | H11: =G11*('IS Pro Forma'!H8/'IS Pro Forma'!G8) -> 6978.5849 | I11: =H11*('IS Pro Forma'!I8/'IS Pro Forma'!H8) -> 7257.8453 | J11: =I11*('IS Pro Forma'!J8/'IS Pro Forma'!I8) -> 7589.2614 | K11: =J11*('IS Pro Forma'!K8/'IS Pro Forma'!J8) -> 7980.7021 | L11: =K11*('IS Pro Forma'!L8/'IS Pro Forma'!K8) -> 8392.2351
C12: Funds Receivable and Customer Accounts | F12: 37671 | G12: 38198 | H12: ='Working Capital Schedule'!H31 -> 39514.97 | I12: ='Working Capital Schedule'!I31 -> 41096.231 | J12: ='Working Capital Schedule'!J31 -> 42972.814 | K12: ='Working Capital Schedule'!K31 -> 45189.277 | L12: ='Working Capital Schedule'!L31 -> 47519.507
C13: Prepaid Expenses and Other Current Assets | F13: 1664 | G13: 1827 | H13: ='Working Capital Schedule'!H22 -> 1928.1402 | I13: ='Working Capital Schedule'!I22 -> 2040.5325 | J13: ='Working Capital Schedule'!J22 -> 2154.6021 | K13: ='Working Capital Schedule'!K22 -> 2288.6248 | L13: ='Working Capital Schedule'!L22 -> 2424.3514
C14: Total Current Assets | F14: =SUM(F8:F13) -> 58206 | G14: =SUM(G8:G13) -> 59759 | H14: =SUM(H8:H13) -> 52072.146 | I14: =SUM(I8:I13) -> 54151.122 | J14: =SUM(J8:J13) -> 56596.493 | K14: =SUM(K8:K13) -> 59489.657 | L14: =SUM(L8:L13) -> 62523.446
C16: Long-Term Investments | F16: 4583 | G16: 4330 | H16: =G16 -> 4330 | I16: =H16 -> 4330 | J16: =I16 -> 4330 | K16: =J16 -> 4330 | L16: =K16 -> 4330
C17: Property and Equipment, Net | F17: 1508 | G17: 1700 | H17: ='D&A Schedule'!G25 -> 1749.5113 | I17: ='D&A Schedule'!H25 -> 1788.1558 | J17: ='D&A Schedule'!I25 -> 1815.1303 | K17: ='D&A Schedule'!J25 -> 1829.3684 | L17: ='D&A Schedule'!K25 -> 1829.4847
C18: Goodwill | F18: 10837 | G18: 10864 | H18: =LBO!D35-(G45-G18) -> 36911 | I18: =H18 -> 36911 | J18: =I18 -> 36911 | K18: =J18 -> 36911 | L18: =K18 -> 36911
C19: Intangible Assets, Net | F19: 326 | G19: 208 | H19: ='D&A Schedule'!G11 -> 110 | I19: ='D&A Schedule'!H11 -> 48 | J19: ='D&A Schedule'!I11 -> 0 | K19: ='D&A Schedule'!J11 -> 0 | L19: ='D&A Schedule'!K11 -> 0
C20: Capitalized Financing Fees, Net | H20: ='LBO Debt Schedule'!H62 -> 376.18286 | I20: ='LBO Debt Schedule'!I62 -> 313.48571 | J20: ='LBO Debt Schedule'!J62 -> 250.78857 | K20: ='LBO Debt Schedule'!K62 -> 188.09143 | L20: ='LBO Debt Schedule'!L62 -> 125.39429
C21: Other Assets | F21: 3265 | G21: 3312 | H21: =('BS Pro Forma'!G21/'IS Pro Forma'!G8)*'IS Pro Forma'!H8 -> 3426.1893 | I21: =('BS Pro Forma'!H21/'IS Pro Forma'!H8)*'IS Pro Forma'!I8 -> 3563.2943 | J21: =('BS Pro Forma'!I21/'IS Pro Forma'!I8)*'IS Pro Forma'!J8 -> 3726.0056 | K21: =('BS Pro Forma'!J21/'IS Pro Forma'!J8)*'IS Pro Forma'!K8 -> 3918.1864 | L21: =('BS Pro Forma'!K21/'IS Pro Forma'!K8)*'IS Pro Forma'!L8 -> 4120.2316
C22: Total Long Term Assets | F22: =SUM(F16:F21) -> 20519 | G22: =SUM(G16:G21) -> 20414 | H22: =SUM(H16:H21) -> 46902.883 | I22: =SUM(I16:I21) -> 46953.936 | J22: =SUM(J16:J21) -> 47032.924 | K22: =SUM(K16:K21) -> 47176.646 | L22: =SUM(L16:L21) -> 47316.111
C24: Total Assets | F24: =F22+F14 -> 78725 | G24: =G22+G14 -> 80173 | H24: =H22+H14 -> 98975.03 | I24: =I22+I14 -> 101105.06 | J24: =J22+J14 -> 103629.42 | K24: =K22+K14 -> 106666.3 | L24: =L22+L14 -> 109839.56
B27: Liabilities and Equity
C28: Accounts Payable | F28: 227 | G28: 240 | H28: ='Working Capital Schedule'!H23 -> 252.22764 | I28: ='Working Capital Schedule'!I23 -> 266.93013 | J28: ='Working Capital Schedule'!J23 -> 281.85202 | K28: ='Working Capital Schedule'!K23 -> 299.38405 | L28: ='Working Capital Schedule'!L23 -> 317.13899
C29: Funds Payable to Customers | F29: 39671 | G29: 40198 | H29: =-'Working Capital Schedule'!H32 -> 41583.925 | I29: =-'Working Capital Schedule'!I32 -> 43247.979 | J29: =-'Working Capital Schedule'!J32 -> 45222.818 | K29: =-'Working Capital Schedule'!K32 -> 47555.331 | L29: =-'Working Capital Schedule'!L32 -> 50007.57
C30: Accrued Expenses and Other Current Liabilities | F30: =5592-1191 -> 4401 | G30: =6005-1396 -> 4609 | H30: ='Working Capital Schedule'!H24 -> 4859.5858 | I30: ='Working Capital Schedule'!I24 -> 5142.8538 | J30: ='Working Capital Schedule'!J24 -> 5430.3489 | K30: ='Working Capital Schedule'!K24 -> 5768.1328 | L30: ='Working Capital Schedule'!L24 -> 6110.2112
C31: Current Portion of Term Debt | F31: 1191 | G31: 1396
C32: Total Current Liabilities | F32: =SUM(F28:F31) -> 45490 | G32: =SUM(G28:G31) -> 46443 | H32: =SUM(H28:H31) -> 46695.738 | I32: =SUM(I28:I31) -> 48657.763 | J32: =SUM(J28:J31) -> 50935.019 | K32: =SUM(K28:K31) -> 53622.848 | L32: =SUM(L28:L31) -> 56434.92
C34: Other Long-Term Liabilities | F34: 2939 | G34: 3487 | H34: =G34*(1+Assumptions!$N$19) -> 3696.22 | I34: =H34*(1+Assumptions!$N$19) -> 3917.9932 | J34: =I34*(1+Assumptions!$N$19) -> 4153.0728 | K34: =J34*(1+Assumptions!$N$19) -> 4402.2572 | L34: =K34*(1+Assumptions!$N$19) -> 4666.3926
C35: Long-Term Debt | F35: 9879 | G35: 9987 | H35: ='LBO Debt Schedule'!H66 -> 26385.01 | I35: ='LBO Debt Schedule'!I66 -> 22348.578 | J35: ='LBO Debt Schedule'!J66 -> 18127.413 | K35: ='LBO Debt Schedule'!K66 -> 13587.376 | L35: ='LBO Debt Schedule'!L66 -> 8614.2824
C36: Total Long Term Liabilities | F36: =SUM(F34:F35) -> 12818 | G36: =SUM(G34:G35) -> 13474 | H36: =SUM(H34:H35) -> 30081.23 | I36: =SUM(I34:I35) -> 26266.571 | J36: =SUM(J34:J35) -> 22280.486 | K36: =SUM(K34:K35) -> 17989.633 | L36: =SUM(L34:L35) -> 13280.675
C38: Total Liabilities | F38: =F36+F32 -> 58308 | G38: =G36+G32 -> 59917 | H38: =H36+H32 -> 76776.968 | I38: =I36+I32 -> 74924.334 | J38: =J36+J32 -> 73215.504 | K38: =K36+K32 -> 71612.481 | L38: =L36+L32 -> 69715.595
C40: Treasury Stock | F40: -27085 | G40: -33138 | H40: 0 | I40: =H40 -> 0 | J40: =I40 -> 0 | K40: =J40 -> 0 | L40: =K40 -> 0
C41: Additional Paid-In-Capital | F41: 20705 | G41: 21582 | H41: 0 | I41: =H41 -> 0 | J41: =I41 -> 0 | K41: =J41 -> 0 | L41: =K41 -> 0
C42: Retained Earnings | F42: 27347 | G42: 32470 | H42: ='IS Pro Forma'!H25-LBO!H51 -> 2953.1214 | I42: =H42+'IS Pro Forma'!I25 -> 6935.7848 | J42: =I42+'IS Pro Forma'!J25 -> 11168.973 | K42: =J42+'IS Pro Forma'!K25 -> 15808.882 | L42: =K42+'IS Pro Forma'!L25 -> 20879.022
C43: Accumulated Other Comprhensive Income (Loss) | F43: -550 | G43: -658 | H43: 0 | I43: =H43 -> 0 | J43: =I43 -> 0 | K43: =J43 -> 0 | L43: =K43 -> 0
C44: Common Equity | H44: =LBO!$D$48 -> 19244.94 | I44: =LBO!$D$48 -> 19244.94 | J44: =LBO!$D$48 -> 19244.94 | K44: =LBO!$D$48 -> 19244.94 | L44: =LBO!$D$48 -> 19244.94
C45: Shareholder's Equity | F45: =SUM(F40:F44) -> 20417 | G45: =SUM(G40:G44) -> 20256 | H45: =SUM(H40:H44) -> 22198.061 | I45: =SUM(I40:I44) -> 26180.725 | J45: =SUM(J40:J44) -> 30413.913 | K45: =SUM(K40:K44) -> 35053.822 | L45: =SUM(L40:L44) -> 40123.962
B47: Total Liabilities and Equity | F47: =F45+F38 -> 78725 | G47: =G45+G38 -> 80173 | H47: =H45+H38 -> 98975.03 | I47: =I45+I38 -> 101105.06 | J47: =J45+J38 -> 103629.42 | K47: =K45+K38 -> 106666.3 | L47: =L45+L38 -> 109839.56
D49: Check | F49: =F47-F24 -> 0 | G49: =G47-G24 -> 0 | H49: =H47-H24 -> 0 | I49: =I47-I24 -> 0 | J49: =J47-J24 -> 0 | K49: =K47-K24 -> 0 | L49: =L47-L24 -> 0

Sheet CFS Pro Forma
L1: ="CURRENTLY RUNNING: "&UPPER(CHOOSE(Scenarios!$C$6,Scenarios!B10,Scenarios!B11,Scenarios!B12))&" SCENARIO" -> CURRENTLY RUNNING: BASE CASE SCENARIO
B2: =Cover!$B$7 -> PayPal
B3: Pro Forma Cash Flow Statement
B4: ($ Millions)
H5: Projected
H6: =IS!H6 -> 2026 | I6: =IS!I6 -> 2027 | J6: =IS!J6 -> 2028 | K6: =IS!K6 -> 2029 | L6: =IS!L6 -> 2030
B7: Operating Activities
C8: Net Income | H8: ='IS Pro Forma'!H25 -> 3879.1814 | I8: ='IS Pro Forma'!I25 -> 3982.6633 | J8: ='IS Pro Forma'!J25 -> 4233.1881 | K8: ='IS Pro Forma'!K25 -> 4639.9089 | L8: ='IS Pro Forma'!L25 -> 5070.1401
C9: Depreciation & Amortization | H9: =-'D&A Schedule'!G29-'LBO Debt Schedule'!H61 -> 934.76236 | I9: =-'D&A Schedule'!H29-'LBO Debt Schedule'!I61 -> 942.58594 | J9: =-'D&A Schedule'!I29-'LBO Debt Schedule'!J61 -> 979.368 | K9: =-'D&A Schedule'!J29-'LBO Debt Schedule'!K61 -> 990.30013 | L9: =-'D&A Schedule'!K29-'LBO Debt Schedule'!L61 -> 1052.989
C10: Adjustments to Loans and Interest Receivable, Held for Sale | H10: =BS!G11-BS!H11 -> -59.508084 | I10: =BS!H11-BS!I11 -> -71.450249 | J10: =BS!I11-BS!J11 -> -84.794578 | K10: =BS!J11-BS!K11 -> -100.1522 | L10: =BS!K11-BS!L11 -> -105.29289
C11: Accounts Receivable | H11: =BS!G10-BS!H10 -> -24.94332 | I11: =BS!H10-BS!I10 -> -34.612229 | J11: =BS!I10-BS!J10 -> -38.506512 | K11: =BS!J10-BS!K10 -> -51.086181 | L11: =BS!K10-BS!L10 -> -51.006425
C12: Other Current Assest and Non-Current Assets | H12: =(BS!G14-BS!H14)+(BS!G21-BS!H21) -> -215.32949 | I12: =(BS!H14-BS!I14)+(BS!H21-BS!I21) -> -249.49735 | J12: =(BS!I14-BS!J14)+(BS!I21-BS!J21) -> -276.78084 | K12: =(BS!J14-BS!K14)+(BS!J21-BS!K21) -> -326.20349 | L12: =(BS!K14-BS!L14)+(BS!K21-BS!L21) -> -337.77184
C13: Accounts Payable | H13: =BS!H28-BS!G28 -> 12.227638 | I13: =BS!I28-BS!H28 -> 14.702488 | J13: =BS!J28-BS!I28 -> 14.921892 | K13: =BS!K28-BS!J28 -> 17.532036 | L13: =BS!L28-BS!K28 -> 17.754935
C14: Other Current Liabilities and Non-Current Liabilities | H14: =(BS!H30-BS!G30)+(BS!H34-BS!G34) -> 459.80583 | I14: =(BS!I30-BS!H30)+(BS!I34-BS!H34) -> 505.04114 | J14: =(BS!J30-BS!I30)+(BS!J34-BS!I34) -> 522.5747 | K14: =(BS!K30-BS!J30)+(BS!K34-BS!J34) -> 586.96827 | L14: =(BS!L30-BS!K30)+(BS!L34-BS!K34) -> 606.21384
C15: Operating Cash Flow | H15: =SUM(H8:H14) -> 4986.1964 | I15: =SUM(I8:I14) -> 5089.4331 | J15: =SUM(J8:J14) -> 5349.9708 | K15: =SUM(K8:K14) -> 5757.2675 | L15: =SUM(L8:L14) -> 6253.0268
B17: Investing Activities
C18: Purchases of Property and Equipment | H18: =-('D&A Schedule'!G22) -> -823.57647 | I18: =-('D&A Schedule'!H22) -> -856.53333 | J18: =-('D&A Schedule'!I22) -> -895.64534 | K18: =-('D&A Schedule'!J22) -> -941.84115 | L18: =-('D&A Schedule'!K22) -> -990.40814
C19: Net Loan & Investment Forecast | H19: =(BS!G12-BS!H12)+(BS!G13-BS!H13) -> -1549.5547 | I19: =(BS!H12-BS!I12)+(BS!H13-BS!I13) -> -1860.5214 | J19: =(BS!I12-BS!J12)+(BS!I13-BS!J13) -> -2207.9997 | K19: =(BS!J12-BS!K12)+(BS!J13-BS!K13) -> -2607.9029 | L19: =(BS!K12-BS!L12)+(BS!K13-BS!L13) -> -2741.7635
C20: Investing Cash Flow | H20: =SUM(H18:H19) -> -2373.1311 | I20: =SUM(I18:I19) -> -2717.0548 | J20: =SUM(J18:J19) -> -3103.6451 | K20: =SUM(K18:K19) -> -3549.744 | L20: =SUM(L18:L19) -> -3732.1716
B22: Financing Activities
C23: Purchases of treasury stock | H23: 0 | I23: 0 | J23: 0 | K23: 0 | L23: 0
C24: Repayments under financing arrangements | H24: =-'LBO Debt Schedule'!H64 -> -236.32 | I24: =-'LBO Debt Schedule'!I64 -> -196.3301 | J24: =-'LBO Debt Schedule'!J64 -> -155.96578 | K24: =-'LBO Debt Schedule'!K64 -> -113.75413 | L24: =-'LBO Debt Schedule'!L64 -> -68.353761
C25: Common Dividends | H25: 0 | I25: 0 | J25: 0 | K25: 0 | L25: 0
C26: Net Float & Financing , Forecast | H26: =BS!H29-BS!G29 -> 1385.9247 | I26: =BS!I29-BS!H29 -> 1664.0539 | J26: =BS!J29-BS!I29 -> 1974.8392 | K26: =BS!K29-BS!J29 -> 2332.5133 | L26: =BS!L29-BS!K29 -> 2452.2385
C27: Financing Cash Flow | H27: =SUM(H23:H26) -> 1149.6047 | I27: =SUM(I23:I26) -> 1467.7238 | J27: =SUM(J23:J26) -> 1818.8734 | K27: =SUM(K23:K26) -> 2218.7592 | L27: =SUM(L23:L26) -> 2383.8848
B29: Change in the Cash Position (Pre- Cash Sweep) | H29: =H27+H20+H15 -> 3762.6699 | I29: =I27+I20+I15 -> 3840.1022 | J29: =J27+J20+J15 -> 4065.1992 | K29: =K27+K20+K15 -> 4426.2827 | L29: =L27+L20+L15 -> 4904.7399
B30: Change in the Cash Position (Post- Cash Sweep) | H30: ='LBO Debt Schedule'!H24 -> 0 | I30: ='LBO Debt Schedule'!I24 -> 0 | J30: ='LBO Debt Schedule'!J24 -> 0 | K30: ='LBO Debt Schedule'!K24 -> 0 | L30: ='LBO Debt Schedule'!L24 -> 0
B31: Discretionary Term A Paydown | H31: =-'LBO Debt Schedule'!H32 -> 0 | I31: =-'LBO Debt Schedule'!I32 -> 0 | J31: =-'LBO Debt Schedule'!J32 -> -1727.5048 | K31: =-'LBO Debt Schedule'!K32 -> -4426.2827 | L31: =-'LBO Debt Schedule'!L32 -> -4904.7399
B32: Discretionary Term B Paydown | H32: =-'LBO Debt Schedule'!H40 -> -3762.6699 | I32: =-'LBO Debt Schedule'!I40 -> -3840.1022 | J32: =-'LBO Debt Schedule'!J40 -> -2337.6944 | K32: =-'LBO Debt Schedule'!K40 -> 0 | L32: =-'LBO Debt Schedule'!L40 -> 0
B33: Beginning Cash | H33: =LBO!E13 -> 1000 | I33: =+H34 -> 1000 | J33: =+I34 -> 1000 | K33: =+J34 -> 1000 | L33: =+K34 -> 1000
B34: Ending Cash | H34: =SUM(H29:H33) -> 1000 | I34: =SUM(I29:I33) -> 1000 | J34: =SUM(J29:J33) -> 1000 | K34: =SUM(K29:K33) -> 1000 | L34: =SUM(L29:L33) -> 1000

Sheet LBO Tax Schedule
L1: ="CURRENTLY RUNNING: "&UPPER(CHOOSE(Scenarios!$C$6,Scenarios!B10,Scenarios!B11,Scenarios!B12))&" SCENARIO" -> CURRENTLY RUNNING: BASE CASE SCENARIO
B2: =Cover!$B$7 -> PayPal
B3: Income Tax Schedule
B4: ($ Millions)
H5: Projected
C6: Tax Rate | E6: =Assumptions!N39 -> 0.21 | H6: ='D&A Schedule'!G19 -> 2026 | I6: ='D&A Schedule'!H19 -> 2027 | J6: ='D&A Schedule'!I19 -> 2028 | K6: ='D&A Schedule'!J19 -> 2029 | L6: ='D&A Schedule'!K19 -> 2030
C9: Accounting EBT (as is on I/S) | G9: A | H9: ='IS Pro Forma'!H22 -> 4606.1474 | I9: ='IS Pro Forma'!I22 -> 4839.3875 | J9: ='IS Pro Forma'!J22 -> 5224.3896 | K9: ='IS Pro Forma'!K22 -> 5784.2916 | L9: ='IS Pro Forma'!L22 -> 6358.8063
C11: Less: Reduction in EBT for timing differences | H11: =Assumptions!J62 -> 1144.4047 | I11: =Assumptions!K62 -> 759.74868 | J11: =Assumptions!L62 -> 504.38283 | K11: =Assumptions!M62 -> 334.85025 | L11: =Assumptions!N62 -> 222.30077
C12: Government EBT | G12: B | H12: =H9-H11 -> 3461.7428 | I12: =I9-I11 -> 4079.6388 | J12: =J9-J11 -> 4720.0067 | K12: =K9-K11 -> 5449.4414 | L12: =L9-L11 -> 6136.5055
C14: =CONCATENATE("Accounting Taxes (",$E$6*100,"% of A)") -> Accounting Taxes (21% of A) | H14: =$E$6*H9 -> 967.29096 | I14: =$E$6*I9 -> 1016.2714 | J14: =$E$6*J9 -> 1097.1218 | K14: =$E$6*K9 -> 1214.7012 | L14: =$E$6*L9 -> 1335.3493
C16: Taxes as Appearing on Income Statement
C17: =CONCATENATE("Current Tax (",$E$6*100,"% of B)") -> Current Tax (21% of B) | H17: =$E$6*H12 -> 726.96598 | I17: =$E$6*I12 -> 856.72415 | J17: =$E$6*J12 -> 991.20141 | K17: =$E$6*K12 -> 1144.3827 | L17: =$E$6*L12 -> 1288.6662
C18: Increase (Decrease) in Deferred Income Taxes | H18: =H14-H17 -> 240.32498 | I18: =I14-I17 -> 159.54722 | J18: =J14-J17 -> 105.92039 | K18: =K14-K17 -> 70.318553 | L18: =L14-L17 -> 46.683162
C19: Total Income Taxes (Same as Accounting Taxes Above) | H19: =SUM(H17:H18) -> 967.29096 | I19: =SUM(I17:I18) -> 1016.2714 | J19: =SUM(J17:J18) -> 1097.1218 | K19: =SUM(K17:K18) -> 1214.7012 | L19: =SUM(L17:L18) -> 1335.3493

Sheet LBO Debt Schedule
L1: ="CURRENTLY RUNNING: "&UPPER(CHOOSE(Scenarios!$C$6,Scenarios!B10,Scenarios!B11,Scenarios!B12))&" SCENARIO" -> CURRENTLY RUNNING: BASE CASE SCENARIO
B2: =Cover!$B$7 -> PayPal
B3: LBO Debt Schedule
B4: ($ Millions)
H5: Projected
H6: =DCF!E13 -> 2026 | I6: =DCF!F13 -> 2027 | J6: =DCF!G13 -> 2028 | K6: =DCF!H13 -> 2029 | L6: =DCF!I13 -> 2030
B7: Cash & Debt
B8: Cash
B9: Cash, BOP | H9: ='CFS Pro Forma'!H33 -> 1000 | I9: =H12 -> 1000 | J9: ='CFS Pro Forma'!J33 -> 1000 | K9: ='CFS Pro Forma'!K33 -> 1000 | L9: ='CFS Pro Forma'!L33 -> 1000
B10: Increases / (decreases) | H10: ='CFS Pro Forma'!H29 -> 3762.6699 | I10: ='CFS Pro Forma'!I29 -> 3840.1022 | J10: ='CFS Pro Forma'!J29 -> 4065.1992 | K10: ='CFS Pro Forma'!K29 -> 4426.2827 | L10: ='CFS Pro Forma'!L29 -> 4904.7399
B11: Less: Cash Sweep | H11: =-(H32+H40) -> -3762.6699 | I11: =-(I32+I40) -> -3840.1022 | J11: =-(J32+J40) -> -4065.1992 | K11: =-(K32+K40) -> -4426.2827 | L11: =-(L32+L40) -> -4904.7399
B12: Cash, EOP | H12: =SUM(H9:H11) -> 1000 | I12: =SUM(I9:I11) -> 1000 | J12: =SUM(J9:J11) -> 1000 | K12: =SUM(K9:K11) -> 1000 | L12: =SUM(L9:L11) -> 1000
B13: Interest rate on cash | H13: =Assumptions!N28 -> 0.03 | I13: =H13 -> 0.03 | J13: =I13 -> 0.03 | K13: =J13 -> 0.03 | L13: =K13 -> 0.03
B14: Interest income | H14: =IF(Assumptions!$N$44="OFF",MAX(AVERAGE(H9,H12)*H13,0),0) -> 30 | I14: =IF(Assumptions!$N$44="OFF",MAX(AVERAGE(I9,I12)*I13,0),0) -> 30 | J14: =IF(Assumptions!$N$44="OFF",MAX(AVERAGE(J9,J12)*J13,0),0) -> 30 | K14: =IF(Assumptions!$N$44="OFF",MAX(AVERAGE(K9,K12)*K13,0),0) -> 30 | L14: =IF(Assumptions!$N$44="OFF",MAX(AVERAGE(L9,L12)*L13,0),0) -> 30
B16: Revolver
B17: Cash, BOP | H17: =H9 -> 1000 | I17: =I9 -> 1000 | J17: =J9 -> 1000 | K17: =K9 -> 1000 | L17: =L9 -> 1000
B18: Less: Minimum cash desired | H18: =-LBO!$E$13 -> -1000 | I18: =-LBO!$E$13 -> -1000 | J18: =-LBO!$E$13 -> -1000 | K18: =-LBO!$E$13 -> -1000 | L18: =-LBO!$E$13 -> -1000
B19: Equals: Excess cash at BOP | H19: =SUM(H17:H18) -> 0 | I19: =SUM(I17:I18) -> 0 | J19: =SUM(J17:J18) -> 0 | K19: =SUM(K17:K18) -> 0 | L19: =SUM(L17:L18) -> 0
B20: Plus: Free cash flows generated during period | H20: ='CFS Pro Forma'!H29 -> 3762.6699 | I20: ='CFS Pro Forma'!I29 -> 3840.1022 | J20: ='CFS Pro Forma'!J29 -> 4065.1992 | K20: ='CFS Pro Forma'!K29 -> 4426.2827 | L20: ='CFS Pro Forma'!L29 -> 4904.7399
B21: Cash available (needed) to paydown (draw from) revolver | H21: =SUM(H19:H20) -> 3762.6699 | I21: =SUM(I19:I20) -> 3840.1022 | J21: =SUM(J19:J20) -> 4065.1992 | K21: =SUM(K19:K20) -> 4426.2827 | L21: =SUM(L19:L20) -> 4904.7399
B23: Revolver, BOP | H23: =LBO!$D$43 -> 0 | I23: =LBO!$D$43 -> 0 | J23: =LBO!$D$43 -> 0 | K23: =LBO!$D$43 -> 0 | L23: =LBO!$D$43 -> 0
B24: Increases / (decreases) | H24: =MIN(H23,H21) -> 0 | I24: =MIN(I23,I21) -> 0 | J24: =MIN(J23,J21) -> 0 | K24: =MIN(K23,K21) -> 0 | L24: =MIN(L23,L21) -> 0
B25: Revolver, EOP | H25: =SUM(H23:H24) -> 0 | I25: =SUM(I23:I24) -> 0 | J25: =SUM(J23:J24) -> 0 | K25: =SUM(K23:K24) -> 0 | L25: =SUM(L23:L24) -> 0
B26: Maximum availability | H26: 5000 | I26: =H26 -> 5000 | J26: =I26 -> 5000 | K26: =J26 -> 5000 | L26: =K26 -> 5000
B27: Compliance check | H27: =IF(H25>H26,"OVERDRAWN","OK") -> OK | I27: =IF(I25>I26,"OVERDRAWN","OK") -> OK | J27: =IF(J25>J26,"OVERDRAWN","OK") -> OK | K27: =IF(K25>K26,"OVERDRAWN","OK") -> OK | L27: =IF(L25>L26,"OVERDRAWN","OK") -> OK
B29: Term Loan A
B30: Term Loan A, BOP | H30: =LBO!D44 -> 13504 | I30: =H33 -> 13368.96 | J30: =I33 -> 13235.27 | K30: =J33 -> 11375.413 | L30: =K33 -> 6835.3761
B31: Mandatory paydown $ | H31: =(H30*H34) -> 135.04 | I31: =(I30*I34) -> 133.6896 | J31: =(J30*J34) -> 132.3527 | K31: =(K30*K34) -> 113.75413 | L31: =(L30*L34) -> 68.353761
B32: Cash sweep (paydown from excess cash flows) | H32: =MIN(H35,H30-H31) -> 0 | I32: =MIN(I35,I30-I31) -> 0 | J32: =MIN(J35,J30-J31) -> 1727.5048 | K32: =MIN(K35,K30-K31) -> 4426.2827 | L32: =MIN(L35,L30-L31) -> 4904.7399
B33: Term Loan A, EOP | H33: =H30-H31-H32 -> 13368.96 | I33: =I30-I31-I32 -> 13235.27 | J33: =J30-J31-J32 -> 11375.413 | K33: =K30-K31-K32 -> 6835.3761 | L33: =L30-L31-L32 -> 1862.2824
B34: Mandatory paydown (% of original) | H34: 0.01 | I34: =H34 -> 0.01 | J34: =I34 -> 0.01 | K34: =J34 -> 0.01 | L34: =K34 -> 0.01
B35: Cash available for cash sweep | H35: =H21-H40 -> 0 | I35: =I21-I40 -> 0 | J35: =J21-J40 -> 1727.5048 | K35: =K21-K40 -> 4426.2827 | L35: =L21-L40 -> 4904.7399
B37: Term Loan B
B38: Term Loan B, BOP | H38: =LBO!D45 -> 10128 | I38: =H41 -> 6264.0501 | J38: =I41 -> 2361.3074 | K38: =J41 -> 0 | L38: =K41 -> 0
B39: Mandatory amortization $ | H39: =(H38*H42) -> 101.28 | I39: =(I38*I42) -> 62.640501 | J39: =(J38*J42) -> 23.613074 | K39: =(K38*K42) -> 0 | L39: =(L38*L42) -> 0
B40: Cash sweep (paydown from excess cash flows) | H40: =MIN(H43,H38-H39) -> 3762.6699 | I40: =MIN(I43,I38-I39) -> 3840.1022 | J40: =MIN(J43,J38-J39) -> 2337.6944 | K40: =MIN(K43,K38-K39) -> 0 | L40: =MIN(L43,L38-L39) -> 0
B41: Term Loan B, EOP | H41: =H38-H39-H40 -> 6264.0501 | I41: =I38-I39-I40 -> 2361.3074 | J41: =J38-J39-J40 -> 0 | K41: =K38-K39-K40 -> 0 | L41: =L38-L39-L40 -> 0
B42: Mandatory paydown (% of original) | H42: 0.01 | I42: =H42 -> 0.01 | J42: =I42 -> 0.01 | K42: =J42 -> 0.01 | L42: =K42 -> 0.01
B43: Cash available for cash sweep | H43: =H21+H24 -> 3762.6699 | I43: =I21+I24 -> 3840.1022 | J43: =J21+J24 -> 4065.1992 | K43: =K21+K24 -> 4426.2827 | L43: =L21+L24 -> 4904.7399
B45: Senior Secured
B46: Senior Secured, BOP | H46: =LBO!D46 -> 3376 | I46: =H48 -> 3376 | J46: =I48 -> 3376 | K46: =J48 -> 3376 | L46: =K48 -> 3376
B47: Amortization | H47: 0 | I47: =H47 -> 0 | J47: =I47 -> 0 | K47: =J47 -> 0 | L47: =K47 -> 0
B48: Senior Secured, EOP | H48: =H46-H47 -> 3376 | I48: =I46-I47 -> 3376 | J48: =J46-J47 -> 3376 | K48: =K46-K47 -> 3376 | L48: =L46-L47 -> 3376
B49: Coupon | H49: 0.065 | I49: =H49 -> 0.065 | J49: =I49 -> 0.065 | K49: =J49 -> 0.065 | L49: =K49 -> 0.065
B50: Coupon Payment | H50: =H49*H46 -> 219.44 | I50: =I49*I46 -> 219.44 | J50: =J49*J46 -> 219.44 | K50: =K49*K46 -> 219.44 | L50: =L49*L46 -> 219.44
B52: Senior Unsecured
B53: Senior Unsecured, BOP | H53: =LBO!D47 -> 3376 | I53: =H55 -> 3376 | J53: =I55 -> 3376 | K53: =J55 -> 3376 | L53: =K55 -> 3376
B54: Amortization | H54: 0 | I54: =H54 -> 0 | J54: =I54 -> 0 | K54: =J54 -> 0 | L54: =K54 -> 0
B55: Senior Unsecured, EOP | H55: =H53-H54 -> 3376 | I55: =I53-I54 -> 3376 | J55: =J53-J54 -> 3376 | K55: =K53-K54 -> 3376 | L55: =L53-L54 -> 3376
B56: Coupon | H56: 0.075 | I56: =H56 -> 0.075 | J56: =I56 -> 0.075 | K56: =J56 -> 0.075 | L56: =K56 -> 0.075
B57: Coupon Payment | H57: =H56*H53 -> 253.2 | I57: =I56*I53 -> 253.2 | J57: =J56*J53 -> 253.2 | K57: =K56*K53 -> 253.2 | L57: =L56*L53 -> 253.2
B59: Capitalized financing fees
B60: Capitalized financing fees, BOP | H60: =LBO!H48 -> 438.88 | I60: =H62 -> 376.18286 | J60: =I62 -> 313.48571 | K60: =J62 -> 250.78857 | L60: =K62 -> 188.09143
B61: Amortization | H61: =-LBO!$J$48 -> -62.697143 | I61: =-LBO!$J$48 -> -62.697143 | J61: =-LBO!$J$48 -> -62.697143 | K61: =-LBO!$J$48 -> -62.697143 | L61: =-LBO!$J$48 -> -62.697143
B62: Capitalized financing fees, EOP | H62: =SUM(H60:H61) -> 376.18286 | I62: =SUM(I60:I61) -> 313.48571 | J62: =SUM(J60:J61) -> 250.78857 | K62: =SUM(K60:K61) -> 188.09143 | L62: =SUM(L60:L61) -> 125.39429
B64: Repayments Under Financing Arrangements | H64: =H47+H54+H39+H31 -> 236.32 | I64: =I47+I54+I39+I31 -> 196.3301 | J64: =J47+J54+J39+J31 -> 155.96578 | K64: =K47+K54+K39+K31 -> 113.75413 | L64: =L47+L54+L39+L31 -> 68.353761
B66: Total Long Term Debt | H66: =H55+H48+H41+H33+H25 -> 26385.01 | I66: =I55+I48+I41+I33+I25 -> 22348.578 | J66: =J55+J48+J41+J33+J25 -> 18127.413 | K66: =K55+K48+K41+K33+K25 -> 13587.376 | L66: =L55+L48+L41+L33+L25 -> 8614.2824
H69: Projected
H70: =H6 -> 2026 | I70: =I6 -> 2027 | J70: =J6 -> 2028 | K70: =K6 -> 2029 | L70: =L6 -> 2030
B71: Interest Expense
B72: Median Fed Funds Rate (SOFR Proxy) | H72: 0.036 | I72: =H72 -> 0.036 | J72: =I72 -> 0.036 | K72: =J72 -> 0.036 | L72: =K72 -> 0.036
E74: SOFR Spread | F74: SOFR floor
B75: Revolver | E75: 0.01 | F75: 0.01 | H75: =IFERROR(IF(Assumptions!$N$44="OFF",($E$75+MAX(H72,$F$75))*AVERAGE(H23,H25),0),0) -> 0 | I75: =IFERROR(IF(Assumptions!$N$44="OFF",($E$75+MAX(I72,$F$75))*AVERAGE(I23,I25),0),0) -> 0 | J75: =IFERROR(IF(Assumptions!$N$44="OFF",($E$75+MAX(J72,$F$75))*AVERAGE(J23,J25),0),0) -> 0 | K75: =IFERROR(IF(Assumptions!$N$44="OFF",($E$75+MAX(K72,$F$75))*AVERAGE(K23,K25),0),0) -> 0 | L75: =IFERROR(IF(Assumptions!$N$44="OFF",($E$75+MAX(L72,$F$75))*AVERAGE(L23,L25),0),0) -> 0
B76: Term Loan A | E76: 0.0225 | F76: 0.01 | H76: =IF(Assumptions!$N$44="OFF",($E$76+MAX(H72,$F$76))*AVERAGE(H30,H33),0) -> 786.03408 | I76: =IF(Assumptions!$N$44="OFF",($E$76+MAX(I72,$F$76))*AVERAGE(I30,I33),0) -> 778.17374 | J76: =IF(Assumptions!$N$44="OFF",($E$76+MAX(J72,$F$76))*AVERAGE(J30,J33),0) -> 719.86249 | K76: =IF(Assumptions!$N$44="OFF",($E$76+MAX(K72,$F$76))*AVERAGE(K30,K33),0) -> 532.66558 | L76: =IF(Assumptions!$N$44="OFF",($E$76+MAX(L72,$F$76))*AVERAGE(L30,L33),0) -> 254.40651
B77: Term Loan B | E77: 0.035 | F77: 0.01 | H77: =IF(Assumptions!$N$44="OFF",($E$77+MAX(H72,$F$77))*AVERAGE(H38,H41),0) -> 581.91778 | I77: =IF(Assumptions!$N$44="OFF",($E$77+MAX(I72,$F$77))*AVERAGE(I38,I41),0) -> 306.20019 | J77: =IF(Assumptions!$N$44="OFF",($E$77+MAX(J72,$F$77))*AVERAGE(J38,J41),0) -> 83.826414 | K77: =IF(Assumptions!$N$44="OFF",($E$77+MAX(K72,$F$77))*AVERAGE(K38,K41),0) -> 0 | L77: =IF(Assumptions!$N$44="OFF",($E$77+MAX(L72,$F$77))*AVERAGE(L38,L41),0) -> 0
B78: Senior Secured | H78: =H50 -> 219.44 | I78: =I50 -> 219.44 | J78: =J50 -> 219.44 | K78: =K50 -> 219.44 | L78: =L50 -> 219.44
B79: Senior Unsecured | H79: =H57 -> 253.2 | I79: =I57 -> 253.2 | J79: =J57 -> 253.2 | K79: =K57 -> 253.2 | L79: =L57 -> 253.2
B81: Annual Interest Expense | H81: =SUM(H75:H79) -> 1840.5919 | I81: =SUM(I75:I79) -> 1557.0139 | J81: =SUM(J75:J79) -> 1276.3289 | K81: =SUM(K75:K79) -> 1005.3056 | L81: =SUM(L75:L79) -> 727.04651
B83: Net Interest Expense | H83: =H81-H14 -> 1810.5919 | I83: =I81-I14 -> 1527.0139 | J83: =J81-J14 -> 1246.3289 | K83: =K81-K14 -> 975.30558 | L83: =L81-L14 -> 697.04651
H86: Projected
H87: =H70 -> 2026 | I87: =I70 -> 2027 | J87: =J70 -> 2028 | K87: =K70 -> 2029 | L87: =L70 -> 2030
B88: Credit Analysis
B89: Total Debt | H89: =H66 -> 26385.01 | I89: =I66 -> 22348.578 | J89: =J66 -> 18127.413 | K89: =K66 -> 13587.376 | L89: =L66 -> 8614.2824
B90: Net Debt | H90: =H89-H12 -> 25385.01 | I90: =I89-I12 -> 21348.578 | J90: =J89-J12 -> 17127.413 | K90: =K89-K12 -> 12587.376 | L90: =L89-L12 -> 7614.2824
B91: Gross Leverage | H91: =H89/'IS Pro Forma'!H28 -> 3.6918454 | I91: =I89/'IS Pro Forma'!I28 -> 3.1457727 | J91: =J89/'IS Pro Forma'!J28 -> 2.5019134 | K91: =K89/'IS Pro Forma'!K28 -> 1.80079 | L91: =L89/'IS Pro Forma'!L28 -> 1.0898395
B92: Net Leverage | H92: =H90/'IS Pro Forma'!H28 -> 3.5519234 | I92: =I90/'IS Pro Forma'!I28 -> 3.0050133 | J92: =J90/'IS Pro Forma'!J28 -> 2.3638952 | K92: =K90/'IS Pro Forma'!K28 -> 1.668256 | L92: =L90/'IS Pro Forma'!L28 -> 0.96332409
B93: Interest Coverage | H93: ='IS Pro Forma'!H28/'LBO Debt Schedule'!H83 -> 3.9472369 | I93: ='IS Pro Forma'!I28/'LBO Debt Schedule'!I83 -> 4.6524269 | J93: ='IS Pro Forma'!J28/'LBO Debt Schedule'!J83 -> 5.8134091 | K93: ='IS Pro Forma'!K28/'LBO Debt Schedule'!K83 -> 7.7362735 | L93: ='IS Pro Forma'!L28/'LBO Debt Schedule'!L83 -> 11.339523

Sheet LBO Exit Valuation
K1: ="CURRENTLY RUNNING: "&UPPER(CHOOSE(Scenarios!$C$6,Scenarios!B10,Scenarios!B11,Scenarios!B12))&" SCENARIO" -> CURRENTLY RUNNING: BASE CASE SCENARIO
B2: =Cover!$B$7 -> PayPal
B3: Exit Valuation
B4: ($ Millions)
E5: Assumed Exit December 31, 2030
B7: EBITDA Multiple at Exit | D7: 0.5 | E7: =F7-0.5 -> 6 | F7: =G7-0.5 -> 6.5 | G7: =LBO!E14 -> 7 | H7: =G7+$D$7 -> 7.5 | I7: =H7+$D$7 -> 8 | J7: =I7+$D$7 -> 8.5 | K7: =J7+$D$7 -> 9
B8: EBITDA at Exit | E8: ='IS Pro Forma'!$L$28 -> 7904.1752 | F8: ='IS Pro Forma'!$L$28 -> 7904.1752 | G8: ='IS Pro Forma'!$L$28 -> 7904.1752 | H8: ='IS Pro Forma'!$L$28 -> 7904.1752 | I8: ='IS Pro Forma'!$L$28 -> 7904.1752 | J8: ='IS Pro Forma'!$L$28 -> 7904.1752 | K8: ='IS Pro Forma'!$L$28 -> 7904.1752
B9: Enterprise Value | E9: =E7*E8 -> 47425.051 | F9: =F7*F8 -> 51377.139 | G9: =G7*G8 -> 55329.226 | H9: =H7*H8 -> 59281.314 | I9: =I7*I8 -> 63233.401 | J9: =J7*J8 -> 67185.489 | K9: =K7*K8 -> 71137.577
B11: Net Debt
B12: Revolver | E12: ='LBO Debt Schedule'!$L$25 -> 0 | F12: ='LBO Debt Schedule'!$L$25 -> 0 | G12: ='LBO Debt Schedule'!$L$25 -> 0 | H12: ='LBO Debt Schedule'!$L$25 -> 0 | I12: ='LBO Debt Schedule'!$L$25 -> 0 | J12: ='LBO Debt Schedule'!$L$25 -> 0 | K12: ='LBO Debt Schedule'!$L$25 -> 0
B13: Term Loan A | E13: ='LBO Debt Schedule'!$L$33 -> 1862.2824 | F13: ='LBO Debt Schedule'!$L$33 -> 1862.2824 | G13: ='LBO Debt Schedule'!$L$33 -> 1862.2824 | H13: ='LBO Debt Schedule'!$L$33 -> 1862.2824 | I13: ='LBO Debt Schedule'!$L$33 -> 1862.2824 | J13: ='LBO Debt Schedule'!$L$33 -> 1862.2824 | K13: ='LBO Debt Schedule'!$L$33 -> 1862.2824
B14: Term Loan B | E14: ='LBO Debt Schedule'!$L$41 -> 0 | F14: ='LBO Debt Schedule'!$L$41 -> 0 | G14: ='LBO Debt Schedule'!$L$41 -> 0 | H14: ='LBO Debt Schedule'!$L$41 -> 0 | I14: ='LBO Debt Schedule'!$L$41 -> 0 | J14: ='LBO Debt Schedule'!$L$41 -> 0 | K14: ='LBO Debt Schedule'!$L$41 -> 0
B15: Senior Secured | E15: ='LBO Debt Schedule'!$L$48 -> 3376 | F15: ='LBO Debt Schedule'!$L$48 -> 3376 | G15: ='LBO Debt Schedule'!$L$48 -> 3376 | H15: ='LBO Debt Schedule'!$L$48 -> 3376 | I15: ='LBO Debt Schedule'!$L$48 -> 3376 | J15: ='LBO Debt Schedule'!$L$48 -> 3376 | K15: ='LBO Debt Schedule'!$L$48 -> 3376
B16: Senior Unsecured | E16: ='LBO Debt Schedule'!$L$55 -> 3376 | F16: ='LBO Debt Schedule'!$L$55 -> 3376 | G16: ='LBO Debt Schedule'!$L$55 -> 3376 | H16: ='LBO Debt Schedule'!$L$55 -> 3376 | I16: ='LBO Debt Schedule'!$L$55 -> 3376 | J16: ='LBO Debt Schedule'!$L$55 -> 3376 | K16: ='LBO Debt Schedule'!$L$55 -> 3376
B17: Cash | E17: =-('LBO Debt Schedule'!$L$12) -> -1000 | F17: =-('LBO Debt Schedule'!$L$12) -> -1000 | G17: =-('LBO Debt Schedule'!$L$12) -> -1000 | H17: =-('LBO Debt Schedule'!$L$12) -> -1000 | I17: =-('LBO Debt Schedule'!$L$12) -> -1000 | J17: =-('LBO Debt Schedule'!$L$12) -> -1000 | K17: =-('LBO Debt Schedule'!$L$12) -> -1000
B19: Equity Value | E19: =E9-SUM(E12:E17) -> 39810.769 | F19: =F9-SUM(F12:F17) -> 43762.856 | G19: =G9-SUM(G12:G17) -> 47714.944 | H19: =H9-SUM(H12:H17) -> 51667.031 | I19: =I9-SUM(I12:I17) -> 55619.119 | J19: =J9-SUM(J12:J17) -> 59571.207 | K19: =K9-SUM(K12:K17) -> 63523.294

Sheet LBO Returns
K1: ="CURRENTLY RUNNING: "&UPPER(CHOOSE(Scenarios!$C$6,Scenarios!B10,Scenarios!B11,Scenarios!B12))&" SCENARIO" -> CURRENTLY RUNNING: BASE CASE SCENARIO
B2: =Cover!$B$7 -> PayPal
B3: LBO Returns
B4: ($ Millions)
G5: Projected
G6: ='LBO Debt Schedule'!H70 -> 2026 | H6: ='LBO Debt Schedule'!I70 -> 2027 | I6: ='LBO Debt Schedule'!J70 -> 2028 | J6: ='LBO Debt Schedule'!K70 -> 2029 | K6: ='LBO Debt Schedule'!L70 -> 2030
D7: MOIC | E7: IRR | F7: Initial
B8: Revolver | D8: =IFERROR((SUM(G8:K8)/-F8),0) -> 0 | E8: =IFERROR(IRR(F8:K8),0) -> 0 | F8: =-(LBO!D43) -> 0 | G8: ='LBO Debt Schedule'!H75+'LBO Debt Schedule'!H24 -> 0 | H8: ='LBO Debt Schedule'!I75+'LBO Debt Schedule'!I24 -> 0 | I8: ='LBO Debt Schedule'!J75+'LBO Debt Schedule'!J24 -> 0 | J8: ='LBO Debt Schedule'!K75+'LBO Debt Schedule'!K24 -> 0 | K8: ='LBO Debt Schedule'!L75+'LBO Debt Schedule'!L25 -> 0
B9: Term Loan A | D9: =IFERROR((SUM(G9:K9)/-F9),"NM") -> 1.2274246 | E9: =IFERROR(IRR(F9:K9),0) -> 0.053096888 | F9: =-(LBO!D44) -> -13504 | G9: ='LBO Debt Schedule'!H76+'LBO Debt Schedule'!H32+'LBO Debt Schedule'!H31 -> 921.07408 | H9: ='LBO Debt Schedule'!I76+'LBO Debt Schedule'!I32+'LBO Debt Schedule'!I31 -> 911.86334 | I9: ='LBO Debt Schedule'!J76+'LBO Debt Schedule'!J32+'LBO Debt Schedule'!J31 -> 2579.72 | J9: ='LBO Debt Schedule'!K76+'LBO Debt Schedule'!K32+'LBO Debt Schedule'!K31 -> 5072.7024 | K9: ='LBO Debt Schedule'!L76+'LBO Debt Schedule'!L32+'LBO Debt Schedule'!L31+'LBO Debt Schedule'!L33 -> 7089.7826
B10: Term Loan B | D10: =IFERROR((SUM(G10:K10)/-F10),"NM") -> 1.0959661 | E10: =IFERROR(IRR(F10:K10),0) -> 0.052082275 | F10: =-(LBO!D45) -> -10128 | G10: ='LBO Debt Schedule'!H77+'LBO Debt Schedule'!H40+'LBO Debt Schedule'!H39 -> 4445.8677 | H10: ='LBO Debt Schedule'!I77+'LBO Debt Schedule'!I40+'LBO Debt Schedule'!I39 -> 4208.9428 | I10: ='LBO Debt Schedule'!J77+'LBO Debt Schedule'!J40+'LBO Debt Schedule'!J39 -> 2445.1339 | J10: ='LBO Debt Schedule'!K77+'LBO Debt Schedule'!K40+'LBO Debt Schedule'!K39 -> 0 | K10: ='LBO Debt Schedule'!L77+'LBO Debt Schedule'!L40+'LBO Debt Schedule'!L39+'LBO Debt Schedule'!L41 -> 0
B11: Senior Secured Note | D11: =IFERROR((SUM(G11:K11)/-F11),"NM") -> 1.325 | E11: =IFERROR(IRR(F11:K11),0) -> 0.065 | F11: =-(LBO!D46) -> -3376 | G11: ='LBO Debt Schedule'!H78+'LBO Debt Schedule'!H47 -> 219.44 | H11: ='LBO Debt Schedule'!I78+'LBO Debt Schedule'!I47 -> 219.44 | I11: ='LBO Debt Schedule'!J78+'LBO Debt Schedule'!J47 -> 219.44 | J11: ='LBO Debt Schedule'!K78+'LBO Debt Schedule'!K47 -> 219.44 | K11: ='LBO Debt Schedule'!L78+'LBO Debt Schedule'!L47+'LBO Debt Schedule'!L48 -> 3595.44
B12: Senior Unsecured Note | D12: =IFERROR((SUM(G12:K12)/-F12),"NM") -> 1.375 | E12: =IFERROR(IRR(F12:K12),0) -> 0.075 | F12: =-(LBO!D47) -> -3376 | G12: ='LBO Debt Schedule'!H54+'LBO Debt Schedule'!H79 -> 253.2 | H12: ='LBO Debt Schedule'!I54+'LBO Debt Schedule'!I79 -> 253.2 | I12: ='LBO Debt Schedule'!J54+'LBO Debt Schedule'!J79 -> 253.2 | J12: ='LBO Debt Schedule'!K54+'LBO Debt Schedule'!K79 -> 253.2 | K12: ='LBO Debt Schedule'!L54+'LBO Debt Schedule'!L79+'LBO Debt Schedule'!L55 -> 3629.2
B13: Sponsor's Equity at exit EBITDA multiple of:
B14: ='LBO Exit Valuation'!E7 -> 6 | D14: =IFERROR((SUM(G14:K14)/-F14),"NM") -> 2.0686356 | E14: =IFERROR(IRR(F14:K14),0) -> 0.15647647 | F14: =-LBO!$D$48 -> -19244.94 | G14: =G15 -> 0 | H14: =H15 -> 0 | I14: =I15 -> 0 | J14: =J15 -> 0 | K14: ='LBO Exit Valuation'!E19 -> 39810.769
B15: ='LBO Exit Valuation'!F7 -> 6.5 | D15: =IFERROR((SUM(G15:K15)/-F15),"NM") -> 2.2739929 | E15: =IFERROR(IRR(F15:K15),0) -> 0.17857661 | F15: =-LBO!$D$48 -> -19244.94 | G15: =G16 -> 0 | H15: =H16 -> 0 | I15: =I16 -> 0 | J15: =J16 -> 0 | K15: ='LBO Exit Valuation'!F19 -> 43762.856
B16: ='LBO Exit Valuation'!$G$7 -> 7 | D16: =IFERROR((SUM(G16:K16)/-F16),"NM") -> 2.4793501 | E16: =IFERROR(IRR(F16:K16),0) -> 0.1991336 | F16: =-LBO!$D$48 -> -19244.94 | G16: 0 | H16: =G16 -> 0 | I16: =H16 -> 0 | J16: =I16 -> 0 | K16: ='LBO Exit Valuation'!G19 -> 47714.944
B17: ='LBO Exit Valuation'!$H$7 -> 7.5 | D17: =IFERROR((SUM(G17:K17)/-F17),"NM") -> 2.6847073 | E17: =IFERROR(IRR(F17:K17),0) -> 0.21837054 | F17: =-LBO!$D$48 -> -19244.94 | G17: =G16 -> 0 | H17: =H16 -> 0 | I17: =I16 -> 0 | J17: =J16 -> 0 | K17: ='LBO Exit Valuation'!H19 -> 51667.031
B18: ='LBO Exit Valuation'!$I$7 -> 8 | D18: =IFERROR((SUM(G18:K18)/-F18),"NM") -> 2.8900646 | E18: =IFERROR(IRR(F18:K18),0) -> 0.23646409 | F18: =-LBO!$D$48 -> -19244.94 | G18: =G17 -> 0 | H18: =H17 -> 0 | I18: =I17 -> 0 | J18: =J17 -> 0 | K18: ='LBO Exit Valuation'!I19 -> 55619.119
B19: ='LBO Exit Valuation'!$J$7 -> 8.5 | D19: =IFERROR((SUM(G19:K19)/-F19),"NM") -> 3.0954218 | E19: =IFERROR(IRR(F19:K19),0) -> 0.25355666 | F19: =-LBO!$D$48 -> -19244.94 | G19: =G18 -> 0 | H19: =H18 -> 0 | I19: =I18 -> 0 | J19: =J18 -> 0 | K19: ='LBO Exit Valuation'!J19 -> 59571.207
B20: ='LBO Exit Valuation'!$K$7 -> 9 | D20: =IFERROR((SUM(G20:K20)/-F20),"NM") -> 3.300779 | E20: =IFERROR(IRR(F20:K20),0) -> 0.26976482 | F20: =-LBO!$D$48 -> -19244.94 | G20: =G19 -> 0 | H20: =H19 -> 0 | I20: =I19 -> 0 | J20: =J19 -> 0 | K20: ='LBO Exit Valuation'!K19 -> 63523.294
B23: Sensitivity Analysis
D24: Actual | F24: Offer Price / Share At Various Sponsor Hurdle Rates
B25: Sponsor Hurdle Rate (Minimum IRR) | F25: 0.15 | G25: =F25+0.05 -> 0.2 | H25: =G25+0.05 -> 0.25 | I25: =H25+0.05 -> 0.3 | J25: =I25+0.05 -> 0.35 | K25: =J25+0.05 -> 0.4
B26: Offer value | D26: =LBO!E28 -> 46303 | F26: =-PV(F25,5,0,'LBO Exit Valuation'!$G$19)-LBO!$D$36-LBO!$D$37+LBO!$D$42+SUM(LBO!$D$43:$D$47) -> 50780.82 | G26: =-PV(G25,5,0,'LBO Exit Valuation'!$G$19)-LBO!$D$36-LBO!$D$37+LBO!$D$42+SUM(LBO!$D$43:$D$47) -> 46233.626 | H26: =-PV(H25,5,0,'LBO Exit Valuation'!$G$19)-LBO!$D$36-LBO!$D$37+LBO!$D$42+SUM(LBO!$D$43:$D$47) -> 42693.293 | I26: =-PV(I25,5,0,'LBO Exit Valuation'!$G$19)-LBO!$D$36-LBO!$D$37+LBO!$D$42+SUM(LBO!$D$43:$D$47) -> 39909.082 | J26: =-PV(J25,5,0,'LBO Exit Valuation'!$G$19)-LBO!$D$36-LBO!$D$37+LBO!$D$42+SUM(LBO!$D$43:$D$47) -> 37699.137 | K26: =-PV(K25,5,0,'LBO Exit Valuation'!$G$19)-LBO!$D$36-LBO!$D$37+LBO!$D$42+SUM(LBO!$D$43:$D$47) -> 35929.911
B27: Diluted shares outstanding | D27: =Assumptions!N9+Assumptions!N11 -> 952.421 | F27: =$D$27 -> 952.421 | G27: =$D$27 -> 952.421 | H27: =$D$27 -> 952.421 | I27: =$D$27 -> 952.421 | J27: =$D$27 -> 952.421 | K27: =$D$27 -> 952.421
B28: Offer value / per share | D28: =D26/D27 -> 48.616106 | F28: =F26/F27 -> 53.317619 | G28: =G26/G27 -> 48.543266 | H28: =H26/H27 -> 44.826073 | I28: =I26/I27 -> 41.902774 | J28: =J26/J27 -> 39.582429 | K28: =K26/K27 -> 37.72482
B29: % Premium / discount | D29: =(D28/LBO!E9)-1 -> 0.0691908 | F29: =(F28/LBO!$E$9)-1 -> 0.17258894 | G29: =(G28/LBO!$E$9)-1 -> 0.067588868 | H29: =(H28/LBO!$E$9)-1 -> -0.01416159 | I29: =(I28/LBO!$E$9)-1 -> -0.078452304 | J29: =(J28/LBO!$E$9)-1 -> -0.12948254 | K29: =(K28/LBO!$E$9)-1 -> -0.17033604
B31: Enterprise value | D31: =D26-LBO!E11-LBO!E12 -> 47264 | F31: =F26-LBO!$E$11-LBO!$E$12 -> 51741.82 | G31: =G26-LBO!$E$11-LBO!$E$12 -> 47194.626 | H31: =H26-LBO!$E$11-LBO!$E$12 -> 43654.293 | I31: =I26-LBO!$E$11-LBO!$E$12 -> 40870.082 | J31: =J26-LBO!$E$11-LBO!$E$12 -> 38660.137 | K31: =K26-LBO!$E$11-LBO!$E$12 -> 36890.911
B32: EV / LTM EBITDA multiple | D32: =D31/LBO!E10 -> 7 | F32: =F31/LBO!$E$10 -> 7.6631842 | G32: =G31/LBO!$E$10 -> 6.9897254 | H32: =H31/LBO!$E$10 -> 6.465387 | I32: =I31/LBO!$E$10 -> 6.0530334 | J32: =J31/LBO!$E$10 -> 5.7257312 | K32: =K31/LBO!$E$10 -> 5.4637013

Sheet Sources
O1: ="CURRENTLY RUNNING: "&UPPER(CHOOSE(Scenarios!$C$6,Scenarios!B10,Scenarios!B11,Scenarios!B12))&" SCENARIO" -> CURRENTLY RUNNING: BASE CASE SCENARIO
B2: PayPal
B3: Sources
B4: Primary sources (company SEC / regulatory filings and press releases) except where noted; market data via Koyfin. Precedent-transaction sources are also attached as
B5: comments on the relevant cells in the Precedents tab.
B7: PayPal (Target) — Company Financials & Market Data
B9: PayPal FY2025 Form 10-K (SEC EDGAR, period ended 12/31/2025)
C10: Supports: revenue, TPV, customer-funds balances & yields, EBITDA, balance sheet, capex, D&A and working-capital inputs
C11: Used across: the Revenue Build, IS, BS, CFS, Assumptions, DCF and LBO tabs
C12: Key information: debt maturity / repayment schedule (p. 105);
C13: minimum-cash & money-transmitter licensing constraints (pp. 10, 44); diluted shares outstanding (cover page, as of 1/28/2026)
B15: PayPal (NASDAQ: PYPL) — share price $45.47 and 52-week range $38.46–$79.50, as of 7/1/2026 (Koyfin)
B17: Comparable Companies (Comps)
B19: Koyfin — market value, enterprise value, revenue and EBITDA for Block, Adyen, Fiserv, Global Payments,
B20: Fidelity National Information Services (FIS) and Shift4, as of 7/1/2026
B22: Valuation Inputs — DCF (WACC & Terminal Value)
B24: Risk-free rate (4.37%) — U.S. 10-Year Treasury yield (U.S. Department of the Treasury)
B25: Equity beta (1.34) — Koyfin
B26: Equity risk premium (5.0%) — model assumption (long-run U.S. equity premium)
B28: Precedent Transactions
B30: Worldpay / Global Payments — announced 4/17/2025, completed 1/9/2026
B32: Global Payments press release — agreements to acquire Worldpay (4/17/2025)
B33: SEC 8-K (EX-99.1) — deal terms; $600M cost / $200M revenue synergies
... B74: Fortune (news) — Honey FY2018 revenue >$100M / >100% growth (PayPal-disclosed)
